Workbook

Sheet All_India_Index_Upto_April23 (1
A1: Sector | B1: Year | C1: Month | D1: Date | E1: Cereals and products | F1: Meat and fish | G1: Egg | H1: Milk and products | I1: Oils and fats | J1: Fruits | K1: Vegetables | L1: Pulses and products | M1: Sugar and Confectionery | N1: Spices | O1: Non-alcoholic beverages | P1: Prepared meals, snacks, sweets etc. | Q1: Food and beverages | R1: Pan, tobacco and intoxicants | S1: Clothing | T1: Footwear | U1: Clothing and footwear | V1: Housing | W1: Fuel and light | X1: Household goods and services | Y1: Health | Z1: Transport and communication | AA1: Recreation and amusement | AB1: Education | AC1: Personal care and effects | AD1: Miscellaneous | AE1: General index
A2: Rural | B2: 2013 | C2: January | D2: =DATE(All_India_Index_Upto_April23__1___1[[#This Row],[Year]],MATCH(All_India_Index_Upto_April23__1___1[[#This Row],[Month]],{"January","February","March","April","May","June","July","August","September","October","November","December"},0),1) -> 41275 | E2: 107.5 | F2: 106.3 | G2: 108.1 | H2: 104.9 | I2: 106.1 | J2: 103.9 | K2: 101.9 | L2: 106.1 | M2: 106.8 | N2: 103.1 | O2: 104.8 | P2: 106.7 | Q2: 105.5 | R2: 105.1 | S2: 106.5 | T2: 105.8 | U2: 106.4 | W2: 105.5 | X2: 104.8 | Y2: 104 | Z2: 103.3 | AA2: 103.4 | AB2: 103.8 | AC2: 104.7 | AD2: 104 | AE2: 105.1
A3: Urban | B3: 2013 | C3: January | D3: =DATE(All_India_Index_Upto_April23__1___1[[#This Row],[Year]],MATCH(All_India_Index_Upto_April23__1___1[[#This Row],[Month]],{"January","February","March","April","May","June","July","August","September","October","November","December"},0),1) -> 41275 | E3: 110.5 | F3: 109.1 | G3: 113 | H3: 103.6 | I3: 103.4 | J3: 102.3 | K3: 102.9 | L3: 105.8 | M3: 105.1 | N3: 101.8 | O3: 105.1 | P3: 107.9 | Q3: 105.9 | R3: 105.2 | S3: 105.9 | T3: 105 | U3: 105.8 | V3: 100.3 | W3: 105.4 | X3: 104.8 | Y3: 104.1 | Z3: 103.2 | AA3: 102.9 | AB3: 103.5 | AC3: 104.3 | AD3: 103.7 | AE3: 104
A4: Rural | B4: 2013 | C4: February | D4: =DATE(All_India_Index_Upto_April23__1___1[[#This Row],[Year]],MATCH(All_India_Index_Upto_April23__1___1[[#This Row],[Month]],{"January","February","March","April","May","June","July","August","September","October","November","December"},0),1) -> 41306 | E4: 109.2 | F4: 108.7 | G4: 110.2 | H4: 105.4 | I4: 106.7 | J4: 104 | K4: 102.4 | L4: 105.9 | M4: 105.7 | N4: 103.1 | O4: 105.1 | P4: 107.7 | Q4: 106.3 | R4: 105.6 | S4: 107.1 | T4: 106.3 | U4: 107 | W4: 106.2 | X4: 105.2 | Y4: 104.4 | Z4: 103.9 | AA4: 104 | AB4: 104.1 | AC4: 104.6 | AD4: 104.4 | AE4: 105.8
A5: Urban | B5: 2013 | C5: February | D5: =DATE(All_India_Index_Upto_April23__1___1[[#This Row],[Year]],MATCH(All_India_Index_Upto_April23__1___1[[#This Row],[Month]],{"January","February","March","April","May","June","July","August","September","October","November","December"},0),1) -> 41306 | E5: 112.9 | F5: 112.9 | G5: 116.9 | H5: 104 | I5: 103.5 | J5: 103.1 | K5: 104.9 | L5: 104.1 | M5: 103.8 | N5: 102.3 | O5: 106 | P5: 109 | Q5: 107.2 | R5: 106 | S5: 106.6 | T5: 105.5 | U5: 106.4 | V5: 100.4 | W5: 105.7 | X5: 105.2 | Y5: 104.7 | Z5: 104.4 | AA5: 103.3 | AB5: 103.7 | AC5: 104.3 | AD5: 104.3 | AE5: 104.7
A6: Rural | B6: 2013 | C6: March | D6: =DATE(All_India_Index_Upto_April23__1___1[[#This Row],[Year]],MATCH(All_India_Index_Upto_April23__1___1[[#This Row],[Month]],{"January","February","March","April","May","June","July","August","September","October","November","December"},0),1) -> 41334 | E6: 110.2 | F6: 108.8 | G6: 109.9 | H6: 105.6 | I6: 106.2 | J6: 105.7 | K6: 101.4 | L6: 105.7 | M6: 105 | N6: 103.3 | O6: 105.6 | P6: 108.2 | Q6: 106.6 | R6: 106.5 | S6: 107.6 | T6: 106.8 | U6: 107.5 | W6: 106.1 | X6: 105.6 | Y6: 104.7 | Z6: 104.6 | AA6: 104 | AB6: 104.3 | AC6: 104.3 | AD6: 104.6 | AE6: 106
A7: Urban | B7: 2013 | C7: March | D7: =DATE(All_India_Index_Upto_April23__1___1[[#This Row],[Year]],MATCH(All_India_Index_Upto_April23__1___1[[#This Row],[Month]],{"January","February","March","April","May","June","July","August","September","October","November","December"},0),1) -> 41334 | E7: 113.9 | F7: 111.4 | G7: 113.2 | H7: 104.3 | I7: 102.7 | J7: 104.9 | K7: 103.8 | L7: 103.5 | M7: 102.6 | N7: 102.4 | O7: 107 | P7: 109.8 | Q7: 107.3 | R7: 106.8 | S7: 107.2 | T7: 106 | U7: 107 | V7: 100.4 | W7: 106 | X7: 105.7 | Y7: 105.2 | Z7: 105.5 | AA7: 103.5 | AB7: 103.8 | AC7: 104.2 | AD7: 104.9 | AE7: 105
A8: Rural | B8: 2013 | C8: April | D8: =DATE(All_India_Index_Upto_April23__1___1[[#This Row],[Year]],MATCH(All_India_Index_Upto_April23__1___1[[#This Row],[Month]],{"January","February","March","April","May","June","July","August","September","October","November","December"},0),1) -> 41365 | E8: 110.2 | F8: 109.5 | G8: 106.9 | H8: 106.3 | I8: 105.7 | J8: 108.3 | K8: 103.4 | L8: 105.7 | M8: 104.2 | N8: 103.2 | O8: 106.5 | P8: 108.8 | Q8: 107.1 | R8: 107.1 | S8: 108.1 | T8: 107.4 | U8: 108 | W8: 106.5 | X8: 106.1 | Y8: 105.1 | Z8: 104.4 | AA8: 104.5 | AB8: 104.8 | AC8: 102.7 | AD8: 104.6 | AE8: 106.4
A9: Urban | B9: 2013 | C9: April | D9: =DATE(All_India_Index_Upto_April23__1___1[[#This Row],[Year]],MATCH(All_India_Index_Upto_April23__1___1[[#This Row],[Month]],{"January","February","March","April","May","June","July","August","September","October","November","December"},0),1) -> 41365 | E9: 114.6 | F9: 113.4 | G9: 106 | H9: 104.7 | I9: 102.1 | J9: 109.5 | K9: 109.7 | L9: 104.6 | M9: 102 | N9: 103.5 | O9: 108.2 | P9: 110.6 | Q9: 108.8 | R9: 108.5 | S9: 107.9 | T9: 106.4 | U9: 107.7 | V9: 100.5 | W9: 106.4 | X9: 106.5 | Y9: 105.7 | Z9: 105 | AA9: 104 | AB9: 105.2 | AC9: 103.2 | AD9: 105.1 | AE9: 105.7
A10: Rural | B10: 2013 | C10: May | D10: =DATE(All_India_Index_Upto_April23__1___1[[#This Row],[Year]],MATCH(All_India_Index_Upto_April23__1___1[[#This Row],[Month]],{"January","February","March","April","May","June","July","August","September","October","November","December"},0),1) -> 41395 | E10: 110.9 | F10: 109.8 | G10: 105.9 | H10: 107.5 | I10: 105.3 | J10: 108.1 | K10: 107.3 | L10: 106.1 | M10: 103.7 | N10: 104 | O10: 107.4 | P10: 109.9 | Q10: 108.1 | R10: 108.1 | S10: 108.8 | T10: 107.9 | U10: 108.6 | W10: 107.5 | X10: 106.8 | Y10: 105.7 | Z10: 104.1 | AA10: 105 | AB10: 105.5 | AC10: 102.1 | AD10: 104.8 | AE10: 107.2
A11: Urban | B11: 2013 | C11: May | D11: =DATE(All_India_Index_Upto_April23__1___1[[#This Row],[Year]],MATCH(All_India_Index_Upto_April23__1___1[[#This Row],[Month]],{"January","February","March","April","May","June","July","August","September","October","November","December"},0),1) -> 41395 | E11: 115.4 | F11: 114.2 | G11: 102.7 | H11: 105.5 | I11: 101.5 | J11: 110.6 | K11: 123.7 | L11: 105.2 | M11: 101.9 | N11: 105 | O11: 109.1 | P11: 111.3 | Q11: 111.1 | R11: 109.8 | S11: 108.5 | T11: 106.7 | U11: 108.3 | V11: 100.5 | W11: 107.2 | X11: 107.1 | Y11: 106.2 | Z11: 103.9 | AA11: 104.6 | AB11: 105.7 | AC11: 102.6 | AD11: 104.9 | AE11: 106.6
A12: Rural | B12: 2013 | C12: June | D12: =DATE(All_India_Index_Upto_April23__1___1[[#This Row],[Year]],MATCH(All_India_Index_Upto_April23__1___1[[#This Row],[Month]],{"January","February","March","April","May","June","July","August","September","October","November","December"},0),1) -> 41426 | E12: 112.3 | F12: 112.1 | G12: 108.1 | H12: 108.3 | I12: 105.9 | J12: 109.2 | K12: 118 | L12: 106.8 | M12: 104.1 | N12: 105.4 | O12: 108.2 | P12: 111 | Q12: 110.6 | R12: 109 | S12: 109.7 | T12: 108.8 | U12: 109.5 | W12: 108.5 | X12: 107.5 | Y12: 106.3 | Z12: 105 | AA12: 105.6 | AB12: 106.5 | AC12: 102.5 | AD12: 105.5 | AE12: 108.9
A13: Urban | B13: 2013 | C13: June | D13: =DATE(All_India_Index_Upto_April23__1___1[[#This Row],[Year]],MATCH(All_India_Index_Upto_April23__1___1[[#This Row],[Month]],{"January","February","March","April","May","June","July","August","September","October","November","December"},0),1) -> 41426 | E13: 117 | F13: 120.1 | G13: 112.5 | H13: 107.3 | I13: 101.3 | J13: 112.4 | K13: 143.6 | L13: 105.4 | M13: 101.4 | N13: 106.4 | O13: 110 | P13: 112.2 | Q13: 115 | R13: 110.9 | S13: 109.2 | T13: 107.2 | U13: 108.9 | V13: 106.6 | W13: 108 | X13: 107.7 | Y13: 106.5 | Z13: 105.2 | AA13: 105.2 | AB13: 108.1 | AC13: 103.3 | AD13: 106.1 | AE13: 109.7
A14: Rural | B14: 2013 | C14: July | D14: =DATE(All_India_Index_Upto_April23__1___1[[#This Row],[Year]],MATCH(All_India_Index_Upto_April23__1___1[[#This Row],[Month]],{"January","February","March","April","May","June","July","August","September","October","November","December"},0),1) -> 41456 | E14: 113.4 | F14: 114.9 | G14: 110.5 | H14: 109.3 | I14: 106.2 | J14: 110.3 | K14: 129.2 | L14: 107.1 | M14: 104.3 | N14: 106.4 | O14: 109.1 | P14: 112.1 | Q14: 113.1 | R14: 109.8 | S14: 110.5 | T14: 109.5 | U14: 110.3 | W14: 109.5 | X14: 108.3 | Y14: 106.9 | Z14: 106.8 | AA14: 106.4 | AB14: 107.8 | AC14: 102.5 | AD14: 106.5 | AE14: 110.7
A15: Urban | B15: 2013 | C15: July | D15: =DATE(All_India_Index_Upto_April23__1___1[[#This Row],[Year]],MATCH(All_India_Index_Upto_April23__1___1[[#This Row],[Month]],{"January","February","March","April","May","June","July","August","September","October","November","December"},0),1) -> 41456 | E15: 117.8 | F15: 119.2 | G15: 114 | H15: 108.3 | I15: 101.1 | J15: 113.2 | K15: 160.9 | L15: 105.1 | M15: 101.3 | N15: 107.5 | O15: 110.4 | P15: 113.1 | Q15: 117.5 | R15: 111.7 | S15: 109.8 | T15: 107.8 | U15: 109.5 | V15: 107.7 | W15: 108.6 | X15: 108.1 | Y15: 107.1 | Z15: 107.3 | AA15: 105.9 | AB15: 110.1 | AC15: 103.2 | AD15: 107.3 | AE15: 111.4
A16: Rural | B16: 2013 | C16: August | D16: =DATE(All_India_Index_Upto_April23__1___1[[#This Row],[Year]],MATCH(All_India_Index_Upto_April23__1___1[[#This Row],[Month]],{"January","February","March","April","May","June","July","August","September","October","November","December"},0),1) -> 41487 | E16: 114.3 | F16: 115.4 | G16: 111.1 | H16: 110 | I16: 106.4 | J16: 110.8 | K16: 138.9 | L16: 107.4 | M16: 104.1 | N16: 106.9 | O16: 109.7 | P16: 112.6 | Q16: 114.9 | R16: 110.7 | S16: 111.3 | T16: 110.2 | U16: 111.1 | W16: 109.9 | X16: 108.7 | Y16: 107.5 | Z16: 107.8 | AA16: 106.8 | AB16: 108.7 | AC16: 105 | AD16: 107.5 | AE16: 112.1
A17: Urban | B17: 2013 | C17: August | D17: =DATE(All_India_Index_Upto_April23__1___1[[#This Row],[Year]],MATCH(All_India_Index_Upto_April23__1___1[[#This Row],[Month]],{"January","February","March","April","May","June","July","August","September","October","November","December"},0),1) -> 41487 | E17: 118.3 | F17: 120.4 | G17: 112.7 | H17: 108.9 | I17: 101.1 | J17: 108.7 | K17: 177 | L17: 104.7 | M17: 101 | N17: 108.5 | O17: 110.9 | P17: 114.3 | Q17: 119.6 | R17: 112.4 | S17: 110.6 | T17: 108.3 | U17: 110.2 | V17: 108.9 | W17: 109.3 | X17: 108.7 | Y17: 107.6 | Z17: 108.1 | AA17: 106.5 | AB17: 110.8 | AC17: 106 | AD17: 108.3 | AE17: 112.7
A18: Rural | B18: 2013 | C18: September | D18: =DATE(All_India_Index_Upto_April23__1___1[[#This Row],[Year]],MATCH(All_India_Index_Upto_April23__1___1[[#This Row],[Month]],{"January","February","March","April","May","June","July","August","September","October","November","December"},0),1) -> 41518 | E18: 115.4 | F18: 115.7 | G18: 111.7 | H18: 111 | I18: 107.4 | J18: 110.9 | K18: 154 | L18: 108.1 | M18: 104.2 | N18: 107.9 | O18: 110.4 | P18: 114 | Q18: 117.8 | R18: 111.7 | S18: 112.7 | T18: 111.4 | U18: 112.5 | W18: 111.1 | X18: 109.6 | Y18: 108.3 | Z18: 109.3 | AA18: 107.7 | AB18: 109.8 | AC18: 106.7 | AD18: 108.7 | AE18: 114.2
A19: Urban | B19: 2013 | C19: September | D19: =DATE(All_India_Index_Upto_April23__1___1[[#This Row],[Year]],MATCH(All_India_Index_Upto_April23__1___1[[#This Row],[Month]],{"January","February","March","April","May","June","July","August","September","October","November","December"},0),1) -> 41518 | E19: 118.6 | F19: 119.1 | G19: 113.2 | H19: 109.6 | I19: 101.7 | J19: 103.2 | K19: 174.3 | L19: 105.1 | M19: 100.8 | N19: 109.1 | O19: 111.1 | P19: 115.4 | Q19: 119.2 | R19: 112.9 | S19: 111.4 | T19: 109 | U19: 111.1 | V19: 109.7 | W19: 109.5 | X19: 109.6 | Y19: 107.9 | Z19: 110.4 | AA19: 107.4 | AB19: 111.2 | AC19: 106.9 | AD19: 109.4 | AE19: 113.2
A20: Rural | B20: 2013 | C20: October | D20: =DATE(All_India_Index_Upto_April23__1___1[[#This Row],[Year]],MATCH(All_India_Index_Upto_April23__1___1[[#This Row],[Month]],{"January","February","March","April","May","June","July","August","September","October","November","December"},0),1) -> 41548 | E20: 116.3 | F20: 115.4 | G20: 112.6 | H20: 111.7 | I20: 107.7 | J20: 113.2 | K20: 164.9 | L20: 108.3 | M20: 103.9 | N20: 108.2 | O20: 111.1 | P20: 114.9 | Q20: 119.8 | R20: 112.2 | S20: 113.6 | T20: 112.3 | U20: 113.4 | W20: 111.6 | X20: 110.4 | Y20: 108.9 | Z20: 109.3 | AA20: 108.3 | AB20: 110.2 | AC20: 107.5 | AD20: 109.1 | AE20: 115.5
A21: Urban | B21: 2013 | C21: October | D21: =DATE(All_India_Index_Upto_April23__1___1[[#This Row],[Year]],MATCH(All_India_Index_Upto_April23__1___1[[#This Row],[Month]],{"January","February","March","April","May","June","July","August","September","October","November","December"},0),1) -> 41548 | E21: 118.9 | F21: 118.1 | G21: 114.5 | H21: 110.4 | I21: 102.3 | J21: 106.2 | K21: 183.5 | L21: 105.3 | M21: 100.2 | N21: 109.6 | O21: 111.4 | P21: 116 | Q21: 120.8 | R21: 113.5 | S21: 112.5 | T21: 109.7 | U21: 112 | V21: 110.5 | W21: 109.7 | X21: 110.2 | Y21: 108.2 | Z21: 109.7 | AA21: 108 | AB21: 111.3 | AC21: 107.3 | AD21: 109.4 | AE21: 114
A22: Urban | B22: 2013 | C22: November | D22: =DATE(All_India_Index_Upto_April23__1___1[[#This Row],[Year]],MATCH(All_India_Index_Upto_April23__1___1[[#This Row],[Month]],{"January","February","March","April","May","June","July","August","September","October","November","December"},0),1) -> 41579 | E22: 119.8 | F22: 116.3 | G22: 122.6 | H22: 112 | I22: 103.2 | J22: 110 | K22: 192.8 | L22: 106.3 | M22: 99.5 | N22: 110.3 | O22: 111.8 | P22: 117.1 | Q22: 122.9 | R22: 114.1 | S22: 113.5 | T22: 110.3 | U22: 113 | V22: 111.1 | W22: 110 | X22: 110.9 | Y22: 108.6 | Z22: 109.5 | AA22: 108.5 | AB22: 111.3 | AC22: 107.9 | AD22: 109.6 | AE22: 115
A23: Rural | B23: 2013 | C23: November | D23: =DATE(All_India_Index_Upto_April23__1___1[[#This Row],[Year]],MATCH(All_India_Index_Upto_April23__1___1[[#This Row],[Month]],{"January","February","March","April","May","June","July","August","September","October","November","December"},0),1) -> 41579 | E23: 117.3 | F23: 114.9 | G23: 116.2 | H23: 112.8 | I23: 108.9 | J23: 116.6 | K23: 178.1 | L23: 109.1 | M23: 103.6 | N23: 109 | O23: 111.8 | P23: 116 | Q23: 122.5 | R23: 112.8 | S23: 114.6 | T23: 113.1 | U23: 114.4 | W23: 112.6 | X23: 111.3 | Y23: 109.7 | Z23: 109.6 | AA23: 108.7 | AB23: 111 | AC23: 108.2 | AD23: 109.8 | AE23: 117.4
A24: Rural | B24: 2013 | C24: December | D24: =DATE(All_India_Index_Upto_April23__1___1[[#This Row],[Year]],MATCH(All_India_Index_Upto_April23__1___1[[#This Row],[Month]],{"January","February","March","April","May","June","July","August","September","October","November","December"},0),1) -> 41609 | E24: 118.4 | F24: 115.9 | G24: 120.4 | H24: 113.8 | I24: 109.5 | J24: 115.5 | K24: 145.7 | L24: 109.5 | M24: 102.9 | N24: 109.8 | O24: 112.1 | P24: 116.8 | Q24: 118.7 | R24: 113.6 | S24: 115.8 | T24: 114 | U24: 115.5 | W24: 112.8 | X24: 112.1 | Y24: 110.1 | Z24: 109.9 | AA24: 109.2 | AB24: 111.6 | AC24: 108.1 | AD24: 110.1 | AE24: 115.5
A25: Urban | B25: 2013 | C25: December | D25: =DATE(All_India_Index_Upto_April23__1___1[[#This Row],[Year]],MATCH(All_India_Index_Upto_April23__1___1[[#This Row],[Month]],{"January","February","March","April","May","June","July","August","September","October","November","December"},0),1) -> 41609 | E25: 120.5 | F25: 118.1 | G25: 128.5 | H25: 112.8 | I25: 103.4 | J25: 110.7 | K25: 144.8 | L25: 107.1 | M25: 98.6 | N25: 111.9 | O25: 112.1 | P25: 118.1 | Q25: 117.8 | R25: 115 | S25: 114.2 | T25: 110.9 | U25: 113.7 | V25: 110.7 | W25: 110.4 | X25: 111.3 | Y25: 109 | Z25: 109.7 | AA25: 108.9 | AB25: 111.4 | AC25: 107.7 | AD25: 109.8 | AE25: 113.3
A26: Rural+Urban | B26: 2013 | C26: January | D26: =DATE(All_India_Index_Upto_April23__1___1[[#This Row],[Year]],MATCH(All_India_Index_Upto_April23__1___1[[#This Row],[Month]],{"January","February","March","April","May","June","July","August","September","October","November","December"},0),1) -> 41275 | E26: 108.4 | F26: 107.3 | G26: 110 | H26: 104.4 | I26: 105.1 | J26: 103.2 | K26: 102.2 | L26: 106 | M26: 106.2 | N26: 102.7 | O26: 104.9 | P26: 107.3 | Q26: 105.6 | R26: 105.1 | S26: 106.3 | T26: 105.5 | U26: 106.2 | V26: 100.3 | W26: 105.5 | X26: 104.8 | Y26: 104 | Z26: 103.2 | AA26: 103.1 | AB26: 103.6 | AC26: 104.5 | AD26: 103.9 | AE26: 104.6
A27: Rural+Urban | B27: 2013 | C27: February | D27: =DATE(All_India_Index_Upto_April23__1___1[[#This Row],[Year]],MATCH(All_India_Index_Upto_April23__1___1[[#This Row],[Month]],{"January","February","March","April","May","June","July","August","September","October","November","December"},0),1) -> 41306 | E27: 110.4 | F27: 110.2 | G27: 112.8 | H27: 104.9 | I27: 105.5 | J27: 103.6 | K27: 103.2 | L27: 105.3 | M27: 105.1 | N27: 102.8 | O27: 105.5 | P27: 108.3 | Q27: 106.6 | R27: 105.7 | S27: 106.9 | T27: 106 | U27: 106.8 | V27: 100.4 | W27: 106 | X27: 105.2 | Y27: 104.5 | Z27: 104.2 | AA27: 103.6 | AB27: 103.9 | AC27: 104.5 | AD27: 104.4 | AE27: 105.3
A28: Rural+Urban | B28: 2013 | C28: March | D28: =DATE(All_India_Index_Upto_April23__1___1[[#This Row],[Year]],MATCH(All_India_Index_Upto_April23__1___1[[#This Row],[Month]],{"January","February","March","April","May","June","July","August","September","October","November","December"},0),1) -> 41334 | E28: 111.4 | F28: 109.7 | G28: 111.2 | H28: 105.1 | I28: 104.9 | J28: 105.3 | K28: 102.2 | L28: 105 | M28: 104.2 | N28: 103 | O28: 106.2 | P28: 108.9 | Q28: 106.9 | R28: 106.6 | S28: 107.4 | T28: 106.5 | U28: 107.3 | V28: 100.4 | W28: 106.1 | X28: 105.6 | Y28: 104.9 | Z28: 105.1 | AA28: 103.7 | AB28: 104 | AC28: 104.3 | AD28: 104.7 | AE28: 105.5
A29: Rural+Urban | B29: 2013 | C29: April | D29: =DATE(All_India_Index_Upto_April23__1___1[[#This Row],[Year]],MATCH(All_India_Index_Upto_April23__1___1[[#This Row],[Month]],{"January","February","March","April","May","June","July","August","September","October","November","December"},0),1) -> 41365 | E29: 111.6 | F29: 110.9 | G29: 106.6 | H29: 105.7 | I29: 104.4 | J29: 108.9 | K29: 105.5 | L29: 105.3 | M29: 103.5 | N29: 103.3 | O29: 107.2 | P29: 109.6 | Q29: 107.7 | R29: 107.5 | S29: 108 | T29: 107 | U29: 107.9 | V29: 100.5 | W29: 106.5 | X29: 106.3 | Y29: 105.3 | Z29: 104.7 | AA29: 104.2 | AB29: 105 | AC29: 102.9 | AD29: 104.8 | AE29: 106.1
A30: Rural+Urban | B30: 2013 | C30: May | D30: =DATE(All_India_Index_Upto_April23__1___1[[#This Row],[Year]],MATCH(All_India_Index_Upto_April23__1___1[[#This Row],[Month]],{"January","February","March","April","May","June","July","August","September","October","November","December"},0),1) -> 41395 | E30: 112.3 | F30: 111.3 | G30: 104.7 | H30: 106.8 | I30: 103.9 | J30: 109.3 | K30: 112.9 | L30: 105.8 | M30: 103.1 | N30: 104.3 | O30: 108.1 | P30: 110.5 | Q30: 109.2 | R30: 108.6 | S30: 108.7 | T30: 107.4 | U30: 108.5 | V30: 100.5 | W30: 107.4 | X30: 106.9 | Y30: 105.9 | Z30: 104 | AA30: 104.8 | AB30: 105.6 | AC30: 102.3 | AD30: 104.8 | AE30: 106.9
A31: Rural+Urban | B31: 2013 | C31: June | D31: =DATE(All_India_Index_Upto_April23__1___1[[#This Row],[Year]],MATCH(All_India_Index_Upto_April23__1___1[[#This Row],[Month]],{"January","February","March","April","May","June","July","August","September","October","November","December"},0),1) -> 41426 | E31: 113.8 | F31: 114.9 | G31: 109.8 | H31: 107.9 | I31: 104.2 | J31: 110.7 | K31: 126.7 | L31: 106.3 | M31: 103.2 | N31: 105.7 | O31: 109 | P31: 111.6 | Q31: 112.2 | R31: 109.5 | S31: 109.5 | T31: 108.1 | U31: 109.3 | V31: 106.6 | W31: 108.3 | X31: 107.6 | Y31: 106.4 | Z31: 105.1 | AA31: 105.4 | AB31: 107.4 | AC31: 102.8 | AD31: 105.8 | AE31: 109.3
A32: Rural+Urban | B32: 2013 | C32: July | D32: =DATE(All_India_Index_Upto_April23__1___1[[#This Row],[Year]],MATCH(All_India_Index_Upto_April23__1___1[[#This Row],[Month]],{"January","February","March","April","May","June","July","August","September","October","November","December"},0),1) -> 41456 | E32: 114.8 | F32: 116.4 | G32: 111.9 | H32: 108.9 | I32: 104.3 | J32: 111.7 | K32: 140 | L32: 106.4 | M32: 103.3 | N32: 106.8 | O32: 109.6 | P32: 112.6 | Q32: 114.7 | R32: 110.3 | S32: 110.2 | T32: 108.8 | U32: 110 | V32: 107.7 | W32: 109.2 | X32: 108.2 | Y32: 107 | Z32: 107.1 | AA32: 106.1 | AB32: 109.1 | AC32: 102.8 | AD32: 106.9 | AE32: 111
A33: Rural+Urban | B33: 2013 | C33: August | D33: =DATE(All_India_Index_Upto_April23__1___1[[#This Row],[Year]],MATCH(All_India_Index_Upto_April23__1___1[[#This Row],[Month]],{"January","February","March","April","May","June","July","August","September","October","November","December"},0),1) -> 41487 | E33: 115.6 | F33: 117.2 | G33: 111.7 | H33: 109.6 | I33: 104.5 | J33: 109.8 | K33: 151.8 | L33: 106.5 | M33: 103.1 | N33: 107.4 | O33: 110.2 | P33: 113.4 | Q33: 116.6 | R33: 111.2 | S33: 111 | T33: 109.4 | U33: 110.7 | V33: 108.9 | W33: 109.7 | X33: 108.7 | Y33: 107.5 | Z33: 108 | AA33: 106.6 | AB33: 109.9 | AC33: 105.4 | AD33: 107.9 | AE33: 112.4
A34: Rural+Urban | B34: 2013 | C34: September | D34: =DATE(All_India_Index_Upto_April23__1___1[[#This Row],[Year]],MATCH(All_India_Index_Upto_April23__1___1[[#This Row],[Month]],{"January","February","March","April","May","June","July","August","September","October","November","December"},0),1) -> 41518 | E34: 116.4 | F34: 116.9 | G34: 112.3 | H34: 110.5 | I34: 105.3 | J34: 107.3 | K34: 160.9 | L34: 107.1 | M34: 103.1 | N34: 108.3 | O34: 110.7 | P34: 114.6 | Q34: 118.3 | R34: 112 | S34: 112.2 | T34: 110.4 | U34: 111.9 | V34: 109.7 | W34: 110.5 | X34: 109.6 | Y34: 108.1 | Z34: 109.9 | AA34: 107.5 | AB34: 110.6 | AC34: 106.8 | AD34: 109 | AE34: 113.7
A35: Rural+Urban | B35: 2013 | C35: October | D35: =DATE(All_India_Index_Upto_April23__1___1[[#This Row],[Year]],MATCH(All_India_Index_Upto_April23__1___1[[#This Row],[Month]],{"January","February","March","April","May","June","July","August","September","October","November","December"},0),1) -> 41548 | E35: 117.1 | F35: 116.3 | G35: 113.3 | H35: 111.2 | I35: 105.7 | J35: 109.9 | K35: 171.2 | L35: 107.3 | M35: 102.7 | N35: 108.7 | O35: 111.2 | P35: 115.4 | Q35: 120.2 | R35: 112.5 | S35: 113.2 | T35: 111.2 | U35: 112.8 | V35: 110.5 | W35: 110.9 | X35: 110.3 | Y35: 108.6 | Z35: 109.5 | AA35: 108.1 | AB35: 110.8 | AC35: 107.4 | AD35: 109.2 | AE35: 114.8
A36: Rural+Urban | B36: 2013 | C36: November | D36: =DATE(All_India_Index_Upto_April23__1___1[[#This Row],[Year]],MATCH(All_India_Index_Upto_April23__1___1[[#This Row],[Month]],{"January","February","March","April","May","June","July","August","September","October","November","December"},0),1) -> 41579 | E36: 118.1 | F36: 115.4 | G36: 118.7 | H36: 112.5 | I36: 106.8 | J36: 113.5 | K36: 183.1 | L36: 108.2 | M36: 102.2 | N36: 109.4 | O36: 111.8 | P36: 116.5 | Q36: 122.6 | R36: 113.1 | S36: 114.2 | T36: 111.9 | U36: 113.8 | V36: 111.1 | W36: 111.6 | X36: 111.1 | Y36: 109.3 | Z36: 109.5 | AA36: 108.6 | AB36: 111.2 | AC36: 108.1 | AD36: 109.7 | AE36: 116.3
A37: Rural+Urban | B37: 2013 | C37: December | D37: =DATE(All_India_Index_Upto_April23__1___1[[#This Row],[Year]],MATCH(All_India_Index_Upto_April23__1___1[[#This Row],[Month]],{"January","February","March","April","May","June","July","August","September","October","November","December"},0),1) -> 41609 | E37: 119.1 | F37: 116.7 | G37: 123.5 | H37: 113.4 | I37: 107.3 | J37: 113.3 | K37: 145.4 | L37: 108.7 | M37: 101.5 | N37: 110.5 | O37: 112.1 | P37: 117.4 | Q37: 118.4 | R37: 114 | S37: 115.2 | T37: 112.7 | U37: 114.8 | V37: 110.7 | W37: 111.9 | X37: 111.7 | Y37: 109.7 | Z37: 109.8 | AA37: 109 | AB37: 111.5 | AC37: 107.9 | AD37: 110 | AE37: 114.5
A38: Rural | B38: 2014 | C38: January | D38: =DATE(All_India_Index_Upto_April23__1___1[[#This Row],[Year]],MATCH(All_India_Index_Upto_April23__1___1[[#This Row],[Month]],{"January","February","March","April","May","June","July","August","September","October","November","December"},0),1) -> 41640 | E38: 118.9 | F38: 117.1 | G38: 120.5 | H38: 114.4 | I38: 109 | J38: 115.5 | K38: 123.9 | L38: 109.6 | M38: 101.8 | N38: 110.2 | O38: 112.4 | P38: 117.3 | Q38: 116 | R38: 114 | S38: 116.5 | T38: 114.5 | U38: 116.2 | W38: 113 | X38: 112.6 | Y38: 110.6 | Z38: 110.5 | AA38: 109.6 | AB38: 111.8 | AC38: 108.3 | AD38: 110.6 | AE38: 114.2
A39: Urban | B39: 2014 | C39: January | D39: =DATE(All_India_Index_Upto_April23__1___1[[#This Row],[Year]],MATCH(All_India_Index_Upto_April23__1___1[[#This Row],[Month]],{"January","February","March","April","May","June","July","August","September","October","November","December"},0),1) -> 41640 | E39: 121.2 | F39: 122 | G39: 129.9 | H39: 113.6 | I39: 102.9 | J39: 112.1 | K39: 118.9 | L39: 107.5 | M39: 96.9 | N39: 112.7 | O39: 112.1 | P39: 119 | Q39: 115.5 | R39: 115.7 | S39: 114.8 | T39: 111.3 | U39: 114.3 | V39: 111.6 | W39: 111 | X39: 111.9 | Y39: 109.7 | Z39: 110.8 | AA39: 109.8 | AB39: 111.5 | AC39: 108 | AD39: 110.5 | AE39: 112.9
A40: Rural | B40: 2014 | C40: February | D40: =DATE(All_India_Index_Upto_April23__1___1[[#This Row],[Year]],MATCH(All_India_Index_Upto_April23__1___1[[#This Row],[Month]],{"January","February","March","April","May","June","July","August","September","October","November","December"},0),1) -> 41671 | E40: 119.4 | F40: 117.7 | G40: 121.2 | H40: 115 | I40: 109 | J40: 116.6 | K40: 116 | L40: 109.8 | M40: 101.1 | N40: 110.4 | O40: 112.9 | P40: 117.8 | Q40: 115.3 | R40: 114.2 | S40: 117.1 | T40: 114.5 | U40: 116.7 | W40: 113.2 | X40: 112.9 | Y40: 110.9 | Z40: 110.8 | AA40: 109.9 | AB40: 112 | AC40: 108.7 | AD40: 110.9 | AE40: 114
A41: Urban | B41: 2014 | C41: February | D41: =DATE(All_India_Index_Upto_April23__1___1[[#This Row],[Year]],MATCH(All_India_Index_Upto_April23__1___1[[#This Row],[Month]],{"January","February","March","April","May","June","July","August","September","October","November","December"},0),1) -> 41671 | E41: 121.9 | F41: 122 | G41: 124.5 | H41: 115.2 | I41: 102.5 | J41: 114.1 | K41: 111.5 | L41: 108.2 | M41: 95.4 | N41: 113.5 | O41: 112.1 | P41: 119.9 | Q41: 115.2 | R41: 116.2 | S41: 115.3 | T41: 111.7 | U41: 114.7 | V41: 112.5 | W41: 111.1 | X41: 112.6 | Y41: 110.4 | Z41: 111.3 | AA41: 110.3 | AB41: 111.6 | AC41: 108.7 | AD41: 111 | AE41: 113.1
A42: Rural | B42: 2014 | C42: March | D42: =DATE(All_India_Index_Upto_April23__1___1[[#This Row],[Year]],MATCH(All_India_Index_Upto_April23__1___1[[#This Row],[Month]],{"January","February","March","April","May","June","July","August","September","October","November","December"},0),1) -> 41699 | E42: 120.1 | F42: 118.1 | G42: 120.7 | H42: 116.1 | I42: 109.3 | J42: 119.6 | K42: 117.9 | L42: 110.2 | M42: 101.2 | N42: 110.7 | O42: 113 | P42: 118.3 | Q42: 116.2 | R42: 114.6 | S42: 117.5 | T42: 114.9 | U42: 117.2 | W42: 113.4 | X42: 113.4 | Y42: 111.4 | Z42: 111.2 | AA42: 110.2 | AB42: 112.4 | AC42: 108.9 | AD42: 111.3 | AE42: 114.6
A43: Urban | B43: 2014 | C43: March | D43: =DATE(All_India_Index_Upto_April23__1___1[[#This Row],[Year]],MATCH(All_India_Index_Upto_April23__1___1[[#This Row],[Month]],{"January","February","March","April","May","June","July","August","September","October","November","December"},0),1) -> 41699 | E43: 122.1 | F43: 121.4 | G43: 121.5 | H43: 116.2 | I43: 102.8 | J43: 117.7 | K43: 113.3 | L43: 108.9 | M43: 96.3 | N43: 114.1 | O43: 112.2 | P43: 120.5 | Q43: 116 | R43: 116.7 | S43: 115.8 | T43: 112.1 | U43: 115.2 | V43: 113.2 | W43: 110.9 | X43: 113 | Y43: 110.8 | Z43: 111.6 | AA43: 110.9 | AB43: 111.8 | AC43: 109.2 | AD43: 111.4 | AE43: 113.7
A44: Rural | B44: 2014 | C44: April | D44: =DATE(All_India_Index_Upto_April23__1___1[[#This Row],[Year]],MATCH(All_India_Index_Upto_April23__1___1[[#This Row],[Month]],{"January","February","March","April","May","June","July","August","September","October","November","December"},0),1) -> 41730 | E44: 120.2 | F44: 118.9 | G44: 118.1 | H44: 117 | I44: 109.7 | J44: 125.5 | K44: 120.5 | L44: 111 | M44: 102.6 | N44: 111.2 | O44: 113.5 | P44: 118.7 | Q44: 117.2 | R44: 115.4 | S44: 118.1 | T44: 116.1 | U44: 117.8 | W44: 113.4 | X44: 113.7 | Y44: 111.8 | Z44: 111.2 | AA44: 110.5 | AB44: 113 | AC44: 108.9 | AD44: 111.5 | AE44: 115.4
A45: Urban | B45: 2014 | C45: April | D45: =DATE(All_India_Index_Upto_April23__1___1[[#This Row],[Year]],MATCH(All_India_Index_Upto_April23__1___1[[#This Row],[Month]],{"January","February","March","April","May","June","July","August","September","October","November","December"},0),1) -> 41730 | E45: 122.5 | F45: 121.7 | G45: 113.3 | H45: 117 | I45: 103.1 | J45: 126.7 | K45: 121.2 | L45: 111 | M45: 100.3 | N45: 115.3 | O45: 112.7 | P45: 121 | Q45: 118.2 | R45: 117.6 | S45: 116.3 | T45: 112.5 | U45: 115.7 | V45: 113.9 | W45: 110.9 | X45: 113.4 | Y45: 111 | Z45: 111.2 | AA45: 111.2 | AB45: 112.5 | AC45: 109.1 | AD45: 111.4 | AE45: 114.7
A46: Rural | B46: 2014 | C46: May | D46: =DATE(All_India_Index_Upto_April23__1___1[[#This Row],[Year]],MATCH(All_India_Index_Upto_April23__1___1[[#This Row],[Month]],{"January","February","March","April","May","June","July","August","September","October","November","December"},0),1) -> 41760 | E46: 120.3 | F46: 120.2 | G46: 116.9 | H46: 118 | I46: 110.1 | J46: 126.3 | K46: 123.9 | L46: 111.5 | M46: 103.5 | N46: 111.6 | O46: 114.2 | P46: 119.2 | Q46: 118.2 | R46: 116.3 | S46: 118.7 | T46: 116.8 | U46: 118.5 | W46: 113.4 | X46: 114.1 | Y46: 112.1 | Z46: 111.4 | AA46: 110.9 | AB46: 113.1 | AC46: 108.9 | AD46: 111.8 | AE46: 116
A47: Urban | B47: 2014 | C47: May | D47: =DATE(All_India_Index_Upto_April23__1___1[[#This Row],[Year]],MATCH(All_India_Index_Upto_April23__1___1[[#This Row],[Month]],{"January","February","March","April","May","June","July","August","September","October","November","December"},0),1) -> 41760 | E47: 122.7 | F47: 124.1 | G47: 114.2 | H47: 119.1 | I47: 103.5 | J47: 129.2 | K47: 127 | L47: 112.6 | M47: 101.3 | N47: 117 | O47: 112.9 | P47: 121.7 | Q47: 120 | R47: 118.3 | S47: 116.8 | T47: 112.9 | U47: 116.2 | V47: 114.3 | W47: 111.1 | X47: 114.1 | Y47: 111.2 | Z47: 111.3 | AA47: 111.5 | AB47: 112.9 | AC47: 109.3 | AD47: 111.7 | AE47: 115.6
A48: Rural | B48: 2014 | C48: June | D48: =DATE(All_India_Index_Upto_April23__1___1[[#This Row],[Year]],MATCH(All_India_Index_Upto_April23__1___1[[#This Row],[Month]],{"January","February","March","April","May","June","July","August","September","October","November","December"},0),1) -> 41791 | E48: 120.7 | F48: 121.6 | G48: 116.1 | H48: 119.3 | I48: 110.3 | J48: 125.8 | K48: 129.3 | L48: 112.2 | M48: 103.6 | N48: 112.3 | O48: 114.9 | P48: 120.1 | Q48: 119.5 | R48: 117.3 | S48: 119.7 | T48: 117.3 | U48: 119.3 | W48: 114.4 | X48: 114.9 | Y48: 112.8 | Z48: 112.2 | AA48: 111.4 | AB48: 114.3 | AC48: 108 | AD48: 112.3 | AE48: 117
A49: Urban | B49: 2014 | C49: June | D49: =DATE(All_India_Index_Upto_April23__1___1[[#This Row],[Year]],MATCH(All_India_Index_Upto_April23__1___1[[#This Row],[Month]],{"January","February","March","April","May","June","July","August","September","October","November","December"},0),1) -> 41791 | E49: 123.1 | F49: 125.9 | G49: 115.4 | H49: 120.4 | I49: 103.4 | J49: 131.2 | K49: 137.5 | L49: 112.8 | M49: 101.4 | N49: 118.3 | O49: 113.2 | P49: 122.4 | Q49: 122 | R49: 119 | S49: 117.4 | T49: 113.2 | U49: 116.7 | V49: 113.9 | W49: 111.2 | X49: 114.3 | Y49: 111.4 | Z49: 111.5 | AA49: 111.8 | AB49: 115.1 | AC49: 108.7 | AD49: 112.2 | AE49: 116.4
A50: Rural | B50: 2014 | C50: July | D50: =DATE(All_India_Index_Upto_April23__1___1[[#This Row],[Year]],MATCH(All_India_Index_Upto_April23__1___1[[#This Row],[Month]],{"January","February","March","April","May","June","July","August","September","October","November","December"},0),1) -> 41821 | E50: 121.7 | F50: 122.5 | G50: 117.7 | H50: 120.6 | I50: 110.4 | J50: 129.1 | K50: 150.1 | L50: 113.2 | M50: 104.8 | N50: 113.3 | O50: 115.6 | P50: 120.9 | Q50: 123.3 | R50: 118 | S50: 120.7 | T50: 118.3 | U50: 120.3 | W50: 115.3 | X50: 115.4 | Y50: 113.4 | Z50: 113.2 | AA50: 111.8 | AB50: 115.5 | AC50: 108.8 | AD50: 113.1 | AE50: 119.5
A51: Urban | B51: 2014 | C51: July | D51: =DATE(All_India_Index_Upto_April23__1___1[[#This Row],[Year]],MATCH(All_India_Index_Upto_April23__1___1[[#This Row],[Month]],{"January","February","March","April","May","June","July","August","September","October","November","December"},0),1) -> 41821 | E51: 123.8 | F51: 126.4 | G51: 118 | H51: 121.6 | I51: 103.5 | J51: 133.7 | K51: 172.4 | L51: 113.1 | M51: 102.7 | N51: 120 | O51: 113.8 | P51: 123.4 | Q51: 127.1 | R51: 121 | S51: 118 | T51: 113.6 | U51: 117.4 | V51: 114.8 | W51: 111.6 | X51: 114.9 | Y51: 111.5 | Z51: 113 | AA51: 112.4 | AB51: 117.8 | AC51: 109.7 | AD51: 113.5 | AE51: 118.9
A52: Rural | B52: 2014 | C52: August | D52: =DATE(All_India_Index_Upto_April23__1___1[[#This Row],[Year]],MATCH(All_India_Index_Upto_April23__1___1[[#This Row],[Month]],{"January","February","March","April","May","June","July","August","September","October","November","December"},0),1) -> 41852 | E52: 121.8 | F52: 122.8 | G52: 117.8 | H52: 121.9 | I52: 110.6 | J52: 129.7 | K52: 161.1 | L52: 114.1 | M52: 105.1 | N52: 114.6 | O52: 115.8 | P52: 121.7 | Q52: 125.3 | R52: 118.8 | S52: 120.9 | T52: 118.8 | U52: 120.7 | W52: 115.4 | X52: 115.9 | Y52: 114 | Z52: 113.2 | AA52: 112.2 | AB52: 116.2 | AC52: 109.4 | AD52: 113.5 | AE52: 120.7
A53: Urban | B53: 2014 | C53: August | D53: =DATE(All_India_Index_Upto_April23__1___1[[#This Row],[Year]],MATCH(All_India_Index_Upto_April23__1___1[[#This Row],[Month]],{"January","February","March","April","May","June","July","August","September","October","November","December"},0),1) -> 41852 | E53: 124.8 | F53: 127.3 | G53: 116.5 | H53: 122.2 | I53: 103.6 | J53: 132.7 | K53: 181.9 | L53: 115.2 | M53: 102.7 | N53: 122.1 | O53: 114.4 | P53: 124.7 | Q53: 128.9 | R53: 123 | S53: 118.6 | T53: 114.1 | U53: 117.9 | V53: 115.5 | W53: 111.8 | X53: 115.3 | Y53: 112.2 | Z53: 112.5 | AA53: 112.9 | AB53: 119.2 | AC53: 110.5 | AD53: 113.9 | AE53: 119.9
A54: Rural | B54: 2014 | C54: September | D54: =DATE(All_India_Index_Upto_April23__1___1[[#This Row],[Year]],MATCH(All_India_Index_Upto_April23__1___1[[#This Row],[Month]],{"January","February","March","April","May","June","July","August","September","October","November","December"},0),1) -> 41883 | E54: 122.3 | F54: 122.4 | G54: 117.8 | H54: 122.7 | I54: 110.4 | J54: 129.8 | K54: 158.8 | L54: 115 | M54: 104.7 | N54: 114.9 | O54: 116.5 | P54: 122.6 | Q54: 125.3 | R54: 119.5 | S54: 121.7 | T54: 119.2 | U54: 121.3 | W54: 115.8 | X54: 116.7 | Y54: 114.5 | Z54: 112.8 | AA54: 112.6 | AB54: 116.6 | AC54: 109.1 | AD54: 113.7 | AE54: 120.9
A55: Urban | B55: 2014 | C55: September | D55: =DATE(All_India_Index_Upto_April23__1___1[[#This Row],[Year]],MATCH(All_India_Index_Upto_April23__1___1[[#This Row],[Month]],{"January","February","March","April","May","June","July","August","September","October","November","December"},0),1) -> 41883 | E55: 124.2 | F55: 125.4 | G55: 116.4 | H55: 122.7 | I55: 103.5 | J55: 124.5 | K55: 168.6 | L55: 116.9 | M55: 101.9 | N55: 122.9 | O55: 114.8 | P55: 125.2 | Q55: 126.7 | R55: 124.3 | S55: 119.2 | T55: 114.5 | U55: 118.4 | V55: 116.1 | W55: 111.8 | X55: 115.5 | Y55: 112.3 | Z55: 111.2 | AA55: 113.4 | AB55: 120 | AC55: 110 | AD55: 113.6 | AE55: 119.2
A56: Rural | B56: 2014 | C56: October | D56: =DATE(All_India_Index_Upto_April23__1___1[[#This Row],[Year]],MATCH(All_India_Index_Upto_April23__1___1[[#This Row],[Month]],{"January","February","March","April","May","June","July","August","September","October","November","December"},0),1) -> 41913 | E56: 122.6 | F56: 122.5 | G56: 118.3 | H56: 123.2 | I56: 110.5 | J56: 128.9 | K56: 155.3 | L56: 115.5 | M56: 104 | N56: 115.3 | O56: 116.8 | P56: 123.2 | Q56: 125.1 | R56: 120 | S56: 122.7 | T56: 120.3 | U56: 122.3 | W56: 116.4 | X56: 117.5 | Y56: 115.3 | Z56: 112.6 | AA56: 113 | AB56: 116.9 | AC56: 109.3 | AD56: 114 | AE56: 121
A57: Urban | B57: 2014 | C57: October | D57: =DATE(All_India_Index_Upto_April23__1___1[[#This Row],[Year]],MATCH(All_India_Index_Upto_April23__1___1[[#This Row],[Month]],{"January","February","March","April","May","June","July","August","September","October","November","December"},0),1) -> 41913 | E57: 124.6 | F57: 126.1 | G57: 117.8 | H57: 123.1 | I57: 103.5 | J57: 123.5 | K57: 159.6 | L57: 117.4 | M57: 101.2 | N57: 123.8 | O57: 115.2 | P57: 125.9 | Q57: 125.8 | R57: 124.3 | S57: 119.6 | T57: 114.9 | U57: 118.9 | V57: 116.7 | W57: 112 | X57: 115.8 | Y57: 112.6 | Z57: 111 | AA57: 113.6 | AB57: 120.2 | AC57: 110.1 | AD57: 113.7 | AE57: 119.1
A58: Rural | B58: 2014 | C58: November | D58: =DATE(All_India_Index_Upto_April23__1___1[[#This Row],[Year]],MATCH(All_India_Index_Upto_April23__1___1[[#This Row],[Month]],{"January","February","March","April","May","June","July","August","September","October","November","December"},0),1) -> 41944 | E58: 122.7 | F58: 122.6 | G58: 119.9 | H58: 124 | I58: 110.5 | J58: 128.8 | K58: 152 | L58: 116.2 | M58: 103.3 | N58: 115.8 | O58: 116.8 | P58: 124.5 | Q58: 124.9 | R58: 120.8 | S58: 123.3 | T58: 120.5 | U58: 122.9 | W58: 117.3 | X58: 118.1 | Y58: 115.9 | Z58: 112 | AA58: 113.3 | AB58: 117.2 | AC58: 108.8 | AD58: 114.1 | AE58: 121.1
A59: Urban | B59: 2014 | C59: November | D59: =DATE(All_India_Index_Upto_April23__1___1[[#This Row],[Year]],MATCH(All_India_Index_Upto_April23__1___1[[#This Row],[Month]],{"January","February","March","April","May","June","July","August","September","October","November","December"},0),1) -> 41944 | E59: 124.5 | F59: 125.6 | G59: 122.7 | H59: 124.6 | I59: 103.2 | J59: 122.2 | K59: 153.2 | L59: 119.3 | M59: 99.8 | N59: 124.6 | O59: 115.8 | P59: 126.9 | Q59: 125.4 | R59: 125.8 | S59: 120.3 | T59: 115.4 | U59: 119.5 | V59: 117.1 | W59: 112.6 | X59: 116.4 | Y59: 113 | Z59: 109.7 | AA59: 114 | AB59: 120.3 | AC59: 109.6 | AD59: 113.4 | AE59: 119
A60: Rural | B60: 2014 | C60: December | D60: =DATE(All_India_Index_Upto_April23__1___1[[#This Row],[Year]],MATCH(All_India_Index_Upto_April23__1___1[[#This Row],[Month]],{"January","February","March","April","May","June","July","August","September","October","November","December"},0),1) -> 41974 | E60: 122.4 | F60: 122.4 | G60: 121.8 | H60: 124.2 | I60: 110.2 | J60: 128.6 | K60: 140.3 | L60: 116.3 | M60: 102 | N60: 116 | O60: 117.3 | P60: 124.8 | Q60: 123.3 | R60: 121.7 | S60: 123.8 | T60: 120.6 | U60: 123.3 | W60: 117.4 | X60: 118.2 | Y60: 116.2 | Z60: 111.5 | AA60: 113.3 | AB60: 117.7 | AC60: 109.4 | AD60: 114.2 | AE60: 120.3
A61: Urban | B61: 2014 | C61: December | D61: =DATE(All_India_Index_Upto_April23__1___1[[#This Row],[Year]],MATCH(All_India_Index_Upto_April23__1___1[[#This Row],[Month]],{"January","February","March","April","May","June","July","August","September","October","November","December"},0),1) -> 41974 | E61: 124 | F61: 124.7 | G61: 126.3 | H61: 124.9 | I61: 103 | J61: 122.3 | K61: 141 | L61: 120.1 | M61: 97.8 | N61: 125.4 | O61: 116.1 | P61: 127.6 | Q61: 124 | R61: 126.4 | S61: 120.7 | T61: 115.8 | U61: 120 | V61: 116.5 | W61: 113 | X61: 116.8 | Y61: 113.2 | Z61: 108.8 | AA61: 114.3 | AB61: 120.7 | AC61: 110.4 | AD61: 113.4 | AE61: 118.4
A62: Rural+Urban | B62: 2014 | C62: January | D62: =DATE(All_India_Index_Upto_April23__1___1[[#This Row],[Year]],MATCH(All_India_Index_Upto_April23__1___1[[#This Row],[Month]],{"January","February","March","April","May","June","July","August","September","October","November","December"},0),1) -> 41640 | E62: 119.6 | F62: 118.8 | G62: 124.1 | H62: 114.1 | I62: 106.8 | J62: 113.9 | K62: 122.2 | L62: 108.9 | M62: 100.2 | N62: 111 | O62: 112.3 | P62: 118.1 | Q62: 115.8 | R62: 114.5 | S62: 115.8 | T62: 113.2 | U62: 115.4 | V62: 111.6 | W62: 112.2 | X62: 112.3 | Y62: 110.3 | Z62: 110.7 | AA62: 109.7 | AB62: 111.6 | AC62: 108.2 | AD62: 110.6 | AE62: 113.6
A63: Rural+Urban | B63: 2014 | C63: February | D63: =DATE(All_India_Index_Upto_April23__1___1[[#This Row],[Year]],MATCH(All_India_Index_Upto_April23__1___1[[#This Row],[Month]],{"January","February","March","April","May","June","July","August","September","October","November","December"},0),1) -> 41671 | E63: 120.2 | F63: 119.2 | G63: 122.5 | H63: 115.1 | I63: 106.6 | J63: 115.4 | K63: 114.5 | L63: 109.3 | M63: 99.2 | N63: 111.4 | O63: 112.6 | P63: 118.8 | Q63: 115.3 | R63: 114.7 | S63: 116.4 | T63: 113.3 | U63: 115.9 | V63: 112.5 | W63: 112.4 | X63: 112.8 | Y63: 110.7 | Z63: 111.1 | AA63: 110.1 | AB63: 111.8 | AC63: 108.7 | AD63: 110.9 | AE63: 113.6
A64: Rural+Urban | B64: 2014 | C64: March | D64: =DATE(All_India_Index_Upto_April23__1___1[[#This Row],[Year]],MATCH(All_India_Index_Upto_April23__1___1[[#This Row],[Month]],{"January","February","March","April","May","June","July","August","September","October","November","December"},0),1) -> 41699 | E64: 120.7 | F64: 119.3 | G64: 121 | H64: 116.1 | I64: 106.9 | J64: 118.7 | K64: 116.3 | L64: 109.8 | M64: 99.6 | N64: 111.8 | O64: 112.7 | P64: 119.3 | Q64: 116.1 | R64: 115.2 | S64: 116.8 | T64: 113.7 | U64: 116.4 | V64: 113.2 | W64: 112.5 | X64: 113.2 | Y64: 111.2 | Z64: 111.4 | AA64: 110.6 | AB64: 112 | AC64: 109 | AD64: 111.3 | AE64: 114.2
A65: Rural+Urban | B65: 2014 | C65: April | D65: =DATE(All_India_Index_Upto_April23__1___1[[#This Row],[Year]],MATCH(All_India_Index_Upto_April23__1___1[[#This Row],[Month]],{"January","February","March","April","May","June","July","August","September","October","November","December"},0),1) -> 41730 | E65: 120.9 | F65: 119.9 | G65: 116.2 | H65: 117 | I65: 107.3 | J65: 126.1 | K65: 120.7 | L65: 111 | M65: 101.8 | N65: 112.6 | O65: 113.2 | P65: 119.8 | Q65: 117.6 | R65: 116 | S65: 117.4 | T65: 114.6 | U65: 117 | V65: 113.9 | W65: 112.5 | X65: 113.6 | Y65: 111.5 | Z65: 111.2 | AA65: 110.9 | AB65: 112.7 | AC65: 109 | AD65: 111.5 | AE65: 115.1
A66: Rural+Urban | B66: 2014 | C66: May | D66: =DATE(All_India_Index_Upto_April23__1___1[[#This Row],[Year]],MATCH(All_India_Index_Upto_April23__1___1[[#This Row],[Month]],{"January","February","March","April","May","June","July","August","September","October","November","December"},0),1) -> 41760 | E66: 121.1 | F66: 121.6 | G66: 115.9 | H66: 118.4 | I66: 107.7 | J66: 127.7 | K66: 125 | L66: 111.9 | M66: 102.8 | N66: 113.4 | O66: 113.7 | P66: 120.4 | Q66: 118.9 | R66: 116.8 | S66: 118 | T66: 115.2 | U66: 117.6 | V66: 114.3 | W66: 112.5 | X66: 114.1 | Y66: 111.8 | Z66: 111.3 | AA66: 111.2 | AB66: 113 | AC66: 109.1 | AD66: 111.8 | AE66: 115.8
A67: Rural+Urban | B67: 2014 | C67: June | D67: =DATE(All_India_Index_Upto_April23__1___1[[#This Row],[Year]],MATCH(All_India_Index_Upto_April23__1___1[[#This Row],[Month]],{"January","February","March","April","May","June","July","August","September","October","November","December"},0),1) -> 41791 | E67: 121.5 | F67: 123.1 | G67: 115.8 | H67: 119.7 | I67: 107.8 | J67: 128.3 | K67: 132.1 | L67: 112.4 | M67: 102.9 | N67: 114.3 | O67: 114.2 | P67: 121.2 | Q67: 120.4 | R67: 117.8 | S67: 118.8 | T67: 115.6 | U67: 118.3 | V67: 113.9 | W67: 113.2 | X67: 114.6 | Y67: 112.3 | Z67: 111.8 | AA67: 111.6 | AB67: 114.8 | AC67: 108.3 | AD67: 112.3 | AE67: 116.7
A68: Rural+Urban | B68: 2014 | C68: July | D68: =DATE(All_India_Index_Upto_April23__1___1[[#This Row],[Year]],MATCH(All_India_Index_Upto_April23__1___1[[#This Row],[Month]],{"January","February","March","April","May","June","July","August","September","October","November","December"},0),1) -> 41821 | E68: 122.4 | F68: 123.9 | G68: 117.8 | H68: 121 | I68: 107.9 | J68: 131.2 | K68: 157.7 | L68: 113.2 | M68: 104.1 | N68: 115.5 | O68: 114.8 | P68: 122.1 | Q68: 124.7 | R68: 118.8 | S68: 119.6 | T68: 116.3 | U68: 119.1 | V68: 114.8 | W68: 113.9 | X68: 115.2 | Y68: 112.7 | Z68: 113.1 | AA68: 112.1 | AB68: 116.8 | AC68: 109.2 | AD68: 113.3 | AE68: 119.2
A69: Rural+Urban | B69: 2014 | C69: August | D69: =DATE(All_India_Index_Upto_April23__1___1[[#This Row],[Year]],MATCH(All_India_Index_Upto_April23__1___1[[#This Row],[Month]],{"January","February","March","April","May","June","July","August","September","October","November","December"},0),1) -> 41852 | E69: 122.7 | F69: 124.4 | G69: 117.3 | H69: 122 | I69: 108 | J69: 131.1 | K69: 168.2 | L69: 114.5 | M69: 104.3 | N69: 117.1 | O69: 115.2 | P69: 123.1 | Q69: 126.6 | R69: 119.9 | S69: 120 | T69: 116.8 | U69: 119.6 | V69: 115.5 | W69: 114 | X69: 115.6 | Y69: 113.3 | Z69: 112.8 | AA69: 112.6 | AB69: 118 | AC69: 109.9 | AD69: 113.7 | AE69: 120.3
A70: Rural+Urban | B70: 2014 | C70: September | D70: =DATE(All_India_Index_Upto_April23__1___1[[#This Row],[Year]],MATCH(All_India_Index_Upto_April23__1___1[[#This Row],[Month]],{"January","February","March","April","May","June","July","August","September","October","November","December"},0),1) -> 41883 | E70: 122.9 | F70: 123.5 | G70: 117.3 | H70: 122.7 | I70: 107.9 | J70: 127.3 | K70: 162.1 | L70: 115.6 | M70: 103.8 | N70: 117.6 | O70: 115.8 | P70: 123.8 | Q70: 125.8 | R70: 120.8 | S70: 120.7 | T70: 117.2 | U70: 120.1 | V70: 116.1 | W70: 114.3 | X70: 116.1 | Y70: 113.7 | Z70: 112 | AA70: 113.1 | AB70: 118.6 | AC70: 109.5 | AD70: 113.7 | AE70: 120.1
A71: Rural+Urban | B71: 2014 | C71: October | D71: =DATE(All_India_Index_Upto_April23__1___1[[#This Row],[Year]],MATCH(All_India_Index_Upto_April23__1___1[[#This Row],[Month]],{"January","February","March","April","May","June","July","August","September","October","November","December"},0),1) -> 41913 | E71: 123.2 | F71: 123.8 | G71: 118.1 | H71: 123.2 | I71: 107.9 | J71: 126.4 | K71: 156.8 | L71: 116.1 | M71: 103.1 | N71: 118.1 | O71: 116.1 | P71: 124.5 | Q71: 125.4 | R71: 121.1 | S71: 121.5 | T71: 118.1 | U71: 121 | V71: 116.7 | W71: 114.7 | X71: 116.7 | Y71: 114.3 | Z71: 111.8 | AA71: 113.3 | AB71: 118.8 | AC71: 109.6 | AD71: 113.9 | AE71: 120.1
A72: Rural+Urban | B72: 2014 | C72: November | D72: =DATE(All_India_Index_Upto_April23__1___1[[#This Row],[Year]],MATCH(All_India_Index_Upto_April23__1___1[[#This Row],[Month]],{"January","February","March","April","May","June","July","August","September","October","November","December"},0),1) -> 41944 | E72: 123.3 | F72: 123.7 | G72: 121 | H72: 124.2 | I72: 107.8 | J72: 125.7 | K72: 152.4 | L72: 117.2 | M72: 102.1 | N72: 118.7 | O72: 116.4 | P72: 125.6 | Q72: 125.1 | R72: 122.1 | S72: 122.1 | T72: 118.4 | U72: 121.6 | V72: 117.1 | W72: 115.5 | X72: 117.3 | Y72: 114.8 | Z72: 110.8 | AA72: 113.7 | AB72: 119 | AC72: 109.1 | AD72: 113.8 | AE72: 120.1
A73: Rural+Urban | B73: 2014 | C73: December | D73: =DATE(All_India_Index_Upto_April23__1___1[[#This Row],[Year]],MATCH(All_India_Index_Upto_April23__1___1[[#This Row],[Month]],{"January","February","March","April","May","June","July","August","September","October","November","December"},0),1) -> 41974 | E73: 122.9 | F73: 123.2 | G73: 123.5 | H73: 124.5 | I73: 107.6 | J73: 125.7 | K73: 140.5 | L73: 117.6 | M73: 100.6 | N73: 119.1 | O73: 116.8 | P73: 126.1 | Q73: 123.6 | R73: 123 | S73: 122.6 | T73: 118.6 | U73: 122 | V73: 116.5 | W73: 115.7 | X73: 117.5 | Y73: 115.1 | Z73: 110.1 | AA73: 113.9 | AB73: 119.5 | AC73: 109.8 | AD73: 113.8 | AE73: 119.4
A74: Rural | B74: 2015 | C74: January | D74: =DATE(All_India_Index_Upto_April23__1___1[[#This Row],[Year]],MATCH(All_India_Index_Upto_April23__1___1[[#This Row],[Month]],{"January","February","March","April","May","June","July","August","September","October","November","December"},0),1) -> 42005 | E74: 123.1 | F74: 123.1 | G74: 122.1 | H74: 124.9 | I74: 111 | J74: 130.4 | K74: 132.3 | L74: 117.2 | M74: 100.5 | N74: 117.2 | O74: 117.9 | P74: 125.6 | Q74: 122.8 | R74: 122.7 | S74: 124.4 | T74: 121.6 | U74: 124 | W74: 118.4 | X74: 118.9 | Y74: 116.6 | Z74: 111 | AA74: 114 | AB74: 118.2 | AC74: 110.2 | AD74: 114.5 | AE74: 120.3
A75: Urban | B75: 2015 | C75: January | D75: =DATE(All_India_Index_Upto_April23__1___1[[#This Row],[Year]],MATCH(All_India_Index_Upto_April23__1___1[[#This Row],[Month]],{"January","February","March","April","May","June","July","August","September","October","November","December"},0),1) -> 42005 | E75: 124 | F75: 125.5 | G75: 126.6 | H75: 125.2 | I75: 104.3 | J75: 121.3 | K75: 134.4 | L75: 122.9 | M75: 96.1 | N75: 126.6 | O75: 116.5 | P75: 128 | Q75: 123.5 | R75: 127.4 | S75: 121 | T75: 116.1 | U75: 120.2 | V75: 117.3 | W75: 113.4 | X75: 117.2 | Y75: 113.7 | Z75: 107.9 | AA75: 114.6 | AB75: 120.8 | AC75: 111.4 | AD75: 113.4 | AE75: 118.5
A76: Rural | B76: 2015 | C76: February | D76: =DATE(All_India_Index_Upto_April23__1___1[[#This Row],[Year]],MATCH(All_India_Index_Upto_April23__1___1[[#This Row],[Month]],{"January","February","March","April","May","June","July","August","September","October","November","December"},0),1) -> 42036 | E76: 123.4 | F76: 124.4 | G76: 122.1 | H76: 125.8 | I76: 111.5 | J76: 129.4 | K76: 128.2 | L76: 118.8 | M76: 100 | N76: 118.6 | O76: 118.8 | P76: 126.8 | Q76: 122.8 | R76: 124.2 | S76: 125.4 | T76: 122.7 | U76: 125 | W76: 120 | X76: 119.6 | Y76: 117.7 | Z76: 110.9 | AA76: 114.8 | AB76: 118.7 | AC76: 110.8 | AD76: 115 | AE76: 120.6
A77: Urban | B77: 2015 | C77: February | D77: =DATE(All_India_Index_Upto_April23__1___1[[#This Row],[Year]],MATCH(All_India_Index_Upto_April23__1___1[[#This Row],[Month]],{"January","February","March","April","May","June","July","August","September","October","November","December"},0),1) -> 42036 | E77: 124.3 | F77: 126.5 | G77: 119.5 | H77: 125.6 | I77: 104.9 | J77: 121.6 | K77: 131.8 | L77: 125.1 | M77: 95 | N77: 127.7 | O77: 116.8 | P77: 128.6 | Q77: 123.7 | R77: 128.1 | S77: 121.3 | T77: 116.5 | U77: 120.6 | V77: 118.1 | W77: 114 | X77: 117.7 | Y77: 114.1 | Z77: 106.8 | AA77: 114.9 | AB77: 120.4 | AC77: 111.7 | AD77: 113.2 | AE77: 118.7
A78: Rural | B78: 2015 | C78: March | D78: =DATE(All_India_Index_Upto_April23__1___1[[#This Row],[Year]],MATCH(All_India_Index_Upto_April23__1___1[[#This Row],[Month]],{"January","February","March","April","May","June","July","August","September","October","November","December"},0),1) -> 42064 | E78: 123.3 | F78: 124.7 | G78: 118.9 | H78: 126 | I78: 111.8 | J78: 130.9 | K78: 128 | L78: 119.9 | M78: 98.9 | N78: 119.4 | O78: 118.9 | P78: 127.7 | Q78: 123.1 | R78: 124.7 | S78: 126 | T78: 122.9 | U78: 125.5 | W78: 120.6 | X78: 120.2 | Y78: 118.2 | Z78: 111.6 | AA78: 115.5 | AB78: 119.4 | AC78: 110.8 | AD78: 115.5 | AE78: 121.1
A79: Urban | B79: 2015 | C79: March | D79: =DATE(All_India_Index_Upto_April23__1___1[[#This Row],[Year]],MATCH(All_India_Index_Upto_April23__1___1[[#This Row],[Month]],{"January","February","March","April","May","June","July","August","September","October","November","December"},0),1) -> 42064 | E79: 124 | F79: 126.7 | G79: 113.5 | H79: 125.9 | I79: 104.8 | J79: 123.8 | K79: 131.4 | L79: 127.2 | M79: 93.2 | N79: 127.4 | O79: 117 | P79: 129.2 | Q79: 123.9 | R79: 128.8 | S79: 121.7 | T79: 116.9 | U79: 120.9 | V79: 118.6 | W79: 114.4 | X79: 118 | Y79: 114.3 | Z79: 108.4 | AA79: 115.4 | AB79: 120.6 | AC79: 111.3 | AD79: 113.8 | AE79: 119.1
A80: Rural | B80: 2015 | C80: April | D80: =DATE(All_India_Index_Upto_April23__1___1[[#This Row],[Year]],MATCH(All_India_Index_Upto_April23__1___1[[#This Row],[Month]],{"January","February","March","April","May","June","July","August","September","October","November","December"},0),1) -> 42095 | E80: 123.3 | F80: 125.5 | G80: 117.2 | H80: 126.8 | I80: 111.9 | J80: 134.2 | K80: 127.5 | L80: 121.5 | M80: 97.8 | N80: 119.8 | O80: 119.4 | P80: 128.7 | Q80: 123.6 | R80: 125.7 | S80: 126.4 | T80: 123.3 | U80: 126 | W80: 121.2 | X80: 120.9 | Y80: 118.6 | Z80: 111.9 | AA80: 116.2 | AB80: 119.9 | AC80: 111.6 | AD80: 116 | AE80: 121.5
A81: Urban | B81: 2015 | C81: April | D81: =DATE(All_India_Index_Upto_April23__1___1[[#This Row],[Year]],MATCH(All_India_Index_Upto_April23__1___1[[#This Row],[Month]],{"January","February","March","April","May","June","July","August","September","October","November","December"},0),1) -> 42095 | E81: 123.8 | F81: 128.2 | G81: 110 | H81: 126.3 | I81: 104.5 | J81: 130.6 | K81: 130.8 | L81: 131.3 | M81: 91.6 | N81: 127.7 | O81: 117.2 | P81: 129.5 | Q81: 124.6 | R81: 130.1 | S81: 122.1 | T81: 117.2 | U81: 121.3 | V81: 119.2 | W81: 114.7 | X81: 118.4 | Y81: 114.6 | Z81: 108.4 | AA81: 115.6 | AB81: 121.7 | AC81: 111.8 | AD81: 114.2 | AE81: 119.7
A82: Rural | B82: 2015 | C82: May | D82: =DATE(All_India_Index_Upto_April23__1___1[[#This Row],[Year]],MATCH(All_India_Index_Upto_April23__1___1[[#This Row],[Month]],{"January","February","March","April","May","June","July","August","September","October","November","December"},0),1) -> 42125 | E82: 123.5 | F82: 127.1 | G82: 117.3 | H82: 127.7 | I82: 112.5 | J82: 134.1 | K82: 128.5 | L82: 124.3 | M82: 97.6 | N82: 120.7 | O82: 120.2 | P82: 129.8 | Q82: 124.4 | R82: 126.7 | S82: 127.3 | T82: 124.1 | U82: 126.8 | W82: 121.9 | X82: 121.5 | Y82: 119.4 | Z82: 113.3 | AA82: 116.7 | AB82: 120.5 | AC82: 112.3 | AD82: 116.9 | AE82: 122.4
A83: Urban | B83: 2015 | C83: May | D83: =DATE(All_India_Index_Upto_April23__1___1[[#This Row],[Year]],MATCH(All_India_Index_Upto_April23__1___1[[#This Row],[Month]],{"January","February","March","April","May","June","July","August","September","October","November","December"},0),1) -> 42125 | E83: 123.8 | F83: 129.7 | G83: 111.3 | H83: 126.6 | I83: 105.2 | J83: 130.8 | K83: 135.6 | L83: 142.6 | M83: 90.8 | N83: 128.8 | O83: 117.7 | P83: 129.9 | Q83: 126.1 | R83: 131.3 | S83: 122.4 | T83: 117.4 | U83: 121.6 | V83: 119.6 | W83: 114.9 | X83: 118.7 | Y83: 114.9 | Z83: 110.8 | AA83: 116 | AB83: 122 | AC83: 112.4 | AD83: 115.2 | AE83: 120.7
A84: Rural | B84: 2015 | C84: June | D84: =DATE(All_India_Index_Upto_April23__1___1[[#This Row],[Year]],MATCH(All_India_Index_Upto_April23__1___1[[#This Row],[Month]],{"January","February","March","April","May","June","July","August","September","October","November","December"},0),1) -> 42156 | E84: 124.1 | F84: 130.4 | G84: 122.1 | H84: 128.7 | I84: 114.1 | J84: 133.2 | K84: 135.2 | L84: 131.9 | M84: 96.3 | N84: 123 | O84: 121.1 | P84: 131.2 | Q84: 126.6 | R84: 128.2 | S84: 128.4 | T84: 125.1 | U84: 128 | W84: 122.6 | X84: 122.8 | Y84: 120.4 | Z84: 114.2 | AA84: 117.9 | AB84: 122 | AC84: 113 | AD84: 117.9 | AE84: 124.1
A85: Urban | B85: 2015 | C85: June | D85: =DATE(All_India_Index_Upto_April23__1___1[[#This Row],[Year]],MATCH(All_India_Index_Upto_April23__1___1[[#This Row],[Month]],{"January","February","March","April","May","June","July","August","September","October","November","December"},0),1) -> 42156 | E85: 123.6 | F85: 134.4 | G85: 120.9 | H85: 127.3 | I85: 106 | J85: 132.3 | K85: 146.7 | L85: 148.1 | M85: 89.8 | N85: 130.5 | O85: 118 | P85: 130.5 | Q85: 128.5 | R85: 132.1 | S85: 123.2 | T85: 117.6 | U85: 122.3 | V85: 119 | W85: 115.1 | X85: 119.2 | Y85: 115.4 | Z85: 111.7 | AA85: 116.2 | AB85: 123.8 | AC85: 112.5 | AD85: 116 | AE85: 121.7
A86: Rural | B86: 2015 | C86: July | D86: =DATE(All_India_Index_Upto_April23__1___1[[#This Row],[Year]],MATCH(All_India_Index_Upto_April23__1___1[[#This Row],[Month]],{"January","February","March","April","May","June","July","August","September","October","November","December"},0),1) -> 42186 | E86: 124 | F86: 131.5 | G86: 122 | H86: 128.7 | I86: 113.5 | J86: 133.3 | K86: 140.8 | L86: 133.8 | M86: 94.1 | N86: 123.4 | O86: 121 | P86: 131.7 | Q86: 127.5 | R86: 129.4 | S86: 128.8 | T86: 125.5 | U86: 128.3 | W86: 123 | X86: 123 | Y86: 120.8 | Z86: 114.1 | AA86: 118 | AB86: 122.9 | AC86: 112.7 | AD86: 118.1 | AE86: 124.7
A87: Urban | B87: 2015 | C87: July | D87: =DATE(All_India_Index_Upto_April23__1___1[[#This Row],[Year]],MATCH(All_India_Index_Upto_April23__1___1[[#This Row],[Month]],{"January","February","March","April","May","June","July","August","September","October","November","December"},0),1) -> 42186 | E87: 123.2 | F87: 134.3 | G87: 119.5 | H87: 127.7 | I87: 106.3 | J87: 132.8 | K87: 153.5 | L87: 149.5 | M87: 85.7 | N87: 131.5 | O87: 118.3 | P87: 131.1 | Q87: 129.5 | R87: 133.1 | S87: 123.5 | T87: 117.9 | U87: 122.7 | V87: 119.9 | W87: 115.3 | X87: 119.5 | Y87: 116 | Z87: 111.5 | AA87: 116.6 | AB87: 125.4 | AC87: 111.7 | AD87: 116.3 | AE87: 122.4
A88: Rural | B88: 2015 | C88: August | D88: =DATE(All_India_Index_Upto_April23__1___1[[#This Row],[Year]],MATCH(All_India_Index_Upto_April23__1___1[[#This Row],[Month]],{"January","February","March","April","May","June","July","August","September","October","November","December"},0),1) -> 42217 | E88: 124.7 | F88: 131.3 | G88: 121.3 | H88: 128.8 | I88: 114 | J88: 134.2 | K88: 153.6 | L88: 137.9 | M88: 93.1 | N88: 123.9 | O88: 121.5 | P88: 132.5 | Q88: 129.8 | R88: 130.1 | S88: 129.5 | T88: 126.3 | U88: 129 | W88: 123.8 | X88: 123.7 | Y88: 121.1 | Z88: 113.6 | AA88: 118.5 | AB88: 123.6 | AC88: 112.5 | AD88: 118.2 | AE88: 126.1
A89: Urban | B89: 2015 | C89: August | D89: =DATE(All_India_Index_Upto_April23__1___1[[#This Row],[Year]],MATCH(All_India_Index_Upto_April23__1___1[[#This Row],[Month]],{"January","February","March","April","May","June","July","August","September","October","November","December"},0),1) -> 42217 | E89: 123.1 | F89: 131.7 | G89: 118.1 | H89: 128 | I89: 106.8 | J89: 130.1 | K89: 165.5 | L89: 156 | M89: 85.3 | N89: 132.7 | O89: 118.8 | P89: 131.7 | Q89: 131.1 | R89: 134.2 | S89: 123.7 | T89: 118.2 | U89: 122.9 | V89: 120.9 | W89: 115.3 | X89: 120 | Y89: 116.6 | Z89: 109.9 | AA89: 117.2 | AB89: 126.2 | AC89: 112 | AD89: 116.2 | AE89: 123.2
A90: Rural | B90: 2015 | C90: September | D90: =DATE(All_India_Index_Upto_April23__1___1[[#This Row],[Year]],MATCH(All_India_Index_Upto_April23__1___1[[#This Row],[Month]],{"January","February","March","April","May","June","July","August","September","October","November","December"},0),1) -> 42248 | E90: 125.1 | F90: 131.1 | G90: 120.7 | H90: 129.2 | I90: 114.7 | J90: 132.3 | K90: 158.9 | L90: 142.1 | M90: 92.5 | N90: 125.4 | O90: 121.9 | P90: 132.7 | Q90: 131 | R90: 131 | S90: 130.4 | T90: 126.8 | U90: 129.9 | W90: 123.7 | X90: 124.5 | Y90: 121.4 | Z90: 113.8 | AA90: 119.6 | AB90: 124.5 | AC90: 113.7 | AD90: 118.8 | AE90: 127
A91: Urban | B91: 2015 | C91: September | D91: =DATE(All_India_Index_Upto_April23__1___1[[#This Row],[Year]],MATCH(All_India_Index_Upto_April23__1___1[[#This Row],[Month]],{"January","February","March","April","May","June","July","August","September","October","November","December"},0),1) -> 42248 | E91: 123.4 | F91: 129 | G91: 115.6 | H91: 128.3 | I91: 107 | J91: 124 | K91: 168.5 | L91: 165.4 | M91: 86.3 | N91: 134.4 | O91: 119.1 | P91: 132.3 | Q91: 131.5 | R91: 134.7 | S91: 124 | T91: 118.6 | U91: 123.2 | V91: 121.6 | W91: 115.1 | X91: 120.4 | Y91: 117.1 | Z91: 109.1 | AA91: 117.3 | AB91: 126.5 | AC91: 112.9 | AD91: 116.2 | AE91: 123.5
A92: Rural | B92: 2015 | C92: October | D92: =DATE(All_India_Index_Upto_April23__1___1[[#This Row],[Year]],MATCH(All_India_Index_Upto_April23__1___1[[#This Row],[Month]],{"January","February","March","April","May","June","July","August","September","October","November","December"},0),1) -> 42278 | E92: 125.6 | F92: 130.4 | G92: 120.8 | H92: 129.4 | I92: 115.8 | J92: 133.2 | K92: 157.7 | L92: 154.2 | M92: 93.7 | N92: 126.6 | O92: 122.3 | P92: 133.1 | Q92: 131.8 | R92: 131.5 | S92: 131.1 | T92: 127.3 | U92: 130.6 | W92: 124.4 | X92: 125.1 | Y92: 122 | Z92: 113.8 | AA92: 120.1 | AB92: 125.1 | AC92: 114.2 | AD92: 119.2 | AE92: 127.7
A93: Urban | B93: 2015 | C93: October | D93: =DATE(All_India_Index_Upto_April23__1___1[[#This Row],[Year]],MATCH(All_India_Index_Upto_April23__1___1[[#This Row],[Month]],{"January","February","March","April","May","June","July","August","September","October","November","December"},0),1) -> 42278 | E93: 123.6 | F93: 128.6 | G93: 115.9 | H93: 128.5 | I93: 109 | J93: 124.1 | K93: 165.8 | L93: 187.2 | M93: 89.4 | N93: 135.8 | O93: 119.4 | P93: 132.9 | Q93: 132.6 | R93: 135.3 | S93: 124.4 | T93: 118.8 | U93: 123.6 | V93: 122.4 | W93: 114.9 | X93: 120.7 | Y93: 117.7 | Z93: 109.3 | AA93: 117.7 | AB93: 126.5 | AC93: 113.5 | AD93: 116.5 | AE93: 124.2
A94: Rural | B94: 2015 | C94: November | D94: =DATE(All_India_Index_Upto_April23__1___1[[#This Row],[Year]],MATCH(All_India_Index_Upto_April23__1___1[[#This Row],[Month]],{"January","February","March","April","May","June","July","August","September","October","November","December"},0),1) -> 42309 | E94: 126.1 | F94: 130.6 | G94: 121.7 | H94: 129.5 | I94: 117.8 | J94: 132.1 | K94: 155.2 | L94: 160.8 | M94: 94.5 | N94: 128.3 | O94: 123.1 | P94: 134.2 | Q94: 132.4 | R94: 132.2 | S94: 132.1 | T94: 128.2 | U94: 131.5 | W94: 125.6 | X94: 125.6 | Y94: 122.6 | Z94: 114 | AA94: 120.9 | AB94: 125.8 | AC94: 114.2 | AD94: 119.6 | AE94: 128.3
A95: Urban | B95: 2015 | C95: November | D95: =DATE(All_India_Index_Upto_April23__1___1[[#This Row],[Year]],MATCH(All_India_Index_Upto_April23__1___1[[#This Row],[Month]],{"January","February","March","April","May","June","July","August","September","October","November","December"},0),1) -> 42309 | E95: 124 | F95: 129.8 | G95: 121.5 | H95: 128.6 | I95: 110 | J95: 123.7 | K95: 164.6 | L95: 191.6 | M95: 90.8 | N95: 137.1 | O95: 119.8 | P95: 133.7 | Q95: 133.3 | R95: 137.6 | S95: 125 | T95: 119.3 | U95: 124.2 | V95: 122.9 | W95: 115.1 | X95: 121 | Y95: 118.1 | Z95: 109.3 | AA95: 117.9 | AB95: 126.6 | AC95: 113.3 | AD95: 116.6 | AE95: 124.6
A96: Rural | B96: 2015 | C96: December | D96: =DATE(All_India_Index_Upto_April23__1___1[[#This Row],[Year]],MATCH(All_India_Index_Upto_April23__1___1[[#This Row],[Month]],{"January","February","March","April","May","June","July","August","September","October","November","December"},0),1) -> 42339 | E96: 126.3 | F96: 131.3 | G96: 123.3 | H96: 129.8 | I96: 118.3 | J96: 131.6 | K96: 145.5 | L96: 162.1 | M96: 95.4 | N96: 128.9 | O96: 123.3 | P96: 135.1 | Q96: 131.4 | R96: 133.1 | S96: 132.5 | T96: 128.5 | U96: 131.9 | W96: 125.7 | X96: 126 | Y96: 123.1 | Z96: 114 | AA96: 121.6 | AB96: 125.6 | AC96: 114.1 | AD96: 119.8 | AE96: 127.9
A97: Urban | B97: 2015 | C97: December | D97: =DATE(All_India_Index_Upto_April23__1___1[[#This Row],[Year]],MATCH(All_India_Index_Upto_April23__1___1[[#This Row],[Month]],{"January","February","March","April","May","June","July","August","September","October","November","December"},0),1) -> 42339 | E97: 124.3 | F97: 131.7 | G97: 127.1 | H97: 128.6 | I97: 110 | J97: 120.8 | K97: 149 | L97: 190.1 | M97: 92.7 | N97: 138.6 | O97: 120.2 | P97: 134.2 | Q97: 131.5 | R97: 138.2 | S97: 125.4 | T97: 119.5 | U97: 124.5 | V97: 122.4 | W97: 116 | X97: 121 | Y97: 118.6 | Z97: 109.3 | AA97: 118.1 | AB97: 126.6 | AC97: 113.2 | AD97: 116.7 | AE97: 124
A98: Rural+Urban | B98: 2015 | C98: January | D98: =DATE(All_India_Index_Upto_April23__1___1[[#This Row],[Year]],MATCH(All_India_Index_Upto_April23__1___1[[#This Row],[Month]],{"January","February","March","April","May","June","July","August","September","October","November","December"},0),1) -> 42005 | E98: 123.4 | F98: 123.9 | G98: 123.8 | H98: 125 | I98: 108.5 | J98: 126.2 | K98: 133 | L98: 119.1 | M98: 99 | N98: 120.3 | O98: 117.3 | P98: 126.7 | Q98: 123.1 | R98: 124 | S98: 123.1 | T98: 119.3 | U98: 122.5 | V98: 117.3 | W98: 116.5 | X98: 118.1 | Y98: 115.5 | Z98: 109.4 | AA98: 114.3 | AB98: 119.7 | AC98: 110.7 | AD98: 114 | AE98: 119.5
A99: Rural+Urban | B99: 2015 | C99: February | D99: =DATE(All_India_Index_Upto_April23__1___1[[#This Row],[Year]],MATCH(All_India_Index_Upto_April23__1___1[[#This Row],[Month]],{"January","February","March","April","May","June","July","August","September","October","November","December"},0),1) -> 42036 | E99: 123.7 | F99: 125.1 | G99: 121.1 | H99: 125.7 | I99: 109.1 | J99: 125.8 | K99: 129.4 | L99: 120.9 | M99: 98.3 | N99: 121.6 | O99: 118 | P99: 127.6 | Q99: 123.1 | R99: 125.2 | S99: 123.8 | T99: 120.1 | U99: 123.3 | V99: 118.1 | W99: 117.7 | X99: 118.7 | Y99: 116.3 | Z99: 108.7 | AA99: 114.9 | AB99: 119.7 | AC99: 111.2 | AD99: 114.1 | AE99: 119.7
A100: Rural+Urban | B100: 2015 | C100: March | D100: =DATE(All_India_Index_Upto_April23__1___1[[#This Row],[Year]],MATCH(All_India_Index_Upto_April23__1___1[[#This Row],[Month]],{"January","February","March","April","May","June","July","August","September","October","November","December"},0),1) -> 42064 | E100: 123.5 | F100: 125.4 | G100: 116.8 | H100: 126 | I100: 109.2 | J100: 127.6 | K100: 129.2 | L100: 122.4 | M100: 97 | N100: 122.1 | O100: 118.1 | P100: 128.4 | Q100: 123.4 | R100: 125.8 | S100: 124.3 | T100: 120.4 | U100: 123.7 | V100: 118.6 | W100: 118.3 | X100: 119.2 | Y100: 116.7 | Z100: 109.9 | AA100: 115.4 | AB100: 120.1 | AC100: 111 | AD100: 114.7 | AE100: 120.2
...

Sheet Inflation_Dashboard

Sheet Q1_Contribution_Analysis
A1: Consumer Price Index (CPI) Analysis Report
A2: Reporting Period: May 2023 | Base Year: 2012
A3: Data Source: All-India Consumer Price Index
A4: Summary
A5: This analysis studies the Consumer Price Index (CPI) for May 2023 to understand which broad areas are putting the most pressure on prices in India.We grouped 26 detailed CPI categories into 8 broader categories such as Food, Health, Energy, and Housing.The analysis shows that Health is the biggest contributor to overall price levels, followed by Clothing & Footwear and Energy.There are also clear differences between Rural and Urban areas, especially in Housing and Energy costs.
A6: Methodology (How the Analysis Was Done)
A7: Step 1: Creating Broad Categories
A8: The original CPI data has 26 individual categories.
A9: These were grouped into 8 broader buckets:
A10: Example: Cereals, Milk, Vegetables, Spices, and Prepared Meals were grouped under Food.
A11: Step 2: Calculating Bucket Index
A12: Since official CPI weights were not available, we used a simple average of all categories within each bucket.
... A19: The following table details the calculated index for each broader category and its percentage share of the analyzed basket:
A21: Bucket Name | B21: Bucket Index (Rural + Urban) | C21: Bucket Index (Rural) | D21: Bucket Index (Urban) | E21: Contribution % (Rural + Urban) | F21: Contribution % (Rural) | G21: Contribution % (Urban)
A22: Food | B22: 177.45385 | C22: 176.20769 | D22: 179.62308 | E22: 0.1241358 | F22: 0.13874028 | G22: 0.12717611
A23: Energy | B23: 182.8 | C23: 182.5 | D23: 183.4 | E23: 0.12787564 | F23: 0.14369464 | G23: 0.12985023
A24: Transport | B24: 164.8 | C24: 169.7 | D24: 160.4 | E24: 0.11528395 | F24: 0.13361633 | G24: 0.11356585
A25: Housing | B25: 175.6 | D25: 175.6 | E25: 0.12283896 | G25: 0.1243277
A26: Health | B26: 185.7 | C26: 187.8 | D26: 182.2 | E26: 0.1299043 | F26: 0.14786769 | G26: 0.12900061
A27: Education | B27: 177.1 | C27: 180.3 | D27: 174.8 | E27: 0.12388827 | F27: 0.14196243 | G27: 0.12376129
A28: Clothing & Footwear | B28: 184.4 | C28: 189.96667 | D28: 176.23333 | E28: 0.1289949 | F28: 0.14957365 | G28: 0.12477611
A29: Others | B29: 181.66 | C29: 183.58 | D29: 180.14 | E29: 0.12707817 | F29: 0.14454499 | G29: 0.1275421
A30: Total | B30: 1429.5138 | C30: 1270.0544 | D30: 1412.3964 | E30: 1 | F30: 1 | G30: 1
B31: Note: Rural Housing data is not available, so Housing is only reflected in Urban and Combined values.
A49: Key Findings
A50: A. Highest Contributor to CPI
A51: Health (13.00%) is the largest contributor to CPI.
A52: This means healthcare-related costs have increased the most compared to the 2012 base year.
A53: Rising medical expenses are the strongest inflation driver in May 2023.
A54: B. Lowest Contributor
A55: Transport and Communication (11.54%) contributes the least.
A56: This suggests that transport and communication prices have grown more slowly than other sectors.
A57: C. Rural vs Urban Differences
A58: Urban Areas:
A59: Housing, Education, and Health play a major role in inflation.
A60: Rural Areas:
... A65: As of May 2023, Health and Clothing & Footwear are the most important drivers of CPI inflation in India. The analysis also shows clear differences in inflation pressure between Rural and Urban households, especially in Housing and Energy. This grouped-bucket approach provides a clear and balanced view of inflation patterns across the economy.

Sheet Sheet6
A1: Category Name | B1: Index (Rural+Urban) | C1: Index (Rural) | D1: Index (Urban) | E1: Bucket | G1: Bucket Name | H1: Bucket Index (Rural + Urban) | I1: Bucket Index (Rural) | J1: Bucket Index (Urban) | K1: Contribution % (Rural + Urban) | L1: Contribution % (Rural) | M1: Contribution % (Urban)
A2: Cereals and products | B2: {=IFERROR( _xlfn.XLOOKUP( 1, (All_India_Index_Upto_April23__1___1[Sector]="Rural+Urban") * (All_India_Index_Upto_April23__1___1[Date]=DATE(2023,5,1)), INDEX(All_India_Index_Upto_April23__1___1[],0, MATCH($A2, All_India_Index_Upto_April23__1___1[#Headers],0) ) ), "")} -> 173.7 | C2: {=IFERROR( _xlfn.XLOOKUP( 1, (All_India_Index_Upto_April23__1___1[Sector]="Rural") * (All_India_Index_Upto_April23__1___1[Date]=DATE(2023,5,1)), INDEX(All_India_Index_Upto_April23__1___1[],0, MATCH($A2, All_India_Index_Upto_April23__1___1[#Headers],0) ) ), "")} -> 173.2 | D2: {=IFERROR( _xlfn.XLOOKUP( 1, (All_India_Index_Upto_April23__1___1[Sector]="Urban") * (All_India_Index_Upto_April23__1___1[Date]=DATE(2023,5,1)), INDEX(All_India_Index_Upto_April23__1___1[],0, MATCH($A2, All_India_Index_Upto_April23__1___1[#Headers],0) ) ), "")} -> 174.7 | E2: Food | G2: Food | H2: =AVERAGEIF($E$2:$E$27, G2, $B$2:$B$27) -> 177.45385 | I2: =IF(G2="Housing","",AVERAGEIF($E:$E, G2, $C:$C)) -> 176.20769 | J2: =AVERAGEIF($E:$E, G2, $D:$D) -> 179.62308 | K2: =H2 / SUM($H$2:$H$9) -> 0.1241358 | L2: =IF(I2="","", I2 / SUM($I$2:$I$9)) -> 0.13874028 | M2: =J2 / SUM($J$2:$J$9) -> 0.12717611
A3: Meat and fish | B3: {=IFERROR( _xlfn.XLOOKUP( 1, (All_India_Index_Upto_April23__1___1[Sector]="Rural+Urban") * (All_India_Index_Upto_April23__1___1[Date]=DATE(2023,5,1)), INDEX(All_India_Index_Upto_April23__1___1[],0, MATCH($A3, All_India_Index_Upto_April23__1___1[#Headers],0) ) ), "")} -> 214.3 | C3: {=IFERROR( _xlfn.XLOOKUP( 1, (All_India_Index_Upto_April23__1___1[Sector]="Rural") * (All_India_Index_Upto_April23__1___1[Date]=DATE(2023,5,1)), INDEX(All_India_Index_Upto_April23__1___1[],0, MATCH($A3, All_India_Index_Upto_April23__1___1[#Headers],0) ) ), "")} -> 211.5 | D3: {=IFERROR( _xlfn.XLOOKUP( 1, (All_India_Index_Upto_April23__1___1[Sector]="Urban") * (All_India_Index_Upto_April23__1___1[Date]=DATE(2023,5,1)), INDEX(All_India_Index_Upto_April23__1___1[],0, MATCH($A3, All_India_Index_Upto_April23__1___1[#Headers],0) ) ), "")} -> 219.4 | E3: Food | G3: Energy | H3: =AVERAGEIF($E$2:$E$27, G3, $B$2:$B$27) -> 182.8 | I3: =IF(G3="Housing","",AVERAGEIF($E:$E, G3, $C:$C)) -> 182.5 | J3: =AVERAGEIF($E:$E, G3, $D:$D) -> 183.4 | K3: =H3 / SUM($H$2:$H$9) -> 0.12787564 | L3: =IF(I3="","", I3 / SUM($I$2:$I$9)) -> 0.14369464 | M3: =J3 / SUM($J$2:$J$9) -> 0.12985023
A4: Egg | B4: {=IFERROR( _xlfn.XLOOKUP( 1, (All_India_Index_Upto_April23__1___1[Sector]="Rural+Urban") * (All_India_Index_Upto_April23__1___1[Date]=DATE(2023,5,1)), INDEX(All_India_Index_Upto_April23__1___1[],0, MATCH($A4, All_India_Index_Upto_April23__1___1[#Headers],0) ) ), "")} -> 173.2 | C4: {=IFERROR( _xlfn.XLOOKUP( 1, (All_India_Index_Upto_April23__1___1[Sector]="Rural") * (All_India_Index_Upto_April23__1___1[Date]=DATE(2023,5,1)), INDEX(All_India_Index_Upto_April23__1___1[],0, MATCH($A4, All_India_Index_Upto_April23__1___1[#Headers],0) ) ), "")} -> 171 | D4: {=IFERROR( _xlfn.XLOOKUP( 1, (All_India_Index_Upto_April23__1___1[Sector]="Urban") * (All_India_Index_Upto_April23__1___1[Date]=DATE(2023,5,1)), INDEX(All_India_Index_Upto_April23__1___1[],0, MATCH($A4, All_India_Index_Upto_April23__1___1[#Headers],0) ) ), "")} -> 176.7 | E4: Food | G4: Transport | H4: =AVERAGEIF($E$2:$E$27, G4, $B$2:$B$27) -> 164.8 | I4: =IF(G4="Housing","",AVERAGEIF($E:$E, G4, $C:$C)) -> 169.7 | J4: =AVERAGEIF($E:$E, G4, $D:$D) -> 160.4 | K4: =H4 / SUM($H$2:$H$9) -> 0.11528395 | L4: =IF(I4="","", I4 / SUM($I$2:$I$9)) -> 0.13361633 | M4: =J4 / SUM($J$2:$J$9) -> 0.11356585
A5: Milk and products | B5: {=IFERROR( _xlfn.XLOOKUP( 1, (All_India_Index_Upto_April23__1___1[Sector]="Rural+Urban") * (All_India_Index_Upto_April23__1___1[Date]=DATE(2023,5,1)), INDEX(All_India_Index_Upto_April23__1___1[],0, MATCH($A5, All_India_Index_Upto_April23__1___1[#Headers],0) ) ), "")} -> 179.5 | C5: {=IFERROR( _xlfn.XLOOKUP( 1, (All_India_Index_Upto_April23__1___1[Sector]="Rural") * (All_India_Index_Upto_April23__1___1[Date]=DATE(2023,5,1)), INDEX(All_India_Index_Upto_April23__1___1[],0, MATCH($A5, All_India_Index_Upto_April23__1___1[#Headers],0) ) ), "")} -> 179.6 | D5: {=IFERROR( _xlfn.XLOOKUP( 1, (All_India_Index_Upto_April23__1___1[Sector]="Urban") * (All_India_Index_Upto_April23__1___1[Date]=DATE(2023,5,1)), INDEX(All_India_Index_Upto_April23__1___1[],0, MATCH($A5, All_India_Index_Upto_April23__1___1[#Headers],0) ) ), "")} -> 179.4 | E5: Food | G5: Housing | H5: 175.6 | I5: =IF(G5="Housing","",AVERAGEIF($E:$E, G5, $C:$C)) | J5: 175.6 | K5: =H5 / SUM($H$2:$H$9) -> 0.12283896 | L5: =IF(I5="","", I5 / SUM($I$2:$I$9)) | M5: =J5 / SUM($J$2:$J$9) -> 0.1243277
A6: Oils and fats | B6: {=IFERROR( _xlfn.XLOOKUP( 1, (All_India_Index_Upto_April23__1___1[Sector]="Rural+Urban") * (All_India_Index_Upto_April23__1___1[Date]=DATE(2023,5,1)), INDEX(All_India_Index_Upto_April23__1___1[],0, MATCH($A6, All_India_Index_Upto_April23__1___1[#Headers],0) ) ), "")} -> 170 | C6: {=IFERROR( _xlfn.XLOOKUP( 1, (All_India_Index_Upto_April23__1___1[Sector]="Rural") * (All_India_Index_Upto_April23__1___1[Date]=DATE(2023,5,1)), INDEX(All_India_Index_Upto_April23__1___1[],0, MATCH($A6, All_India_Index_Upto_April23__1___1[#Headers],0) ) ), "")} -> 173.3 | D6: {=IFERROR( _xlfn.XLOOKUP( 1, (All_India_Index_Upto_April23__1___1[Sector]="Urban") * (All_India_Index_Upto_April23__1___1[Date]=DATE(2023,5,1)), INDEX(All_India_Index_Upto_April23__1___1[],0, MATCH($A6, All_India_Index_Upto_April23__1___1[#Headers],0) ) ), "")} -> 164.4 | E6: Food | G6: Health | H6: =AVERAGEIF($E$2:$E$27, G6, $B$2:$B$27) -> 185.7 | I6: =IF(G6="Housing","",AVERAGEIF($E:$E, G6, $C:$C)) -> 187.8 | J6: =AVERAGEIF($E:$E, G6, $D:$D) -> 182.2 | K6: =H6 / SUM($H$2:$H$9) -> 0.1299043 | L6: =IF(I6="","", I6 / SUM($I$2:$I$9)) -> 0.14786769 | M6: =J6 / SUM($J$2:$J$9) -> 0.12900061
A7: Fruits | B7: {=IFERROR( _xlfn.XLOOKUP( 1, (All_India_Index_Upto_April23__1___1[Sector]="Rural+Urban") * (All_India_Index_Upto_April23__1___1[Date]=DATE(2023,5,1)), INDEX(All_India_Index_Upto_April23__1___1[],0, MATCH($A7, All_India_Index_Upto_April23__1___1[#Headers],0) ) ), "")} -> 172.2 | C7: {=IFERROR( _xlfn.XLOOKUP( 1, (All_India_Index_Upto_April23__1___1[Sector]="Rural") * (All_India_Index_Upto_April23__1___1[Date]=DATE(2023,5,1)), INDEX(All_India_Index_Upto_April23__1___1[],0, MATCH($A7, All_India_Index_Upto_April23__1___1[#Headers],0) ) ), "")} -> 169 | D7: {=IFERROR( _xlfn.XLOOKUP( 1, (All_India_Index_Upto_April23__1___1[Sector]="Urban") * (All_India_Index_Upto_April23__1___1[Date]=DATE(2023,5,1)), INDEX(All_India_Index_Upto_April23__1___1[],0, MATCH($A7, All_India_Index_Upto_April23__1___1[#Headers],0) ) ), "")} -> 175.8 | E7: Food | G7: Education | H7: =AVERAGEIF($E$2:$E$27, G7, $B$2:$B$27) -> 177.1 | I7: =IF(G7="Housing","",AVERAGEIF($E:$E, G7, $C:$C)) -> 180.3 | J7: =AVERAGEIF($E:$E, G7, $D:$D) -> 174.8 | K7: =H7 / SUM($H$2:$H$9) -> 0.12388827 | L7: =IF(I7="","", I7 / SUM($I$2:$I$9)) -> 0.14196243 | M7: =J7 / SUM($J$2:$J$9) -> 0.12376129
A8: Vegetables | B8: {=IFERROR( _xlfn.XLOOKUP( 1, (All_India_Index_Upto_April23__1___1[Sector]="Rural+Urban") * (All_India_Index_Upto_April23__1___1[Date]=DATE(2023,5,1)), INDEX(All_India_Index_Upto_April23__1___1[],0, MATCH($A8, All_India_Index_Upto_April23__1___1[#Headers],0) ) ), "")} -> 161 | C8: {=IFERROR( _xlfn.XLOOKUP( 1, (All_India_Index_Upto_April23__1___1[Sector]="Rural") * (All_India_Index_Upto_April23__1___1[Date]=DATE(2023,5,1)), INDEX(All_India_Index_Upto_April23__1___1[],0, MATCH($A8, All_India_Index_Upto_April23__1___1[#Headers],0) ) ), "")} -> 148.7 | D8: {=IFERROR( _xlfn.XLOOKUP( 1, (All_India_Index_Upto_April23__1___1[Sector]="Urban") * (All_India_Index_Upto_April23__1___1[Date]=DATE(2023,5,1)), INDEX(All_India_Index_Upto_April23__1___1[],0, MATCH($A8, All_India_Index_Upto_April23__1___1[#Headers],0) ) ), "")} -> 185 | E8: Food | G8: Clothing & Footwear | H8: =AVERAGEIF($E$2:$E$27, G8, $B$2:$B$27) -> 184.4 | I8: =IF(G8="Housing","",AVERAGEIF($E:$E, G8, $C:$C)) -> 189.96667 | J8: =AVERAGEIF($E:$E, G8, $D:$D) -> 176.23333 | K8: =H8 / SUM($H$2:$H$9) -> 0.1289949 | L8: =IF(I8="","", I8 / SUM($I$2:$I$9)) -> 0.14957365 | M8: =J8 / SUM($J$2:$J$9) -> 0.12477611
A9: Pulses and products | B9: {=IFERROR( _xlfn.XLOOKUP( 1, (All_India_Index_Upto_April23__1___1[Sector]="Rural+Urban") * (All_India_Index_Upto_April23__1___1[Date]=DATE(2023,5,1)), INDEX(All_India_Index_Upto_April23__1___1[],0, MATCH($A9, All_India_Index_Upto_April23__1___1[#Headers],0) ) ), "")} -> 175.6 | C9: {=IFERROR( _xlfn.XLOOKUP( 1, (All_India_Index_Upto_April23__1___1[Sector]="Rural") * (All_India_Index_Upto_April23__1___1[Date]=DATE(2023,5,1)), INDEX(All_India_Index_Upto_April23__1___1[],0, MATCH($A9, All_India_Index_Upto_April23__1___1[#Headers],0) ) ), "")} -> 174.9 | D9: {=IFERROR( _xlfn.XLOOKUP( 1, (All_India_Index_Upto_April23__1___1[Sector]="Urban") * (All_India_Index_Upto_April23__1___1[Date]=DATE(2023,5,1)), INDEX(All_India_Index_Upto_April23__1___1[],0, MATCH($A9, All_India_Index_Upto_April23__1___1[#Headers],0) ) ), "")} -> 176.9 | E9: Food | G9: Others | H9: =AVERAGEIF($E$2:$E$27, G9, $B$2:$B$27) -> 181.66 | I9: =IF(G9="Housing","",AVERAGEIF($E:$E, G9, $C:$C)) -> 183.58 | J9: =AVERAGEIF($E:$E, G9, $D:$D) -> 180.14 | K9: =H9 / SUM($H$2:$H$9) -> 0.12707817 | L9: =IF(I9="","", I9 / SUM($I$2:$I$9)) -> 0.14454499 | M9: =J9 / SUM($J$2:$J$9) -> 0.1275421
A10: Sugar and Confectionery | B10: {=IFERROR( _xlfn.XLOOKUP( 1, (All_India_Index_Upto_April23__1___1[Sector]="Rural+Urban") * (All_India_Index_Upto_April23__1___1[Date]=DATE(2023,5,1)), INDEX(All_India_Index_Upto_April23__1___1[],0, MATCH($A10, All_India_Index_Upto_April23__1___1[#Headers],0) ) ), "")} -> 122.7 | C10: {=IFERROR( _xlfn.XLOOKUP( 1, (All_India_Index_Upto_April23__1___1[Sector]="Rural") * (All_India_Index_Upto_April23__1___1[Date]=DATE(2023,5,1)), INDEX(All_India_Index_Upto_April23__1___1[],0, MATCH($A10, All_India_Index_Upto_April23__1___1[#Headers],0) ) ), "")} -> 121.9 | D10: {=IFERROR( _xlfn.XLOOKUP( 1, (All_India_Index_Upto_April23__1___1[Sector]="Urban") * (All_India_Index_Upto_April23__1___1[Date]=DATE(2023,5,1)), INDEX(All_India_Index_Upto_April23__1___1[],0, MATCH($A10, All_India_Index_Upto_April23__1___1[#Headers],0) ) ), "")} -> 124.2 | E10: Food | G10: Total | H10: =SUM(H2:H9) -> 1429.5138 | I10: =SUM(I2:I9) -> 1270.0544 | J10: =SUM(J2:J9) -> 1412.3964 | K10: =H10 / SUM($H$2:$H$9) -> 1 | L10: =IF(I10="","", I10 / SUM($I$2:$I$9)) -> 1 | M10: =J10 / SUM($J$2:$J$9) -> 1
A11: Spices | B11: {=IFERROR( _xlfn.XLOOKUP( 1, (All_India_Index_Upto_April23__1___1[Sector]="Rural+Urban") * (All_India_Index_Upto_April23__1___1[Date]=DATE(2023,5,1)), INDEX(All_India_Index_Upto_April23__1___1[],0, MATCH($A11, All_India_Index_Upto_April23__1___1[#Headers],0) ) ), "")} -> 218 | C11: {=IFERROR( _xlfn.XLOOKUP( 1, (All_India_Index_Upto_April23__1___1[Sector]="Rural") * (All_India_Index_Upto_April23__1___1[Date]=DATE(2023,5,1)), INDEX(All_India_Index_Upto_April23__1___1[],0, MATCH($A11, All_India_Index_Upto_April23__1___1[#Headers],0) ) ), "")} -> 221 | D11: {=IFERROR( _xlfn.XLOOKUP( 1, (All_India_Index_Upto_April23__1___1[Sector]="Urban") * (All_India_Index_Upto_April23__1___1[Date]=DATE(2023,5,1)), INDEX(All_India_Index_Upto_April23__1___1[],0, MATCH($A11, All_India_Index_Upto_April23__1___1[#Headers],0) ) ), "")} -> 211.9 | E11: Food
A12: Non-alcoholic beverages | B12: {=IFERROR( _xlfn.XLOOKUP( 1, (All_India_Index_Upto_April23__1___1[Sector]="Rural+Urban") * (All_India_Index_Upto_April23__1___1[Date]=DATE(2023,5,1)), INDEX(All_India_Index_Upto_April23__1___1[],0, MATCH($A12, All_India_Index_Upto_April23__1___1[#Headers],0) ) ), "")} -> 173.4 | C12: {=IFERROR( _xlfn.XLOOKUP( 1, (All_India_Index_Upto_April23__1___1[Sector]="Rural") * (All_India_Index_Upto_April23__1___1[Date]=DATE(2023,5,1)), INDEX(All_India_Index_Upto_April23__1___1[],0, MATCH($A12, All_India_Index_Upto_April23__1___1[#Headers],0) ) ), "")} -> 178.7 | D12: {=IFERROR( _xlfn.XLOOKUP( 1, (All_India_Index_Upto_April23__1___1[Sector]="Urban") * (All_India_Index_Upto_April23__1___1[Date]=DATE(2023,5,1)), INDEX(All_India_Index_Upto_April23__1___1[],0, MATCH($A12, All_India_Index_Upto_April23__1___1[#Headers],0) ) ), "")} -> 165.9 | E12: Food
A13: Prepared meals, snacks, sweets etc. | B13: {=IFERROR( _xlfn.XLOOKUP( 1, (All_India_Index_Upto_April23__1___1[Sector]="Rural+Urban") * (All_India_Index_Upto_April23__1___1[Date]=DATE(2023,5,1)), INDEX(All_India_Index_Upto_April23__1___1[],0, MATCH($A13, All_India_Index_Upto_April23__1___1[#Headers],0) ) ), "")} -> 194.2 | C13: {=IFERROR( _xlfn.XLOOKUP( 1, (All_India_Index_Upto_April23__1___1[Sector]="Rural") * (All_India_Index_Upto_April23__1___1[Date]=DATE(2023,5,1)), INDEX(All_India_Index_Upto_April23__1___1[],0, MATCH($A13, All_India_Index_Upto_April23__1___1[#Headers],0) ) ), "")} -> 191.1 | D13: {=IFERROR( _xlfn.XLOOKUP( 1, (All_India_Index_Upto_April23__1___1[Sector]="Urban") * (All_India_Index_Upto_April23__1___1[Date]=DATE(2023,5,1)), INDEX(All_India_Index_Upto_April23__1___1[],0, MATCH($A13, All_India_Index_Upto_April23__1___1[#Headers],0) ) ), "")} -> 197.7 | E13: Food
A14: Food and beverages | B14: {=IFERROR( _xlfn.XLOOKUP( 1, (All_India_Index_Upto_April23__1___1[Sector]="Rural+Urban") * (All_India_Index_Upto_April23__1___1[Date]=DATE(2023,5,1)), INDEX(All_India_Index_Upto_April23__1___1[],0, MATCH($A14, All_India_Index_Upto_April23__1___1[#Headers],0) ) ), "")} -> 179.1 | C14: {=IFERROR( _xlfn.XLOOKUP( 1, (All_India_Index_Upto_April23__1___1[Sector]="Rural") * (All_India_Index_Upto_April23__1___1[Date]=DATE(2023,5,1)), INDEX(All_India_Index_Upto_April23__1___1[],0, MATCH($A14, All_India_Index_Upto_April23__1___1[#Headers],0) ) ), "")} -> 176.8 | D14: {=IFERROR( _xlfn.XLOOKUP( 1, (All_India_Index_Upto_April23__1___1[Sector]="Urban") * (All_India_Index_Upto_April23__1___1[Date]=DATE(2023,5,1)), INDEX(All_India_Index_Upto_April23__1___1[],0, MATCH($A14, All_India_Index_Upto_April23__1___1[#Headers],0) ) ), "")} -> 183.1 | E14: Food
A15: Pan, tobacco and intoxicants | B15: {=IFERROR( _xlfn.XLOOKUP( 1, (All_India_Index_Upto_April23__1___1[Sector]="Rural+Urban") * (All_India_Index_Upto_April23__1___1[Date]=DATE(2023,5,1)), INDEX(All_India_Index_Upto_April23__1___1[],0, MATCH($A15, All_India_Index_Upto_April23__1___1[#Headers],0) ) ), "")} -> 201 | C15: {=IFERROR( _xlfn.XLOOKUP( 1, (All_India_Index_Upto_April23__1___1[Sector]="Rural") * (All_India_Index_Upto_April23__1___1[Date]=DATE(2023,5,1)), INDEX(All_India_Index_Upto_April23__1___1[],0, MATCH($A15, All_India_Index_Upto_April23__1___1[#Headers],0) ) ), "")} -> 199.9 | D15: {=IFERROR( _xlfn.XLOOKUP( 1, (All_India_Index_Upto_April23__1___1[Sector]="Urban") * (All_India_Index_Upto_April23__1___1[Date]=DATE(2023,5,1)), INDEX(All_India_Index_Upto_April23__1___1[],0, MATCH($A15, All_India_Index_Upto_April23__1___1[#Headers],0) ) ), "")} -> 204.2 | E15: Others
A16: Clothing | B16: {=IFERROR( _xlfn.XLOOKUP( 1, (All_India_Index_Upto_April23__1___1[Sector]="Rural+Urban") * (All_India_Index_Upto_April23__1___1[Date]=DATE(2023,5,1)), INDEX(All_India_Index_Upto_April23__1___1[],0, MATCH($A16, All_India_Index_Upto_April23__1___1[#Headers],0) ) ), "")} -> 187.3 | C16: {=IFERROR( _xlfn.XLOOKUP( 1, (All_India_Index_Upto_April23__1___1[Sector]="Rural") * (All_India_Index_Upto_April23__1___1[Date]=DATE(2023,5,1)), INDEX(All_India_Index_Upto_April23__1___1[],0, MATCH($A16, All_India_Index_Upto_April23__1___1[#Headers],0) ) ), "")} -> 191.2 | D16: {=IFERROR( _xlfn.XLOOKUP( 1, (All_India_Index_Upto_April23__1___1[Sector]="Urban") * (All_India_Index_Upto_April23__1___1[Date]=DATE(2023,5,1)), INDEX(All_India_Index_Upto_April23__1___1[],0, MATCH($A16, All_India_Index_Upto_April23__1___1[#Headers],0) ) ), "")} -> 181.3 | E16: Clothing & Footwear
A17: Footwear | B17: {=IFERROR( _xlfn.XLOOKUP( 1, (All_India_Index_Upto_April23__1___1[Sector]="Rural+Urban") * (All_India_Index_Upto_April23__1___1[Date]=DATE(2023,5,1)), INDEX(All_India_Index_Upto_April23__1___1[],0, MATCH($A17, All_India_Index_Upto_April23__1___1[#Headers],0) ) ), "")} -> 179.7 | C17: {=IFERROR( _xlfn.XLOOKUP( 1, (All_India_Index_Upto_April23__1___1[Sector]="Rural") * (All_India_Index_Upto_April23__1___1[Date]=DATE(2023,5,1)), INDEX(All_India_Index_Upto_April23__1___1[],0, MATCH($A17, All_India_Index_Upto_April23__1___1[#Headers],0) ) ), "")} -> 187.9 | D17: {=IFERROR( _xlfn.XLOOKUP( 1, (All_India_Index_Upto_April23__1___1[Sector]="Urban") * (All_India_Index_Upto_April23__1___1[Date]=DATE(2023,5,1)), INDEX(All_India_Index_Upto_April23__1___1[],0, MATCH($A17, All_India_Index_Upto_April23__1___1[#Headers],0) ) ), "")} -> 168.1 | E17: Clothing & Footwear
A18: Clothing and footwear | B18: {=IFERROR( _xlfn.XLOOKUP( 1, (All_India_Index_Upto_April23__1___1[Sector]="Rural+Urban") * (All_India_Index_Upto_April23__1___1[Date]=DATE(2023,5,1)), INDEX(All_India_Index_Upto_April23__1___1[],0, MATCH($A18, All_India_Index_Upto_April23__1___1[#Headers],0) ) ), "")} -> 186.2 | C18: {=IFERROR( _xlfn.XLOOKUP( 1, (All_India_Index_Upto_April23__1___1[Sector]="Rural") * (All_India_Index_Upto_April23__1___1[Date]=DATE(2023,5,1)), INDEX(All_India_Index_Upto_April23__1___1[],0, MATCH($A18, All_India_Index_Upto_April23__1___1[#Headers],0) ) ), "")} -> 190.8 | D18: {=IFERROR( _xlfn.XLOOKUP( 1, (All_India_Index_Upto_April23__1___1[Sector]="Urban") * (All_India_Index_Upto_April23__1___1[Date]=DATE(2023,5,1)), INDEX(All_India_Index_Upto_April23__1___1[],0, MATCH($A18, All_India_Index_Upto_April23__1___1[#Headers],0) ) ), "")} -> 179.3 | E18: Clothing & Footwear
A19: Housing | B19: {=IFERROR( _xlfn.XLOOKUP( 1, (All_India_Index_Upto_April23__1___1[Sector]="Rural+Urban") * (All_India_Index_Upto_April23__1___1[Date]=DATE(2023,5,1)), INDEX(All_India_Index_Upto_April23__1___1[],0, MATCH($A19, All_India_Index_Upto_April23__1___1[#Headers],0) ) ), "")} -> 175.6 | D19: {=IFERROR( _xlfn.XLOOKUP( 1, (All_India_Index_Upto_April23__1___1[Sector]="Urban") * (All_India_Index_Upto_April23__1___1[Date]=DATE(2023,5,1)), INDEX(All_India_Index_Upto_April23__1___1[],0, MATCH($A19, All_India_Index_Upto_April23__1___1[#Headers],0) ) ), "")} -> 175.6 | E19: Housing
A20: Fuel and light | B20: {=IFERROR( _xlfn.XLOOKUP( 1, (All_India_Index_Upto_April23__1___1[Sector]="Rural+Urban") * (All_India_Index_Upto_April23__1___1[Date]=DATE(2023,5,1)), INDEX(All_India_Index_Upto_April23__1___1[],0, MATCH($A20, All_India_Index_Upto_April23__1___1[#Headers],0) ) ), "")} -> 182.8 | C20: {=IFERROR( _xlfn.XLOOKUP( 1, (All_India_Index_Upto_April23__1___1[Sector]="Rural") * (All_India_Index_Upto_April23__1___1[Date]=DATE(2023,5,1)), INDEX(All_India_Index_Upto_April23__1___1[],0, MATCH($A20, All_India_Index_Upto_April23__1___1[#Headers],0) ) ), "")} -> 182.5 | D20: {=IFERROR( _xlfn.XLOOKUP( 1, (All_India_Index_Upto_April23__1___1[Sector]="Urban") * (All_India_Index_Upto_April23__1___1[Date]=DATE(2023,5,1)), INDEX(All_India_Index_Upto_April23__1___1[],0, MATCH($A20, All_India_Index_Upto_April23__1___1[#Headers],0) ) ), "")} -> 183.4 | E20: Energy
A21: Household goods and services | B21: {=IFERROR( _xlfn.XLOOKUP( 1, (All_India_Index_Upto_April23__1___1[Sector]="Rural+Urban") * (All_India_Index_Upto_April23__1___1[Date]=DATE(2023,5,1)), INDEX(All_India_Index_Upto_April23__1___1[],0, MATCH($A21, All_India_Index_Upto_April23__1___1[#Headers],0) ) ), "")} -> 175.2 | C21: {=IFERROR( _xlfn.XLOOKUP( 1, (All_India_Index_Upto_April23__1___1[Sector]="Rural") * (All_India_Index_Upto_April23__1___1[Date]=DATE(2023,5,1)), INDEX(All_India_Index_Upto_April23__1___1[],0, MATCH($A21, All_India_Index_Upto_April23__1___1[#Headers],0) ) ), "")} -> 179.8 | D21: {=IFERROR( _xlfn.XLOOKUP( 1, (All_India_Index_Upto_April23__1___1[Sector]="Urban") * (All_India_Index_Upto_April23__1___1[Date]=DATE(2023,5,1)), INDEX(All_India_Index_Upto_April23__1___1[],0, MATCH($A21, All_India_Index_Upto_April23__1___1[#Headers],0) ) ), "")} -> 170.1 | E21: Others
A22: Health | B22: {=IFERROR( _xlfn.XLOOKUP( 1, (All_India_Index_Upto_April23__1___1[Sector]="Rural+Urban") * (All_India_Index_Upto_April23__1___1[Date]=DATE(2023,5,1)), INDEX(All_India_Index_Upto_April23__1___1[],0, MATCH($A22, All_India_Index_Upto_April23__1___1[#Headers],0) ) ), "")} -> 185.7 | C22: {=IFERROR( _xlfn.XLOOKUP( 1, (All_India_Index_Upto_April23__1___1[Sector]="Rural") * (All_India_Index_Upto_April23__1___1[Date]=DATE(2023,5,1)), INDEX(All_India_Index_Upto_April23__1___1[],0, MATCH($A22, All_India_Index_Upto_April23__1___1[#Headers],0) ) ), "")} -> 187.8 | D22: {=IFERROR( _xlfn.XLOOKUP( 1, (All_India_Index_Upto_April23__1___1[Sector]="Urban") * (All_India_Index_Upto_April23__1___1[Date]=DATE(2023,5,1)), INDEX(All_India_Index_Upto_April23__1___1[],0, MATCH($A22, All_India_Index_Upto_April23__1___1[#Headers],0) ) ), "")} -> 182.2 | E22: Health
A23: Transport and communication | B23: {=IFERROR( _xlfn.XLOOKUP( 1, (All_India_Index_Upto_April23__1___1[Sector]="Rural+Urban") * (All_India_Index_Upto_April23__1___1[Date]=DATE(2023,5,1)), INDEX(All_India_Index_Upto_April23__1___1[],0, MATCH($A23, All_India_Index_Upto_April23__1___1[#Headers],0) ) ), "")} -> 164.8 | C23: {=IFERROR( _xlfn.XLOOKUP( 1, (All_India_Index_Upto_April23__1___1[Sector]="Rural") * (All_India_Index_Upto_April23__1___1[Date]=DATE(2023,5,1)), INDEX(All_India_Index_Upto_April23__1___1[],0, MATCH($A23, All_India_Index_Upto_April23__1___1[#Headers],0) ) ), "")} -> 169.7 | D23: {=IFERROR( _xlfn.XLOOKUP( 1, (All_India_Index_Upto_April23__1___1[Sector]="Urban") * (All_India_Index_Upto_April23__1___1[Date]=DATE(2023,5,1)), INDEX(All_India_Index_Upto_April23__1___1[],0, MATCH($A23, All_India_Index_Upto_April23__1___1[#Headers],0) ) ), "")} -> 160.4 | E23: Transport
A24: Recreation and amusement | B24: {=IFERROR( _xlfn.XLOOKUP( 1, (All_India_Index_Upto_April23__1___1[Sector]="Rural+Urban") * (All_India_Index_Upto_April23__1___1[Date]=DATE(2023,5,1)), INDEX(All_India_Index_Upto_April23__1___1[],0, MATCH($A24, All_India_Index_Upto_April23__1___1[#Headers],0) ) ), "")} -> 171.2 | C24: {=IFERROR( _xlfn.XLOOKUP( 1, (All_India_Index_Upto_April23__1___1[Sector]="Rural") * (All_India_Index_Upto_April23__1___1[Date]=DATE(2023,5,1)), INDEX(All_India_Index_Upto_April23__1___1[],0, MATCH($A24, All_India_Index_Upto_April23__1___1[#Headers],0) ) ), "")} -> 173.8 | D24: {=IFERROR( _xlfn.XLOOKUP( 1, (All_India_Index_Upto_April23__1___1[Sector]="Urban") * (All_India_Index_Upto_April23__1___1[Date]=DATE(2023,5,1)), INDEX(All_India_Index_Upto_April23__1___1[],0, MATCH($A24, All_India_Index_Upto_April23__1___1[#Headers],0) ) ), "")} -> 169.2 | E24: Others
A25: Education | B25: {=IFERROR( _xlfn.XLOOKUP( 1, (All_India_Index_Upto_April23__1___1[Sector]="Rural+Urban") * (All_India_Index_Upto_April23__1___1[Date]=DATE(2023,5,1)), INDEX(All_India_Index_Upto_April23__1___1[],0, MATCH($A25, All_India_Index_Upto_April23__1___1[#Headers],0) ) ), "")} -> 177.1 | C25: {=IFERROR( _xlfn.XLOOKUP( 1, (All_India_Index_Upto_April23__1___1[Sector]="Rural") * (All_India_Index_Upto_April23__1___1[Date]=DATE(2023,5,1)), INDEX(All_India_Index_Upto_April23__1___1[],0, MATCH($A25, All_India_Index_Upto_April23__1___1[#Headers],0) ) ), "")} -> 180.3 | D25: {=IFERROR( _xlfn.XLOOKUP( 1, (All_India_Index_Upto_April23__1___1[Sector]="Urban") * (All_India_Index_Upto_April23__1___1[Date]=DATE(2023,5,1)), INDEX(All_India_Index_Upto_April23__1___1[],0, MATCH($A25, All_India_Index_Upto_April23__1___1[#Headers],0) ) ), "")} -> 174.8 | E25: Education
A26: Personal care and effects | B26: {=IFERROR( _xlfn.XLOOKUP( 1, (All_India_Index_Upto_April23__1___1[Sector]="Rural+Urban") * (All_India_Index_Upto_April23__1___1[Date]=DATE(2023,5,1)), INDEX(All_India_Index_Upto_April23__1___1[],0, MATCH($A26, All_India_Index_Upto_April23__1___1[#Headers],0) ) ), "")} -> 185.2 | C26: {=IFERROR( _xlfn.XLOOKUP( 1, (All_India_Index_Upto_April23__1___1[Sector]="Rural") * (All_India_Index_Upto_April23__1___1[Date]=DATE(2023,5,1)), INDEX(All_India_Index_Upto_April23__1___1[],0, MATCH($A26, All_India_Index_Upto_April23__1___1[#Headers],0) ) ), "")} -> 184.9 | D26: {=IFERROR( _xlfn.XLOOKUP( 1, (All_India_Index_Upto_April23__1___1[Sector]="Urban") * (All_India_Index_Upto_April23__1___1[Date]=DATE(2023,5,1)), INDEX(All_India_Index_Upto_April23__1___1[],0, MATCH($A26, All_India_Index_Upto_April23__1___1[#Headers],0) ) ), "")} -> 185.6 | E26: Others
A27: Miscellaneous | B27: {=IFERROR( _xlfn.XLOOKUP( 1, (All_India_Index_Upto_April23__1___1[Sector]="Rural+Urban") * (All_India_Index_Upto_April23__1___1[Date]=DATE(2023,5,1)), INDEX(All_India_Index_Upto_April23__1___1[],0, MATCH($A27, All_India_Index_Upto_April23__1___1[#Headers],0) ) ), "")} -> 175.7 | C27: {=IFERROR( _xlfn.XLOOKUP( 1, (All_India_Index_Upto_April23__1___1[Sector]="Rural") * (All_India_Index_Upto_April23__1___1[Date]=DATE(2023,5,1)), INDEX(All_India_Index_Upto_April23__1___1[],0, MATCH($A27, All_India_Index_Upto_April23__1___1[#Headers],0) ) ), "")} -> 179.5 | D27: {=IFERROR( _xlfn.XLOOKUP( 1, (All_India_Index_Upto_April23__1___1[Sector]="Urban") * (All_India_Index_Upto_April23__1___1[Date]=DATE(2023,5,1)), INDEX(All_India_Index_Upto_April23__1___1[],0, MATCH($A27, All_India_Index_Upto_April23__1___1[#Headers],0) ) ), "")} -> 171.6 | E27: Others

Sheet Sheet7
A1: Date | B1: Year | C1: Month | D1: General Index (Rural + Urban) | E1: Prev Year Index | F1: MoM Inflation % | H1: Year | I1: Avg YoY Inflation %
A2: 42736 | B2: =YEAR(A2) -> 2017 | C2: =MONTH(A2) -> 1 | D2: {=IFERROR( INDEX( All_India_Index_Upto_April23__1___1[General index], MATCH( 1, (All_India_Index_Upto_April23__1___1[Sector]="Rural+Urban") * (All_India_Index_Upto_April23__1___1[Date]=A2), 0 ) ), "")} -> 130.3 | E2: {=IFERROR( INDEX( All_India_Index_Upto_April23__1___1[General index], MATCH( 1, (All_India_Index_Upto_April23__1___1[Sector]="Rural+Urban") * (All_India_Index_Upto_April23__1___1[Date]=DATE(YEAR(A2)-1, MONTH(A2), 1)), 0 ) ), "")} -> 126.3 | F2: =IFERROR( (D2-E2)/E2, "") -> 0.031670625 | H2: 2017 | I2: =AVERAGEIFS($F:$F, $B:$B, H2) -> 0.033273885
A3: 42767 | B3: =YEAR(A3) -> 2017 | C3: =MONTH(A3) -> 2 | D3: {=IFERROR( INDEX( All_India_Index_Upto_April23__1___1[General index], MATCH( 1, (All_India_Index_Upto_April23__1___1[Sector]="Rural+Urban") * (All_India_Index_Upto_April23__1___1[Date]=A3), 0 ) ), "")} -> 130.6 | E3: {=IFERROR( INDEX( All_India_Index_Upto_April23__1___1[General index], MATCH( 1, (All_India_Index_Upto_April23__1___1[Sector]="Rural+Urban") * (All_India_Index_Upto_April23__1___1[Date]=DATE(YEAR(A3)-1, MONTH(A3), 1)), 0 ) ), "")} -> 126 | F3: =IFERROR( (D3-E3)/E3, "") -> 0.036507937 | H3: 2018 | I3: =AVERAGEIFS($F:$F, $B:$B, H3) -> 0.039676972
A4: 42795 | B4: =YEAR(A4) -> 2017 | C4: =MONTH(A4) -> 3 | D4: {=IFERROR( INDEX( All_India_Index_Upto_April23__1___1[General index], MATCH( 1, (All_India_Index_Upto_April23__1___1[Sector]="Rural+Urban") * (All_India_Index_Upto_April23__1___1[Date]=A4), 0 ) ), "")} -> 130.9 | E4: {=IFERROR( INDEX( All_India_Index_Upto_April23__1___1[General index], MATCH( 1, (All_India_Index_Upto_April23__1___1[Sector]="Rural+Urban") * (All_India_Index_Upto_April23__1___1[Date]=DATE(YEAR(A4)-1, MONTH(A4), 1)), 0 ) ), "")} -> 126 | F4: =IFERROR( (D4-E4)/E4, "") -> 0.038888889 | H4: 2019 | I4: =AVERAGEIFS($F:$F, $B:$B, H4) -> 0.037704798
A5: 42826 | B5: =YEAR(A5) -> 2017 | C5: =MONTH(A5) -> 4 | D5: {=IFERROR( INDEX( All_India_Index_Upto_April23__1___1[General index], MATCH( 1, (All_India_Index_Upto_April23__1___1[Sector]="Rural+Urban") * (All_India_Index_Upto_April23__1___1[Date]=A5), 0 ) ), "")} -> 131.1 | E5: {=IFERROR( INDEX( All_India_Index_Upto_April23__1___1[General index], MATCH( 1, (All_India_Index_Upto_April23__1___1[Sector]="Rural+Urban") * (All_India_Index_Upto_April23__1___1[Date]=DATE(YEAR(A5)-1, MONTH(A5), 1)), 0 ) ), "")} -> 127.3 | F5: =IFERROR( (D5-E5)/E5, "") -> 0.029850746 | H5: 2020 | I5: =AVERAGEIFS($F:$F, $B:$B, H5) -> 0.062670091
A6: 42856 | B6: =YEAR(A6) -> 2017 | C6: =MONTH(A6) -> 5 | D6: {=IFERROR( INDEX( All_India_Index_Upto_April23__1___1[General index], MATCH( 1, (All_India_Index_Upto_April23__1___1[Sector]="Rural+Urban") * (All_India_Index_Upto_April23__1___1[Date]=A6), 0 ) ), "")} -> 131.4 | E6: {=IFERROR( INDEX( All_India_Index_Upto_April23__1___1[General index], MATCH( 1, (All_India_Index_Upto_April23__1___1[Sector]="Rural+Urban") * (All_India_Index_Upto_April23__1___1[Date]=DATE(YEAR(A6)-1, MONTH(A6), 1)), 0 ) ), "")} -> 128.6 | F6: =IFERROR( (D6-E6)/E6, "") -> 0.021772939 | H6: 2021 | I6: =AVERAGEIFS($F:$F, $B:$B, H6) -> 0.053818467
A7: 42887 | B7: =YEAR(A7) -> 2017 | C7: =MONTH(A7) -> 6 | D7: {=IFERROR( INDEX( All_India_Index_Upto_April23__1___1[General index], MATCH( 1, (All_India_Index_Upto_April23__1___1[Sector]="Rural+Urban") * (All_India_Index_Upto_April23__1___1[Date]=A7), 0 ) ), "")} -> 132 | E7: {=IFERROR( INDEX( All_India_Index_Upto_April23__1___1[General index], MATCH( 1, (All_India_Index_Upto_April23__1___1[Sector]="Rural+Urban") * (All_India_Index_Upto_April23__1___1[Date]=DATE(YEAR(A7)-1, MONTH(A7), 1)), 0 ) ), "")} -> 130.1 | F7: =IFERROR( (D7-E7)/E7, "") -> 0.014604151 | H7: 2022 | I7: =AVERAGEIFS($F:$F, $B:$B, H7) -> 0.06624065
A8: 42917 | B8: =YEAR(A8) -> 2017 | C8: =MONTH(A8) -> 7 | D8: {=IFERROR( INDEX( All_India_Index_Upto_April23__1___1[General index], MATCH( 1, (All_India_Index_Upto_April23__1___1[Sector]="Rural+Urban") * (All_India_Index_Upto_April23__1___1[Date]=A8), 0 ) ), "")} -> 134.2 | E8: {=IFERROR( INDEX( All_India_Index_Upto_April23__1___1[General index], MATCH( 1, (All_India_Index_Upto_April23__1___1[Sector]="Rural+Urban") * (All_India_Index_Upto_April23__1___1[Date]=DATE(YEAR(A8)-1, MONTH(A8), 1)), 0 ) ), "")} -> 131.1 | F8: =IFERROR( (D8-E8)/E8, "") -> 0.023646072 | H8: 2023 | I8: =AVERAGEIFS($F:$F, $B:$B, H8) -> 0.055756722
A9: 42948 | B9: =YEAR(A9) -> 2017 | C9: =MONTH(A9) -> 8 | D9: {=IFERROR( INDEX( All_India_Index_Upto_April23__1___1[General index], MATCH( 1, (All_India_Index_Upto_April23__1___1[Sector]="Rural+Urban") * (All_India_Index_Upto_April23__1___1[Date]=A9), 0 ) ), "")} -> 135.4 | E9: {=IFERROR( INDEX( All_India_Index_Upto_April23__1___1[General index], MATCH( 1, (All_India_Index_Upto_April23__1___1[Sector]="Rural+Urban") * (All_India_Index_Upto_April23__1___1[Date]=DATE(YEAR(A9)-1, MONTH(A9), 1)), 0 ) ), "")} -> 131.1 | F9: =IFERROR( (D9-E9)/E9, "") -> 0.03279939
A10: 42979 | B10: =YEAR(A10) -> 2017 | C10: =MONTH(A10) -> 9 | D10: {=IFERROR( INDEX( All_India_Index_Upto_April23__1___1[General index], MATCH( 1, (All_India_Index_Upto_April23__1___1[Sector]="Rural+Urban") * (All_India_Index_Upto_April23__1___1[Date]=A10), 0 ) ), "")} -> 135.2 | E10: {=IFERROR( INDEX( All_India_Index_Upto_April23__1___1[General index], MATCH( 1, (All_India_Index_Upto_April23__1___1[Sector]="Rural+Urban") * (All_India_Index_Upto_April23__1___1[Date]=DATE(YEAR(A10)-1, MONTH(A10), 1)), 0 ) ), "")} -> 130.9 | F10: =IFERROR( (D10-E10)/E10, "") -> 0.032849503
A11: 43009 | B11: =YEAR(A11) -> 2017 | C11: =MONTH(A11) -> 10 | D11: {=IFERROR( INDEX( All_India_Index_Upto_April23__1___1[General index], MATCH( 1, (All_India_Index_Upto_April23__1___1[Sector]="Rural+Urban") * (All_India_Index_Upto_April23__1___1[Date]=A11), 0 ) ), "")} -> 136.1 | E11: {=IFERROR( INDEX( All_India_Index_Upto_April23__1___1[General index], MATCH( 1, (All_India_Index_Upto_April23__1___1[Sector]="Rural+Urban") * (All_India_Index_Upto_April23__1___1[Date]=DATE(YEAR(A11)-1, MONTH(A11), 1)), 0 ) ), "")} -> 131.4 | F11: =IFERROR( (D11-E11)/E11, "") -> 0.035768645
A12: 43040 | B12: =YEAR(A12) -> 2017 | C12: =MONTH(A12) -> 11 | D12: {=IFERROR( INDEX( All_India_Index_Upto_April23__1___1[General index], MATCH( 1, (All_India_Index_Upto_April23__1___1[Sector]="Rural+Urban") * (All_India_Index_Upto_April23__1___1[Date]=A12), 0 ) ), "")} -> 137.6 | E12: {=IFERROR( INDEX( All_India_Index_Upto_April23__1___1[General index], MATCH( 1, (All_India_Index_Upto_April23__1___1[Sector]="Rural+Urban") * (All_India_Index_Upto_April23__1___1[Date]=DATE(YEAR(A12)-1, MONTH(A12), 1)), 0 ) ), "")} -> 131.2 | F12: =IFERROR( (D12-E12)/E12, "") -> 0.048780488
A13: 43070 | B13: =YEAR(A13) -> 2017 | C13: =MONTH(A13) -> 12 | D13: {=IFERROR( INDEX( All_India_Index_Upto_April23__1___1[General index], MATCH( 1, (All_India_Index_Upto_April23__1___1[Sector]="Rural+Urban") * (All_India_Index_Upto_April23__1___1[Date]=A13), 0 ) ), "")} -> 137.2 | E13: {=IFERROR( INDEX( All_India_Index_Upto_April23__1___1[General index], MATCH( 1, (All_India_Index_Upto_April23__1___1[Sector]="Rural+Urban") * (All_India_Index_Upto_April23__1___1[Date]=DATE(YEAR(A13)-1, MONTH(A13), 1)), 0 ) ), "")} -> 130.4 | F13: =IFERROR( (D13-E13)/E13, "") -> 0.052147239
A14: 43101 | B14: =YEAR(A14) -> 2018 | C14: =MONTH(A14) -> 1 | D14: {=IFERROR( INDEX( All_India_Index_Upto_April23__1___1[General index], MATCH( 1, (All_India_Index_Upto_April23__1___1[Sector]="Rural+Urban") * (All_India_Index_Upto_April23__1___1[Date]=A14), 0 ) ), "")} -> 136.9 | E14: {=IFERROR( INDEX( All_India_Index_Upto_April23__1___1[General index], MATCH( 1, (All_India_Index_Upto_April23__1___1[Sector]="Rural+Urban") * (All_India_Index_Upto_April23__1___1[Date]=DATE(YEAR(A14)-1, MONTH(A14), 1)), 0 ) ), "")} -> 130.3 | F14: =IFERROR( (D14-E14)/E14, "") -> 0.050652341
A15: 43132 | B15: =YEAR(A15) -> 2018 | C15: =MONTH(A15) -> 2 | D15: {=IFERROR( INDEX( All_India_Index_Upto_April23__1___1[General index], MATCH( 1, (All_India_Index_Upto_April23__1___1[Sector]="Rural+Urban") * (All_India_Index_Upto_April23__1___1[Date]=A15), 0 ) ), "")} -> 136.4 | E15: {=IFERROR( INDEX( All_India_Index_Upto_April23__1___1[General index], MATCH( 1, (All_India_Index_Upto_April23__1___1[Sector]="Rural+Urban") * (All_India_Index_Upto_April23__1___1[Date]=DATE(YEAR(A15)-1, MONTH(A15), 1)), 0 ) ), "")} -> 130.6 | F15: =IFERROR( (D15-E15)/E15, "") -> 0.044410413
A16: 43160 | B16: =YEAR(A16) -> 2018 | C16: =MONTH(A16) -> 3 | D16: {=IFERROR( INDEX( All_India_Index_Upto_April23__1___1[General index], MATCH( 1, (All_India_Index_Upto_April23__1___1[Sector]="Rural+Urban") * (All_India_Index_Upto_April23__1___1[Date]=A16), 0 ) ), "")} -> 136.5 | E16: {=IFERROR( INDEX( All_India_Index_Upto_April23__1___1[General index], MATCH( 1, (All_India_Index_Upto_April23__1___1[Sector]="Rural+Urban") * (All_India_Index_Upto_April23__1___1[Date]=DATE(YEAR(A16)-1, MONTH(A16), 1)), 0 ) ), "")} -> 130.9 | F16: =IFERROR( (D16-E16)/E16, "") -> 0.042780749
A17: 43191 | B17: =YEAR(A17) -> 2018 | C17: =MONTH(A17) -> 4 | D17: {=IFERROR( INDEX( All_India_Index_Upto_April23__1___1[General index], MATCH( 1, (All_India_Index_Upto_April23__1___1[Sector]="Rural+Urban") * (All_India_Index_Upto_April23__1___1[Date]=A17), 0 ) ), "")} -> 137.1 | E17: {=IFERROR( INDEX( All_India_Index_Upto_April23__1___1[General index], MATCH( 1, (All_India_Index_Upto_April23__1___1[Sector]="Rural+Urban") * (All_India_Index_Upto_April23__1___1[Date]=DATE(YEAR(A17)-1, MONTH(A17), 1)), 0 ) ), "")} -> 131.1 | F17: =IFERROR( (D17-E17)/E17, "") -> 0.04576659
A18: 43221 | B18: =YEAR(A18) -> 2018 | C18: =MONTH(A18) -> 5 | D18: {=IFERROR( INDEX( All_India_Index_Upto_April23__1___1[General index], MATCH( 1, (All_India_Index_Upto_April23__1___1[Sector]="Rural+Urban") * (All_India_Index_Upto_April23__1___1[Date]=A18), 0 ) ), "")} -> 137.8 | E18: {=IFERROR( INDEX( All_India_Index_Upto_April23__1___1[General index], MATCH( 1, (All_India_Index_Upto_April23__1___1[Sector]="Rural+Urban") * (All_India_Index_Upto_April23__1___1[Date]=DATE(YEAR(A18)-1, MONTH(A18), 1)), 0 ) ), "")} -> 131.4 | F18: =IFERROR( (D18-E18)/E18, "") -> 0.04870624
A19: 43252 | B19: =YEAR(A19) -> 2018 | C19: =MONTH(A19) -> 6 | D19: {=IFERROR( INDEX( All_India_Index_Upto_April23__1___1[General index], MATCH( 1, (All_India_Index_Upto_April23__1___1[Sector]="Rural+Urban") * (All_India_Index_Upto_April23__1___1[Date]=A19), 0 ) ), "")} -> 138.5 | E19: {=IFERROR( INDEX( All_India_Index_Upto_April23__1___1[General index], MATCH( 1, (All_India_Index_Upto_April23__1___1[Sector]="Rural+Urban") * (All_India_Index_Upto_April23__1___1[Date]=DATE(YEAR(A19)-1, MONTH(A19), 1)), 0 ) ), "")} -> 132 | F19: =IFERROR( (D19-E19)/E19, "") -> 0.049242424
A20: 43282 | B20: =YEAR(A20) -> 2018 | C20: =MONTH(A20) -> 7 | D20: {=IFERROR( INDEX( All_India_Index_Upto_April23__1___1[General index], MATCH( 1, (All_India_Index_Upto_April23__1___1[Sector]="Rural+Urban") * (All_India_Index_Upto_April23__1___1[Date]=A20), 0 ) ), "")} -> 139.8 | E20: {=IFERROR( INDEX( All_India_Index_Upto_April23__1___1[General index], MATCH( 1, (All_India_Index_Upto_April23__1___1[Sector]="Rural+Urban") * (All_India_Index_Upto_April23__1___1[Date]=DATE(YEAR(A20)-1, MONTH(A20), 1)), 0 ) ), "")} -> 134.2 | F20: =IFERROR( (D20-E20)/E20, "") -> 0.041728763
... A85: 45261 | B85: =YEAR(A85) -> 2023 | C85: =MONTH(A85) -> 12 | D85: {=IFERROR( INDEX( All_India_Index_Upto_April23__1___1[General index], MATCH( 1, (All_India_Index_Upto_April23__1___1[Sector]="Rural+Urban") * (All_India_Index_Upto_April23__1___1[Date]=A85), 0 ) ), "")} | E85: {=IFERROR( INDEX( All_India_Index_Upto_April23__1___1[General index], MATCH( 1, (All_India_Index_Upto_April23__1___1[Sector]="Rural+Urban") * (All_India_Index_Upto_April23__1___1[Date]=DATE(YEAR(A85)-1, MONTH(A85), 1)), 0 ) ), "")} -> 175.7 | F85: =IFERROR( (D85-E85)/E85, "")

Sheet Q2_YoY_Inflation_Trend
A1: Year-on-Year (YoY) CPI Inflation Trend Analysis
A2: Scope:
A3: All-India CPI (Rural + Urban combined)
A4: Period Covered: 2017–2023
A5: Base Year: 2012 = 100
A6: Index Used: General CPI Index (Entire Basket)
A8: Objective
A9: To analyse the year-on-year (YoY) inflation trend of the overall CPI basket, identify the year with the highest inflation, and explain the key reasons behind it.
A11: Year-wise YoY Inflation Summary (Table)
A13: Year | B13: Avg YoY Inflation % | C13: Comment
A14: 2017 | B14: 0.033273885
A15: 2018 | B15: 0.039676972
A16: 2019 | B16: 0.037704798
A17: 2020 | B17: 0.062670091 | C17: (Highest)
A18: 2021 | B18: 0.053818467
A19: 2022 | B19: 0.06624065
A20: 2023 | B20: 0.055756722
D24: The YoY CPI inflation peaked in 2020 due to COVID-19 related supply disruptions, food price pressures, and increased healthcare costs.
A26: Key Insights
A27: Insight 1: Inflation was moderate before COVID
A28: • From 2017 to 2019, inflation remained stable between 3–4%
A29: • Indicates relatively balanced demand and supply conditions
A31: Insight 2: Sharp inflation spike during 2020
A32: • 2020 recorded the highest YoY inflation
A33: • This spike is not demand-driven, but supply-side driven
A34: Key reasons:
A35: • Nationwide COVID-19 lockdowns
A36: • Disrupted supply chains
A37: • Shortage of essential goods
A38: • Rising food and healthcare prices
... A58: The YoY CPI inflation trend shows that external shocks (like COVID-19) can significantly impact inflation even when demand is weak. While inflation surged sharply in 2020, subsequent years reflect gradual stabilisation, though price pressures remain higher than pre-COVID levels.

Sheet Sheet2
A1: Date | B1: Food Index (Rural+Urban) | C1: Previous Month Food Index | D1: MoM Food Inflation % | E1: Remark
A2: 44713 | B2: {=IFERROR( INDEX(All_India_Index_Upto_April23__1___1[Food and beverages], MATCH(1, (All_India_Index_Upto_April23__1___1[Sector]="Rural+Urban")* (All_India_Index_Upto_April23__1___1[Date]=A2), 0) ), "")} -> 174.9
A3: 44743 | B3: {=IFERROR( INDEX(All_India_Index_Upto_April23__1___1[Food and beverages], MATCH(1, (All_India_Index_Upto_April23__1___1[Sector]="Rural+Urban")* (All_India_Index_Upto_April23__1___1[Date]=A3), 0) ), "")} -> 175 | C3: =IFERROR(B2,"") -> 174.9 | D3: =IFERROR((B3/C3)-1,"") -> 0.00057175529 | E3: =IF(D3=$A$16,"Highest Inflation", IF(D3=$A$17,"Lowest Inflation",""))
A4: 44774 | B4: {=IFERROR( INDEX(All_India_Index_Upto_April23__1___1[Food and beverages], MATCH(1, (All_India_Index_Upto_April23__1___1[Sector]="Rural+Urban")* (All_India_Index_Upto_April23__1___1[Date]=A4), 0) ), "")} -> 176.3 | C4: =IFERROR(B3,"") -> 175 | D4: =IFERROR((B4/C4)-1,"") -> 0.0074285714 | E4: =IF(D4=$A$16,"Highest Inflation", IF(D4=$A$17,"Lowest Inflation",""))
A5: 44805 | B5: {=IFERROR( INDEX(All_India_Index_Upto_April23__1___1[Food and beverages], MATCH(1, (All_India_Index_Upto_April23__1___1[Sector]="Rural+Urban")* (All_India_Index_Upto_April23__1___1[Date]=A5), 0) ), "")} -> 177.8 | C5: =IFERROR(B4,"") -> 176.3 | D5: =IFERROR((B5/C5)-1,"") -> 0.0085082246 | E5: =IF(D5=$A$16,"Highest Inflation", IF(D5=$A$17,"Lowest Inflation",""))
A6: 44835 | B6: {=IFERROR( INDEX(All_India_Index_Upto_April23__1___1[Food and beverages], MATCH(1, (All_India_Index_Upto_April23__1___1[Sector]="Rural+Urban")* (All_India_Index_Upto_April23__1___1[Date]=A6), 0) ), "")} -> 179.6 | C6: =IFERROR(B5,"") -> 177.8 | D6: =IFERROR((B6/C6)-1,"") -> 0.010123735 | E6: =IF(D6=$A$16,"Highest Inflation", IF(D6=$A$17,"Lowest Inflation","")) -> Highest Inflation
A7: 44866 | B7: {=IFERROR( INDEX(All_India_Index_Upto_April23__1___1[Food and beverages], MATCH(1, (All_India_Index_Upto_April23__1___1[Sector]="Rural+Urban")* (All_India_Index_Upto_April23__1___1[Date]=A7), 0) ), "")} -> 178.3 | C7: =IFERROR(B6,"") -> 179.6 | D7: =IFERROR((B7/C7)-1,"") -> -0.0072383073 | E7: =IF(D7=$A$16,"Highest Inflation", IF(D7=$A$17,"Lowest Inflation",""))
A8: 44896 | B8: {=IFERROR( INDEX(All_India_Index_Upto_April23__1___1[Food and beverages], MATCH(1, (All_India_Index_Upto_April23__1___1[Sector]="Rural+Urban")* (All_India_Index_Upto_April23__1___1[Date]=A8), 0) ), "")} -> 175.9 | C8: =IFERROR(B7,"") -> 178.3 | D8: =IFERROR((B8/C8)-1,"") -> -0.01346046 | E8: =IF(D8=$A$16,"Highest Inflation", IF(D8=$A$17,"Lowest Inflation","")) -> Lowest Inflation
A9: 44927 | B9: {=IFERROR( INDEX(All_India_Index_Upto_April23__1___1[Food and beverages], MATCH(1, (All_India_Index_Upto_April23__1___1[Sector]="Rural+Urban")* (All_India_Index_Upto_April23__1___1[Date]=A9), 0) ), "")} -> 176.7 | C9: =IFERROR(B8,"") -> 175.9 | D9: =IFERROR((B9/C9)-1,"") -> 0.0045480387 | E9: =IF(D9=$A$16,"Highest Inflation", IF(D9=$A$17,"Lowest Inflation",""))
A10: 44958 | B10: {=IFERROR( INDEX(All_India_Index_Upto_April23__1___1[Food and beverages], MATCH(1, (All_India_Index_Upto_April23__1___1[Sector]="Rural+Urban")* (All_India_Index_Upto_April23__1___1[Date]=A10), 0) ), "")} -> 177 | C10: =IFERROR(B9,"") -> 176.7 | D10: =IFERROR((B10/C10)-1,"") -> 0.0016977929 | E10: =IF(D10=$A$16,"Highest Inflation", IF(D10=$A$17,"Lowest Inflation",""))
A11: 44986 | B11: {=IFERROR( INDEX(All_India_Index_Upto_April23__1___1[Food and beverages], MATCH(1, (All_India_Index_Upto_April23__1___1[Sector]="Rural+Urban")* (All_India_Index_Upto_April23__1___1[Date]=A11), 0) ), "")} -> 177 | C11: =IFERROR(B10,"") -> 177 | D11: =IFERROR((B11/C11)-1,"") -> 0 | E11: =IF(D11=$A$16,"Highest Inflation", IF(D11=$A$17,"Lowest Inflation",""))
A12: 45017 | B12: {=IFERROR( INDEX(All_India_Index_Upto_April23__1___1[Food and beverages], MATCH(1, (All_India_Index_Upto_April23__1___1[Sector]="Rural+Urban")* (All_India_Index_Upto_April23__1___1[Date]=A12), 0) ), "")} -> 177.9 | C12: =IFERROR(B11,"") -> 177 | D12: =IFERROR((B12/C12)-1,"") -> 0.0050847458 | E12: =IF(D12=$A$16,"Highest Inflation", IF(D12=$A$17,"Lowest Inflation",""))
A13: 45047 | B13: {=IFERROR( INDEX(All_India_Index_Upto_April23__1___1[Food and beverages], MATCH(1, (All_India_Index_Upto_April23__1___1[Sector]="Rural+Urban")* (All_India_Index_Upto_April23__1___1[Date]=A13), 0) ), "")} -> 179.1 | C13: =IFERROR(B12,"") -> 177.9 | D13: =IFERROR((B13/C13)-1,"") -> 0.0067453626 | E13: =IF(D13=$A$16,"Highest Inflation", IF(D13=$A$17,"Lowest Inflation",""))
A15: Identify Highest & Lowest Food Inflation
A16: =MAX(D3:D13) -> 0.010123735
A17: =MIN(D3:D13) -> -0.01346046
A19: Food Category | B19: Index (Jun-22) | C19: Index (May-23) | D19: Absolute Change | E19: Status
A20: Spices | B20: {=IFERROR( INDEX(All_India_Index_Upto_April23__1___1[#All], MATCH(1, (All_India_Index_Upto_April23__1___1[Date]=DATE(2022,6,1))* (All_India_Index_Upto_April23__1___1[Sector]="Rural+Urban"), 0), MATCH(A20, All_India_Index_Upto_April23__1___1[#Headers],0) ), "")} -> 184.9 | C20: {=IFERROR( INDEX(All_India_Index_Upto_April23__1___1[#All], MATCH(1, (All_India_Index_Upto_April23__1___1[Date]=DATE(2023,5,1))* (All_India_Index_Upto_April23__1___1[Sector]="Rural+Urban"), 0), MATCH(A20, All_India_Index_Upto_April23__1___1[#Headers],0) ), "")} -> 212.9 | D20: =C20 - B20 -> 28 | E20: Highest increase
A21: Cereals and products | B21: {=IFERROR( INDEX(All_India_Index_Upto_April23__1___1[#All], MATCH(1, (All_India_Index_Upto_April23__1___1[Date]=DATE(2022,6,1))* (All_India_Index_Upto_April23__1___1[Sector]="Rural+Urban"), 0), MATCH(A21, All_India_Index_Upto_April23__1___1[#Headers],0) ), "")} -> 154.1 | C21: {=IFERROR( INDEX(All_India_Index_Upto_April23__1___1[#All], MATCH(1, (All_India_Index_Upto_April23__1___1[Date]=DATE(2023,5,1))* (All_India_Index_Upto_April23__1___1[Sector]="Rural+Urban"), 0), MATCH(A21, All_India_Index_Upto_April23__1___1[#Headers],0) ), "")} -> 173.8 | D21: =C21 - B21 -> 19.7 | E21: Large rise
A22: Milk and products | B22: {=IFERROR( INDEX(All_India_Index_Upto_April23__1___1[#All], MATCH(1, (All_India_Index_Upto_April23__1___1[Date]=DATE(2022,6,1))* (All_India_Index_Upto_April23__1___1[Sector]="Rural+Urban"), 0), MATCH(A22, All_India_Index_Upto_April23__1___1[#Headers],0) ), "")} -> 164.9 | C22: {=IFERROR( INDEX(All_India_Index_Upto_April23__1___1[#All], MATCH(1, (All_India_Index_Upto_April23__1___1[Date]=DATE(2023,5,1))* (All_India_Index_Upto_April23__1___1[Sector]="Rural+Urban"), 0), MATCH(A22, All_India_Index_Upto_April23__1___1[#Headers],0) ), "")} -> 178.4 | D22: =C22 - B22 -> 13.5
A23: Prepared meals, snacks, sweets etc. | B23: {=IFERROR( INDEX(All_India_Index_Upto_April23__1___1[#All], MATCH(1, (All_India_Index_Upto_April23__1___1[Date]=DATE(2022,6,1))* (All_India_Index_Upto_April23__1___1[Sector]="Rural+Urban"), 0), MATCH(A23, All_India_Index_Upto_April23__1___1[#Headers],0) ), "")} -> 182.5 | C23: {=IFERROR( INDEX(All_India_Index_Upto_April23__1___1[#All], MATCH(1, (All_India_Index_Upto_April23__1___1[Date]=DATE(2023,5,1))* (All_India_Index_Upto_April23__1___1[Sector]="Rural+Urban"), 0), MATCH(A23, All_India_Index_Upto_April23__1___1[#Headers],0) ), "")} -> 193.5 | D23: =C23 - B23 -> 11
A24: Pulses and products | B24: {=IFERROR( INDEX(All_India_Index_Upto_April23__1___1[#All], MATCH(1, (All_India_Index_Upto_April23__1___1[Date]=DATE(2022,6,1))* (All_India_Index_Upto_April23__1___1[Sector]="Rural+Urban"), 0), MATCH(A24, All_India_Index_Upto_April23__1___1[#Headers],0) ), "")} -> 164.7 | C24: {=IFERROR( INDEX(All_India_Index_Upto_April23__1___1[#All], MATCH(1, (All_India_Index_Upto_April23__1___1[Date]=DATE(2023,5,1))* (All_India_Index_Upto_April23__1___1[Sector]="Rural+Urban"), 0), MATCH(A24, All_India_Index_Upto_April23__1___1[#Headers],0) ), "")} -> 173.4 | D24: =C24 - B24 -> 8.7
A25: Egg | B25: {=IFERROR( INDEX(All_India_Index_Upto_April23__1___1[#All], MATCH(1, (All_India_Index_Upto_April23__1___1[Date]=DATE(2022,6,1))* (All_India_Index_Upto_April23__1___1[Sector]="Rural+Urban"), 0), MATCH(A25, All_India_Index_Upto_April23__1___1[#Headers],0) ), "")} -> 162.4 | C25: {=IFERROR( INDEX(All_India_Index_Upto_April23__1___1[#All], MATCH(1, (All_India_Index_Upto_April23__1___1[Date]=DATE(2023,5,1))* (All_India_Index_Upto_April23__1___1[Sector]="Rural+Urban"), 0), MATCH(A25, All_India_Index_Upto_April23__1___1[#Headers],0) ), "")} -> 169.6 | D25: =C25 - B25 -> 7.2
A26: Non-alcoholic beverages | B26: {=IFERROR( INDEX(All_India_Index_Upto_April23__1___1[#All], MATCH(1, (All_India_Index_Upto_April23__1___1[Date]=DATE(2022,6,1))* (All_India_Index_Upto_April23__1___1[Sector]="Rural+Urban"), 0), MATCH(A26, All_India_Index_Upto_April23__1___1[#Headers],0) ), "")} -> 167.1 | C26: {=IFERROR( INDEX(All_India_Index_Upto_April23__1___1[#All], MATCH(1, (All_India_Index_Upto_April23__1___1[Date]=DATE(2023,5,1))* (All_India_Index_Upto_April23__1___1[Sector]="Rural+Urban"), 0), MATCH(A26, All_India_Index_Upto_April23__1___1[#Headers],0) ), "")} -> 172.9 | D26: =C26 - B26 -> 5.8
A27: Fruits | B27: {=IFERROR( INDEX(All_India_Index_Upto_April23__1___1[#All], MATCH(1, (All_India_Index_Upto_April23__1___1[Date]=DATE(2022,6,1))* (All_India_Index_Upto_April23__1___1[Sector]="Rural+Urban"), 0), MATCH(A27, All_India_Index_Upto_April23__1___1[#Headers],0) ), "")} -> 171 | C27: {=IFERROR( INDEX(All_India_Index_Upto_April23__1___1[#All], MATCH(1, (All_India_Index_Upto_April23__1___1[Date]=DATE(2023,5,1))* (All_India_Index_Upto_April23__1___1[Sector]="Rural+Urban"), 0), MATCH(A27, All_India_Index_Upto_April23__1___1[#Headers],0) ), "")} -> 176.3 | D27: =C27 - B27 -> 5.3
A28: Food and beverages | B28: {=IFERROR( INDEX(All_India_Index_Upto_April23__1___1[#All], MATCH(1, (All_India_Index_Upto_April23__1___1[Date]=DATE(2022,6,1))* (All_India_Index_Upto_April23__1___1[Sector]="Rural+Urban"), 0), MATCH(A28, All_India_Index_Upto_April23__1___1[#Headers],0) ), "")} -> 173.3 | C28: {=IFERROR( INDEX(All_India_Index_Upto_April23__1___1[#All], MATCH(1, (All_India_Index_Upto_April23__1___1[Date]=DATE(2023,5,1))* (All_India_Index_Upto_April23__1___1[Sector]="Rural+Urban"), 0), MATCH(A28, All_India_Index_Upto_April23__1___1[#Headers],0) ), "")} -> 177.9 | D28: =C28 - B28 -> 4.6 | E28: Aggregate
A29: Sugar and Confectionery | B29: {=IFERROR( INDEX(All_India_Index_Upto_April23__1___1[#All], MATCH(1, (All_India_Index_Upto_April23__1___1[Date]=DATE(2022,6,1))* (All_India_Index_Upto_April23__1___1[Sector]="Rural+Urban"), 0), MATCH(A29, All_India_Index_Upto_April23__1___1[#Headers],0) ), "")} -> 119.7 | C29: {=IFERROR( INDEX(All_India_Index_Upto_April23__1___1[#All], MATCH(1, (All_India_Index_Upto_April23__1___1[Date]=DATE(2023,5,1))* (All_India_Index_Upto_April23__1___1[Sector]="Rural+Urban"), 0), MATCH(A29, All_India_Index_Upto_April23__1___1[#Headers],0) ), "")} -> 121.3 | D29: =C29 - B29 -> 1.6 | E29: Stable
A30: Meat and fish | B30: {=IFERROR( INDEX(All_India_Index_Upto_April23__1___1[#All], MATCH(1, (All_India_Index_Upto_April23__1___1[Date]=DATE(2022,6,1))* (All_India_Index_Upto_April23__1___1[Sector]="Rural+Urban"), 0), MATCH(A30, All_India_Index_Upto_April23__1___1[#Headers],0) ), "")} -> 217 | C30: {=IFERROR( INDEX(All_India_Index_Upto_April23__1___1[#All], MATCH(1, (All_India_Index_Upto_April23__1___1[Date]=DATE(2023,5,1))* (All_India_Index_Upto_April23__1___1[Sector]="Rural+Urban"), 0), MATCH(A30, All_India_Index_Upto_April23__1___1[#Headers],0) ), "")} -> 209.3 | D30: =C30 - B30 -> -7.7 | E30: Price correction
A31: Vegetables | B31: {=IFERROR( INDEX(All_India_Index_Upto_April23__1___1[#All], MATCH(1, (All_India_Index_Upto_April23__1___1[Date]=DATE(2022,6,1))* (All_India_Index_Upto_April23__1___1[Sector]="Rural+Urban"), 0), MATCH(A31, All_India_Index_Upto_April23__1___1[#Headers],0) ), "")} -> 174.9 | C31: {=IFERROR( INDEX(All_India_Index_Upto_April23__1___1[#All], MATCH(1, (All_India_Index_Upto_April23__1___1[Date]=DATE(2023,5,1))* (All_India_Index_Upto_April23__1___1[Sector]="Rural+Urban"), 0), MATCH(A31, All_India_Index_Upto_April23__1___1[#Headers],0) ), "")} -> 155.4 | D31: =C31 - B31 -> -19.5 | E31: Strong volatility
A32: Oils and fats | B32: {=IFERROR( INDEX(All_India_Index_Upto_April23__1___1[#All], MATCH(1, (All_India_Index_Upto_April23__1___1[Date]=DATE(2022,6,1))* (All_India_Index_Upto_April23__1___1[Sector]="Rural+Urban"), 0), MATCH(A32, All_India_Index_Upto_April23__1___1[#Headers],0) ), "")} -> 202.4 | C32: {=IFERROR( INDEX(All_India_Index_Upto_April23__1___1[#All], MATCH(1, (All_India_Index_Upto_April23__1___1[Date]=DATE(2023,5,1))* (All_India_Index_Upto_April23__1___1[Sector]="Rural+Urban"), 0), MATCH(A32, All_India_Index_Upto_April23__1___1[#Headers],0) ), "")} -> 174.9 | D32: =C32 - B32 -> -27.5 | E32: Sharp fall
A34: Identify the Biggest Contributor
A35: =MAX(D20:D32) -> 28
A36: =MIN(D20:D32) -> -27.5

Sheet Q3_Food_Inflation
A1: Food Inflation Analysis (12 Months Ending May 2023)
A2: India’s retail inflation touched a 3-month high of 5.55% in November 2023, driven largely by rising food prices.
A3: To understand this pressure, we analyze food inflation trends over the 12-month period from June 2022 to May 2023, focusing on both monthly movements and category-level contributions.
A5: Part A: Month-on-Month (MoM) Trend in Food Inflation
A6: Objective | B6: To study how food prices changed month by month, and identify the highest and lowest food inflation months.
A8: Methodology
A9: • Used Food Index (Rural + Urban) values for each month.
A10: • MoM Food Inflation %= Current Month Index – Previous Month Index​/Previous Month Index X 100
A12: Date | B12: Food Index (Rural+Urban) | C12: Previous Month Food Index | D12: MoM Food Inflation % | E12: Remark
A13: 44713 | B13: {=IFERROR( INDEX(All_India_Index_Upto_April23__1___1[Food and beverages], MATCH(1, (All_India_Index_Upto_April23__1___1[Sector]="Rural+Urban")* (All_India_Index_Upto_April23__1___1[Date]=A13), 0) ), "")} -> 174.9
A14: 44743 | B14: {=IFERROR( INDEX(All_India_Index_Upto_April23__1___1[Food and beverages], MATCH(1, (All_India_Index_Upto_April23__1___1[Sector]="Rural+Urban")* (All_India_Index_Upto_April23__1___1[Date]=A14), 0) ), "")} -> 175 | C14: =IFERROR(B13,"") -> 174.9 | D14: =IFERROR((B14/C14)-1,"") -> 0.00057175529
A15: 44774 | B15: {=IFERROR( INDEX(All_India_Index_Upto_April23__1___1[Food and beverages], MATCH(1, (All_India_Index_Upto_April23__1___1[Sector]="Rural+Urban")* (All_India_Index_Upto_April23__1___1[Date]=A15), 0) ), "")} -> 176.3 | C15: =IFERROR(B14,"") -> 175 | D15: =IFERROR((B15/C15)-1,"") -> 0.0074285714
A16: 44805 | B16: {=IFERROR( INDEX(All_India_Index_Upto_April23__1___1[Food and beverages], MATCH(1, (All_India_Index_Upto_April23__1___1[Sector]="Rural+Urban")* (All_India_Index_Upto_April23__1___1[Date]=A16), 0) ), "")} -> 177.8 | C16: =IFERROR(B15,"") -> 176.3 | D16: =IFERROR((B16/C16)-1,"") -> 0.0085082246
A17: 44835 | B17: {=IFERROR( INDEX(All_India_Index_Upto_April23__1___1[Food and beverages], MATCH(1, (All_India_Index_Upto_April23__1___1[Sector]="Rural+Urban")* (All_India_Index_Upto_April23__1___1[Date]=A17), 0) ), "")} -> 179.6 | C17: =IFERROR(B16,"") -> 177.8 | D17: =IFERROR((B17/C17)-1,"") -> 0.010123735 | E17: Highest Inflation
A18: 44866 | B18: {=IFERROR( INDEX(All_India_Index_Upto_April23__1___1[Food and beverages], MATCH(1, (All_India_Index_Upto_April23__1___1[Sector]="Rural+Urban")* (All_India_Index_Upto_April23__1___1[Date]=A18), 0) ), "")} -> 178.3 | C18: =IFERROR(B17,"") -> 179.6 | D18: =IFERROR((B18/C18)-1,"") -> -0.0072383073
A19: 44896 | B19: {=IFERROR( INDEX(All_India_Index_Upto_April23__1___1[Food and beverages], MATCH(1, (All_India_Index_Upto_April23__1___1[Sector]="Rural+Urban")* (All_India_Index_Upto_April23__1___1[Date]=A19), 0) ), "")} -> 175.9 | C19: =IFERROR(B18,"") -> 178.3 | D19: =IFERROR((B19/C19)-1,"") -> -0.01346046 | E19: Lowest Inflation
A20: 44927 | B20: {=IFERROR( INDEX(All_India_Index_Upto_April23__1___1[Food and beverages], MATCH(1, (All_India_Index_Upto_April23__1___1[Sector]="Rural+Urban")* (All_India_Index_Upto_April23__1___1[Date]=A20), 0) ), "")} -> 176.7 | C20: =IFERROR(B19,"") -> 175.9 | D20: =IFERROR((B20/C20)-1,"") -> 0.0045480387
A21: 44958 | B21: {=IFERROR( INDEX(All_India_Index_Upto_April23__1___1[Food and beverages], MATCH(1, (All_India_Index_Upto_April23__1___1[Sector]="Rural+Urban")* (All_India_Index_Upto_April23__1___1[Date]=A21), 0) ), "")} -> 177 | C21: =IFERROR(B20,"") -> 176.7 | D21: =IFERROR((B21/C21)-1,"") -> 0.0016977929
A22: 44986 | B22: {=IFERROR( INDEX(All_India_Index_Upto_April23__1___1[Food and beverages], MATCH(1, (All_India_Index_Upto_April23__1___1[Sector]="Rural+Urban")* (All_India_Index_Upto_April23__1___1[Date]=A22), 0) ), "")} -> 177 | C22: =IFERROR(B21,"") -> 177 | D22: =IFERROR((B22/C22)-1,"") -> 0
A23: 45017 | B23: {=IFERROR( INDEX(All_India_Index_Upto_April23__1___1[Food and beverages], MATCH(1, (All_India_Index_Upto_April23__1___1[Sector]="Rural+Urban")* (All_India_Index_Upto_April23__1___1[Date]=A23), 0) ), "")} -> 177.9 | C23: =IFERROR(B22,"") -> 177 | D23: =IFERROR((B23/C23)-1,"") -> 0.0050847458
A24: 45047 | B24: {=IFERROR( INDEX(All_India_Index_Upto_April23__1___1[Food and beverages], MATCH(1, (All_India_Index_Upto_April23__1___1[Sector]="Rural+Urban")* (All_India_Index_Upto_April23__1___1[Date]=A24), 0) ), "")} -> 179.1 | C24: =IFERROR(B23,"") -> 177.9 | D24: =IFERROR((B24/C24)-1,"") -> 0.0067453626
A49: Key Findings from MoM Analysis
A50: Highest Food Inflation:
A51: 📌 October 2022 (+1.0%)
A52: • Driven by seasonal price pressures in cereals, spices, and prepared food items.
A53: • Festive demand also contributed to higher food prices.
A54: Lowest Food Inflation:
A55: 📌 December 2022 (-1.3%)
A56: • Reflects correction in vegetable prices and easing supply constraints.
A57: • Improved harvest and supply conditions reduced overall food inflation.
A58: Overall Trend: | B58: Food inflation was volatile in mid-2022, peaked around Oct-22, corrected sharply in Dec-22, and remained moderate but positive in early 2023.
A60: Insight
A61: Food inflation during this period was not linear. It was driven by seasonal and supply-side factors, with sharp month-to-month fluctuations rather than a steady rise.
A63: Part B: Absolute Price Changes & Biggest Contributor (Within Food Category)
A64: Objective
A65: To identify:
A66: 1. Absolute price changes across food categories between June 2022 and May 2023
A67: 2. The single largest contributor to food inflation
A69: Methodology
A70: • Compared index values in Jun-22 vs May-23 for each food item.
A71: • Calculated Absolute Change as: Absolute Change=Index (May-23)−Index (Jun-22)
A73: Food Category | B73: Index (Jun-22) | C73: Index (May-23) | D73: Absolute Change | E73: Status
A74: Spices | B74: {=IFERROR( INDEX(All_India_Index_Upto_April23__1___1[#All], MATCH(1, (All_India_Index_Upto_April23__1___1[Date]=DATE(2022,6,1))* (All_India_Index_Upto_April23__1___1[Sector]="Rural+Urban"), 0), MATCH(A74, All_India_Index_Upto_April23__1___1[#Headers],0) ), "")} -> 184.9 | C74: {=IFERROR( INDEX(All_India_Index_Upto_April23__1___1[#All], MATCH(1, (All_India_Index_Upto_April23__1___1[Date]=DATE(2023,5,1))* (All_India_Index_Upto_April23__1___1[Sector]="Rural+Urban"), 0), MATCH(A74, All_India_Index_Upto_April23__1___1[#Headers],0) ), "")} -> 212.9 | D74: =C74 - B74 -> 28 | E74: Highest increase
A75: Cereals and products | B75: {=IFERROR( INDEX(All_India_Index_Upto_April23__1___1[#All], MATCH(1, (All_India_Index_Upto_April23__1___1[Date]=DATE(2022,6,1))* (All_India_Index_Upto_April23__1___1[Sector]="Rural+Urban"), 0), MATCH(A75, All_India_Index_Upto_April23__1___1[#Headers],0) ), "")} -> 154.1 | C75: {=IFERROR( INDEX(All_India_Index_Upto_April23__1___1[#All], MATCH(1, (All_India_Index_Upto_April23__1___1[Date]=DATE(2023,5,1))* (All_India_Index_Upto_April23__1___1[Sector]="Rural+Urban"), 0), MATCH(A75, All_India_Index_Upto_April23__1___1[#Headers],0) ), "")} -> 173.8 | D75: =C75 - B75 -> 19.7 | E75: Large rise
A76: Milk and products | B76: {=IFERROR( INDEX(All_India_Index_Upto_April23__1___1[#All], MATCH(1, (All_India_Index_Upto_April23__1___1[Date]=DATE(2022,6,1))* (All_India_Index_Upto_April23__1___1[Sector]="Rural+Urban"), 0), MATCH(A76, All_India_Index_Upto_April23__1___1[#Headers],0) ), "")} -> 164.9 | C76: {=IFERROR( INDEX(All_India_Index_Upto_April23__1___1[#All], MATCH(1, (All_India_Index_Upto_April23__1___1[Date]=DATE(2023,5,1))* (All_India_Index_Upto_April23__1___1[Sector]="Rural+Urban"), 0), MATCH(A76, All_India_Index_Upto_April23__1___1[#Headers],0) ), "")} -> 178.4 | D76: =C76 - B76 -> 13.5
A77: Prepared meals, snacks, sweets etc. | B77: {=IFERROR( INDEX(All_India_Index_Upto_April23__1___1[#All], MATCH(1, (All_India_Index_Upto_April23__1___1[Date]=DATE(2022,6,1))* (All_India_Index_Upto_April23__1___1[Sector]="Rural+Urban"), 0), MATCH(A77, All_India_Index_Upto_April23__1___1[#Headers],0) ), "")} -> 182.5 | C77: {=IFERROR( INDEX(All_India_Index_Upto_April23__1___1[#All], MATCH(1, (All_India_Index_Upto_April23__1___1[Date]=DATE(2023,5,1))* (All_India_Index_Upto_April23__1___1[Sector]="Rural+Urban"), 0), MATCH(A77, All_India_Index_Upto_April23__1___1[#Headers],0) ), "")} -> 193.5 | D77: =C77 - B77 -> 11
A78: Pulses and products | B78: {=IFERROR( INDEX(All_India_Index_Upto_April23__1___1[#All], MATCH(1, (All_India_Index_Upto_April23__1___1[Date]=DATE(2022,6,1))* (All_India_Index_Upto_April23__1___1[Sector]="Rural+Urban"), 0), MATCH(A78, All_India_Index_Upto_April23__1___1[#Headers],0) ), "")} -> 164.7 | C78: {=IFERROR( INDEX(All_India_Index_Upto_April23__1___1[#All], MATCH(1, (All_India_Index_Upto_April23__1___1[Date]=DATE(2023,5,1))* (All_India_Index_Upto_April23__1___1[Sector]="Rural+Urban"), 0), MATCH(A78, All_India_Index_Upto_April23__1___1[#Headers],0) ), "")} -> 173.4 | D78: =C78 - B78 -> 8.7
A79: Egg | B79: {=IFERROR( INDEX(All_India_Index_Upto_April23__1___1[#All], MATCH(1, (All_India_Index_Upto_April23__1___1[Date]=DATE(2022,6,1))* (All_India_Index_Upto_April23__1___1[Sector]="Rural+Urban"), 0), MATCH(A79, All_India_Index_Upto_April23__1___1[#Headers],0) ), "")} -> 162.4 | C79: {=IFERROR( INDEX(All_India_Index_Upto_April23__1___1[#All], MATCH(1, (All_India_Index_Upto_April23__1___1[Date]=DATE(2023,5,1))* (All_India_Index_Upto_April23__1___1[Sector]="Rural+Urban"), 0), MATCH(A79, All_India_Index_Upto_April23__1___1[#Headers],0) ), "")} -> 169.6 | D79: =C79 - B79 -> 7.2
A80: Non-alcoholic beverages | B80: {=IFERROR( INDEX(All_India_Index_Upto_April23__1___1[#All], MATCH(1, (All_India_Index_Upto_April23__1___1[Date]=DATE(2022,6,1))* (All_India_Index_Upto_April23__1___1[Sector]="Rural+Urban"), 0), MATCH(A80, All_India_Index_Upto_April23__1___1[#Headers],0) ), "")} -> 167.1 | C80: {=IFERROR( INDEX(All_India_Index_Upto_April23__1___1[#All], MATCH(1, (All_India_Index_Upto_April23__1___1[Date]=DATE(2023,5,1))* (All_India_Index_Upto_April23__1___1[Sector]="Rural+Urban"), 0), MATCH(A80, All_India_Index_Upto_April23__1___1[#Headers],0) ), "")} -> 172.9 | D80: =C80 - B80 -> 5.8
A81: Fruits | B81: {=IFERROR( INDEX(All_India_Index_Upto_April23__1___1[#All], MATCH(1, (All_India_Index_Upto_April23__1___1[Date]=DATE(2022,6,1))* (All_India_Index_Upto_April23__1___1[Sector]="Rural+Urban"), 0), MATCH(A81, All_India_Index_Upto_April23__1___1[#Headers],0) ), "")} -> 171 | C81: {=IFERROR( INDEX(All_India_Index_Upto_April23__1___1[#All], MATCH(1, (All_India_Index_Upto_April23__1___1[Date]=DATE(2023,5,1))* (All_India_Index_Upto_April23__1___1[Sector]="Rural+Urban"), 0), MATCH(A81, All_India_Index_Upto_April23__1___1[#Headers],0) ), "")} -> 176.3 | D81: =C81 - B81 -> 5.3
A82: Food and beverages | B82: {=IFERROR( INDEX(All_India_Index_Upto_April23__1___1[#All], MATCH(1, (All_India_Index_Upto_April23__1___1[Date]=DATE(2022,6,1))* (All_India_Index_Upto_April23__1___1[Sector]="Rural+Urban"), 0), MATCH(A82, All_India_Index_Upto_April23__1___1[#Headers],0) ), "")} -> 173.3 | C82: {=IFERROR( INDEX(All_India_Index_Upto_April23__1___1[#All], MATCH(1, (All_India_Index_Upto_April23__1___1[Date]=DATE(2023,5,1))* (All_India_Index_Upto_April23__1___1[Sector]="Rural+Urban"), 0), MATCH(A82, All_India_Index_Upto_April23__1___1[#Headers],0) ), "")} -> 177.9 | D82: =C82 - B82 -> 4.6 | E82: Aggregate
A83: Sugar and Confectionery | B83: {=IFERROR( INDEX(All_India_Index_Upto_April23__1___1[#All], MATCH(1, (All_India_Index_Upto_April23__1___1[Date]=DATE(2022,6,1))* (All_India_Index_Upto_April23__1___1[Sector]="Rural+Urban"), 0), MATCH(A83, All_India_Index_Upto_April23__1___1[#Headers],0) ), "")} -> 119.7 | C83: {=IFERROR( INDEX(All_India_Index_Upto_April23__1___1[#All], MATCH(1, (All_India_Index_Upto_April23__1___1[Date]=DATE(2023,5,1))* (All_India_Index_Upto_April23__1___1[Sector]="Rural+Urban"), 0), MATCH(A83, All_India_Index_Upto_April23__1___1[#Headers],0) ), "")} -> 121.3 | D83: =C83 - B83 -> 1.6 | E83: Stable
A84: Meat and fish | B84: {=IFERROR( INDEX(All_India_Index_Upto_April23__1___1[#All], MATCH(1, (All_India_Index_Upto_April23__1___1[Date]=DATE(2022,6,1))* (All_India_Index_Upto_April23__1___1[Sector]="Rural+Urban"), 0), MATCH(A84, All_India_Index_Upto_April23__1___1[#Headers],0) ), "")} -> 217 | C84: {=IFERROR( INDEX(All_India_Index_Upto_April23__1___1[#All], MATCH(1, (All_India_Index_Upto_April23__1___1[Date]=DATE(2023,5,1))* (All_India_Index_Upto_April23__1___1[Sector]="Rural+Urban"), 0), MATCH(A84, All_India_Index_Upto_April23__1___1[#Headers],0) ), "")} -> 209.3 | D84: =C84 - B84 -> -7.7 | E84: Price correction
A85: Vegetables | B85: {=IFERROR( INDEX(All_India_Index_Upto_April23__1___1[#All], MATCH(1, (All_India_Index_Upto_April23__1___1[Date]=DATE(2022,6,1))* (All_India_Index_Upto_April23__1___1[Sector]="Rural+Urban"), 0), MATCH(A85, All_India_Index_Upto_April23__1___1[#Headers],0) ), "")} -> 174.9 | C85: {=IFERROR( INDEX(All_India_Index_Upto_April23__1___1[#All], MATCH(1, (All_India_Index_Upto_April23__1___1[Date]=DATE(2023,5,1))* (All_India_Index_Upto_April23__1___1[Sector]="Rural+Urban"), 0), MATCH(A85, All_India_Index_Upto_April23__1___1[#Headers],0) ), "")} -> 155.4 | D85: =C85 - B85 -> -19.5 | E85: Strong volatility
A86: Oils and fats | B86: {=IFERROR( INDEX(All_India_Index_Upto_April23__1___1[#All], MATCH(1, (All_India_Index_Upto_April23__1___1[Date]=DATE(2022,6,1))* (All_India_Index_Upto_April23__1___1[Sector]="Rural+Urban"), 0), MATCH(A86, All_India_Index_Upto_April23__1___1[#Headers],0) ), "")} -> 202.4 | C86: {=IFERROR( INDEX(All_India_Index_Upto_April23__1___1[#All], MATCH(1, (All_India_Index_Upto_April23__1___1[Date]=DATE(2023,5,1))* (All_India_Index_Upto_April23__1___1[Sector]="Rural+Urban"), 0), MATCH(A86, All_India_Index_Upto_April23__1___1[#Headers],0) ), "")} -> 174.9 | D86: =C86 - B86 -> -27.5 | E86: Sharp fall
A120: Absolute Change in Food Categories (Jun-22 to May-23)
A121: Top Positive Contributors
A122: 1. Spices: +28.0
A123: 2. Cereals and Products: +19.7
A124: 3. Milk and Products: +13.5
A125: 4. Prepared Meals, Snacks & Sweets: +11.0
A126: Categories Showing Decline
A127: 1. Oils and Fats: -27.5
A128: 2. Vegetables: -19.5
A130: Biggest Individual Contributor to Food Inflation
A131: 📌 Spices
A132: • Recorded the highest absolute increase (+28 points).
... A145: • The analysis confirms that supply-side pressures and essential food items, rather than discretionary consumption, were the main inflation drivers.

Sheet Sheet8
A1: Date | B1: Year | C1: Month | D1: General Index (Rural + Urban) | E1: Prev Year Index | F1: YoY Inflation % | G1: COVID_Flag | I1: Period | J1: Avg YoY Inflation % | L1: Period | M1: Avg Food Inflation % | O1: Food Index (R+U) | P1: Prev Year Food Index | Q1: Food YoY Inflation % | R1: COVID_Flag | T1: Health Index (R+U) | U1: Prev Year Health Index | V1: Health YoY Inflation % | W1: COVID_Flag | Y1: Other Index (R+U) | Z1: Prev Year Other Index | AA1: Other YoY Inflation % | AB1: COVID_Flag | AD1: Category | AE1: Pre-COVID | AF1: COVID
A2: 42736 | B2: 2017 | C2: January | D2: {=IFERROR( INDEX( All_India_Index_Upto_April23__1___1[General index], MATCH( 1, (All_India_Index_Upto_April23__1___1[Sector]="Rural+Urban") * (All_India_Index_Upto_April23__1___1[Date]=A2), 0 ) ), "")} -> 130.3 | E2: {=IFERROR( INDEX( All_India_Index_Upto_April23__1___1[General index], MATCH( 1, (All_India_Index_Upto_April23__1___1[Sector]="Rural+Urban") * (All_India_Index_Upto_April23__1___1[Date]=EDATE(A2,-12)), 0 ) ), "")} -> 126.3 | F2: =IF(OR(E2="",D2=""),NA(),(D2/E2)-1) -> 0.031670625 | G2: =IF(A2<DATE(2020,3,1), "Pre-COVID", IF(A2<DATE(2022,4,1), "COVID", "Post-COVID" ) ) -> Pre-COVID | I2: Pre-COVID | J2: =AVERAGEIFS( F:F, G:G, "Pre-COVID" ) -> 0.038698799 | L2: Pre-COVID | M2: =AVERAGEIFS( Q:Q, R:R, "Pre-COVID" ) -> 0.021608001 | O2: {=IFERROR( AVERAGE( INDEX(All_India_Index_Upto_April23__1___1[Cereals and products], MATCH(1,(All_India_Index_Upto_April23__1___1[Date]=$A2)* (All_India_Index_Upto_April23__1___1[Sector]="Rural+Urban"),0)), INDEX(All_India_Index_Upto_April23__1___1[Meat and fish], MATCH(1,(All_India_Index_Upto_April23__1___1[Date]=$A2)* (All_India_Index_Upto_April23__1___1[Sector]="Rural+Urban"),0)), INDEX(All_India_Index_Upto_April23__1___1[Egg], MATCH(1,(All_India_Index_Upto_April23__1___1[Date]=$A2)* (All_India_Index_Upto_April23__1___1[Sector]="Rural+Urban"),0)), INDEX(All_India_Index_Upto_April23__1___1[Milk and products], MATCH(1,(All_India_Index_Upto_April23__1___1[Date]=$A2)* (All_India_Index_Upto_April23__1___1[Sector]="Rural+Urban"),0)), INDEX(All_India_Index_Upto_April23__1___1[Oils and fats], MATCH(1,(All_India_Index_Upto_April23__1___1[Date]=$A2)* (All_India_Index_Upto_April23__1___1[Sector]="Rural+Urban"),0)), INDEX(All_India_Index_Upto_April23__1___1[Fruits], MATCH(1,(All_India_Index_Upto_April23__1___1[Date]=$A2)* (All_India_Index_Upto_April23__1___1[Sector]="Rural+Urban"),0)), INDEX(All_India_Index_Upto_April23__1___1[Vegetables], MATCH(1,(All_India_Index_Upto_April23__1___1[Date]=$A2)* (All_India_Index_Upto_April23__1___1[Sector]="Rural+Urban"),0)), INDEX(All_India_Index_Upto_April23__1___1[Pulses and products], MATCH(1,(All_India_Index_Upto_April23__1___1[Date]=$A2)* (All_India_Index_Upto_April23__1___1[Sector]="Rural+Urban"),0)), INDEX(All_India_Index_Upto_April23__1___1[Sugar and Confectionery], MATCH(1,(All_India_Index_Upto_April23__1___1[Date]=$A2)* (All_India_Index_Upto_April23__1___1[Sector]="Rural+Urban"),0)), INDEX(All_India_Index_Upto_April23__1___1[Spices], MATCH(1,(All_India_Index_Upto_April23__1___1[Date]=$A2)* (All_India_Index_Upto_April23__1___1[Sector]="Rural+Urban"),0)), INDEX(All_India_Index_Upto_April23__1___1[Non-alcoholic beverages], MATCH(1,(All_India_Index_Upto_April23__1___1[Date]=$A2)* (All_India_Index_Upto_April23__1___1[Sector]="Rural+Urban"),0)), INDEX(All_India_Index_Upto_April23__1___1[Prepared meals, snacks, sweets etc.], MATCH(1,(All_India_Index_Upto_April23__1___1[Date]=$A2)* (All_India_Index_Upto_April23__1___1[Sector]="Rural+Urban"),0)) ), "")} -> 132.85 | P2: {=IFERROR( AVERAGE( INDEX(All_India_Index_Upto_April23__1___1[Cereals and products], MATCH(1,(All_India_Index_Upto_April23__1___1[Date]=EDATE($A2,-12))* (All_India_Index_Upto_April23__1___1[Sector]="Rural+Urban"),0)), INDEX(All_India_Index_Upto_April23__1___1[Meat and fish], MATCH(1,(All_India_Index_Upto_April23__1___1[Date]=EDATE($A2,-12))* (All_India_Index_Upto_April23__1___1[Sector]="Rural+Urban"),0)), INDEX(All_India_Index_Upto_April23__1___1[Egg], MATCH(1,(All_India_Index_Upto_April23__1___1[Date]=EDATE($A2,-12))* (All_India_Index_Upto_April23__1___1[Sector]="Rural+Urban"),0)), INDEX(All_India_Index_Upto_April23__1___1[Milk and products], MATCH(1,(All_India_Index_Upto_April23__1___1[Date]=EDATE($A2,-12))* (All_India_Index_Upto_April23__1___1[Sector]="Rural+Urban"),0)), INDEX(All_India_Index_Upto_April23__1___1[Oils and fats], MATCH(1,(All_India_Index_Upto_April23__1___1[Date]=EDATE($A2,-12))* (All_India_Index_Upto_April23__1___1[Sector]="Rural+Urban"),0)), INDEX(All_India_Index_Upto_April23__1___1[Fruits], MATCH(1,(All_India_Index_Upto_April23__1___1[Date]=EDATE($A2,-12))* (All_India_Index_Upto_April23__1___1[Sector]="Rural+Urban"),0)), INDEX(All_India_Index_Upto_April23__1___1[Vegetables], MATCH(1,(All_India_Index_Upto_April23__1___1[Date]=EDATE($A2,-12))* (All_India_Index_Upto_April23__1___1[Sector]="Rural+Urban"),0)), INDEX(All_India_Index_Upto_April23__1___1[Pulses and products], MATCH(1,(All_India_Index_Upto_April23__1___1[Date]=EDATE($A2,-12))* (All_India_Index_Upto_April23__1___1[Sector]="Rural+Urban"),0)), INDEX(All_India_Index_Upto_April23__1___1[Sugar and Confectionery], MATCH(1,(All_India_Index_Upto_April23__1___1[Date]=EDATE($A2,-12))* (All_India_Index_Upto_April23__1___1[Sector]="Rural+Urban"),0)), INDEX(All_India_Index_Upto_April23__1___1[Spices], MATCH(1,(All_India_Index_Upto_April23__1___1[Date]=EDATE($A2,-12))* (All_India_Index_Upto_April23__1___1[Sector]="Rural+Urban"),0)), INDEX(All_India_Index_Upto_April23__1___1[Non-alcoholic beverages], MATCH(1,(All_India_Index_Upto_April23__1___1[Date]=EDATE($A2,-12))* (All_India_Index_Upto_April23__1___1[Sector]="Rural+Urban"),0)), INDEX(All_India_Index_Upto_April23__1___1[Prepared meals, snacks, sweets etc.], MATCH(1,(All_India_Index_Upto_April23__1___1[Date]=EDATE($A2,-12))* (All_India_Index_Upto_April23__1___1[Sector]="Rural+Urban"),0)) ), "")} -> 130.03333 | Q2: =IFERROR((O2-P2)/P2,"") -> 0.021661113 | R2: =IF(A2<DATE(2020,3,1), "Pre-COVID", IF(A2<DATE(2022,4,1), "COVID", "Post-COVID" ) ) -> Pre-COVID | T2: {=IFERROR( INDEX( All_India_Index_Upto_April23__1___1[Health], MATCH( 1, (All_India_Index_Upto_April23__1___1[Date]=$A2) * (All_India_Index_Upto_April23__1___1[Sector]="Rural+Urban"), 0 ) ), "")} -> 127.1 | U2: {=IFERROR( INDEX( All_India_Index_Upto_April23__1___1[Health], MATCH( 1, (All_India_Index_Upto_April23__1___1[Date]=EDATE($A2,-12)) * (All_India_Index_Upto_April23__1___1[Sector]="Rural+Urban"), 0 ) ), "")} -> 122 | V2: =IFERROR((T2-U2)/U2,"") -> 0.041803279 | W2: =IF(A2<DATE(2020,3,1), "Pre-COVID", IF(A2<DATE(2022,4,1), "COVID", "Post-COVID" ) ) -> Pre-COVID | Y2: {=IFERROR( AVERAGE( INDEX(All_India_Index_Upto_April23__1___1[Pan, tobacco and intoxicants], MATCH(1,(All_India_Index_Upto_April23__1___1[Date]=$A2)* (All_India_Index_Upto_April23__1___1[Sector]="Rural+Urban"),0)), INDEX(All_India_Index_Upto_April23__1___1[Clothing], MATCH(1,(All_India_Index_Upto_April23__1___1[Date]=$A2)* (All_India_Index_Upto_April23__1___1[Sector]="Rural+Urban"),0)), INDEX(All_India_Index_Upto_April23__1___1[Footwear], MATCH(1,(All_India_Index_Upto_April23__1___1[Date]=$A2)* (All_India_Index_Upto_April23__1___1[Sector]="Rural+Urban"),0)), INDEX(All_India_Index_Upto_April23__1___1[Clothing and footwear], MATCH(1,(All_India_Index_Upto_April23__1___1[Date]=$A2)* (All_India_Index_Upto_April23__1___1[Sector]="Rural+Urban"),0)), INDEX(All_India_Index_Upto_April23__1___1[Housing], MATCH(1,(All_India_Index_Upto_April23__1___1[Date]=$A2)* (All_India_Index_Upto_April23__1___1[Sector]="Rural+Urban"),0)), INDEX(All_India_Index_Upto_April23__1___1[Fuel and light], MATCH(1,(All_India_Index_Upto_April23__1___1[Date]=$A2)* (All_India_Index_Upto_April23__1___1[Sector]="Rural+Urban"),0)), INDEX(All_India_Index_Upto_April23__1___1[Household goods and services], MATCH(1,(All_India_Index_Upto_April23__1___1[Date]=$A2)* (All_India_Index_Upto_April23__1___1[Sector]="Rural+Urban"),0)), INDEX(All_India_Index_Upto_April23__1___1[Health], MATCH(1,(All_India_Index_Upto_April23__1___1[Date]=$A2)* (All_India_Index_Upto_April23__1___1[Sector]="Rural+Urban"),0)), INDEX(All_India_Index_Upto_April23__1___1[Transport and communication], MATCH(1,(All_India_Index_Upto_April23__1___1[Date]=$A2)* (All_India_Index_Upto_April23__1___1[Sector]="Rural+Urban"),0)), INDEX(All_India_Index_Upto_April23__1___1[Recreation and amusement], MATCH(1,(All_India_Index_Upto_April23__1___1[Date]=$A2)* (All_India_Index_Upto_April23__1___1[Sector]="Rural+Urban"),0)), INDEX(All_India_Index_Upto_April23__1___1[Education], MATCH(1,(All_India_Index_Upto_April23__1___1[Date]=$A2)* (All_India_Index_Upto_April23__1___1[Sector]="Rural+Urban"),0)), INDEX(All_India_Index_Upto_April23__1___1[Personal care and effects], MATCH(1,(All_India_Index_Upto_April23__1___1[Date]=$A2)* (All_India_Index_Upto_April23__1___1[Sector]="Rural+Urban"),0)), INDEX(All_India_Index_Upto_April23__1___1[Miscellaneous], MATCH(1,(All_India_Index_Upto_April23__1___1[Date]=$A2)* (All_India_Index_Upto_April23__1___1[Sector]="Rural+Urban"),0)) ), "")} -> 129.175 | Z2: {=IFERROR( AVERAGE( INDEX(All_India_Index_Upto_April23__1___1[Pan, tobacco and intoxicants], MATCH(1,(All_India_Index_Upto_April23__1___1[Date]=EDATE($A2,-12))* (All_India_Index_Upto_April23__1___1[Sector]="Rural+Urban"),0)), INDEX(All_India_Index_Upto_April23__1___1[Clothing], MATCH(1,(All_India_Index_Upto_April23__1___1[Date]=EDATE($A2,-12))* (All_India_Index_Upto_April23__1___1[Sector]="Rural+Urban"),0)), INDEX(All_India_Index_Upto_April23__1___1[Footwear], MATCH(1,(All_India_Index_Upto_April23__1___1[Date]=EDATE($A2,-12))* (All_India_Index_Upto_April23__1___1[Sector]="Rural+Urban"),0)), INDEX(All_India_Index_Upto_April23__1___1[Clothing and footwear], MATCH(1,(All_India_Index_Upto_April23__1___1[Date]=EDATE($A2,-12))* (All_India_Index_Upto_April23__1___1[Sector]="Rural+Urban"),0)), INDEX(All_India_Index_Upto_April23__1___1[Housing], MATCH(1,(All_India_Index_Upto_April23__1___1[Date]=EDATE($A2,-12))* (All_India_Index_Upto_April23__1___1[Sector]="Rural+Urban"),0)), INDEX(All_India_Index_Upto_April23__1___1[Fuel and light], MATCH(1,(All_India_Index_Upto_April23__1___1[Date]=EDATE($A2,-12))* (All_India_Index_Upto_April23__1___1[Sector]="Rural+Urban"),0)), INDEX(All_India_Index_Upto_April23__1___1[Household goods and services], MATCH(1,(All_India_Index_Upto_April23__1___1[Date]=EDATE($A2,-12))* (All_India_Index_Upto_April23__1___1[Sector]="Rural+Urban"),0)), INDEX(All_India_Index_Upto_April23__1___1[Health], MATCH(1,(All_India_Index_Upto_April23__1___1[Date]=EDATE($A2,-12))* (All_India_Index_Upto_April23__1___1[Sector]="Rural+Urban"),0)), INDEX(All_India_Index_Upto_April23__1___1[Transport and communication], MATCH(1,(All_India_Index_Upto_April23__1___1[Date]=EDATE($A2,-12))* (All_India_Index_Upto_April23__1___1[Sector]="Rural+Urban"),0)), INDEX(All_India_Index_Upto_April23__1___1[Recreation and amusement], MATCH(1,(All_India_Index_Upto_April23__1___1[Date]=EDATE($A2,-12))* (All_India_Index_Upto_April23__1___1[Sector]="Rural+Urban"),0)), INDEX(All_India_Index_Upto_April23__1___1[Education], MATCH(1,(All_India_Index_Upto_April23__1___1[Date]=EDATE($A2,-12))* (All_India_Index_Upto_April23__1___1[Sector]="Rural+Urban"),0)), INDEX(All_India_Index_Upto_April23__1___1[Personal care and effects], MATCH(1,(All_India_Index_Upto_April23__1___1[Date]=EDATE($A2,-12))* (All_India_Index_Upto_April23__1___1[Sector]="Rural+Urban"),0)), INDEX(All_India_Index_Upto_April23__1___1[Miscellaneous], MATCH(1,(All_India_Index_Upto_April23__1___1[Date]=EDATE($A2,-12))* (All_India_Index_Upto_April23__1___1[Sector]="Rural+Urban"),0)) ), "")} -> 123.26667 | AA2: =IFERROR((Y2-Z2)/Z2,"") -> 0.047931314 | AB2: =IF(A2<DATE(2020,3,1), "Pre-COVID", IF(A2<DATE(2022,4,1), "COVID", "Post-COVID" ) ) -> Pre-COVID | AD2: Overall CPI | AE2: 0.039 | AF2: 0.057
A3: 42767 | B3: 2017 | C3: February | D3: {=IFERROR( INDEX( All_India_Index_Upto_April23__1___1[General index], MATCH( 1, (All_India_Index_Upto_April23__1___1[Sector]="Rural+Urban") * (All_India_Index_Upto_April23__1___1[Date]=A3), 0 ) ), "")} -> 130.6 | E3: {=IFERROR( INDEX( All_India_Index_Upto_April23__1___1[General index], MATCH( 1, (All_India_Index_Upto_April23__1___1[Sector]="Rural+Urban") * (All_India_Index_Upto_April23__1___1[Date]=EDATE(A3,-12)), 0 ) ), "")} -> 126 | F3: =IF(OR(E3="",D3=""),NA(),(D3/E3)-1) -> 0.036507937 | G3: =IF(A3<DATE(2020,3,1), "Pre-COVID", IF(A3<DATE(2022,4,1), "COVID", "Post-COVID" ) ) -> Pre-COVID | I3: COVID | J3: =AVERAGEIFS( F:F, G:G, "COVID" ) -> #N/A | L3: COVID | M3: =AVERAGEIFS( Q:Q, R:R, "COVID" ) -> #N/A | O3: {=IFERROR( AVERAGE( INDEX(All_India_Index_Upto_April23__1___1[Cereals and products], MATCH(1,(All_India_Index_Upto_April23__1___1[Date]=$A3)* (All_India_Index_Upto_April23__1___1[Sector]="Rural+Urban"),0)), INDEX(All_India_Index_Upto_April23__1___1[Meat and fish], MATCH(1,(All_India_Index_Upto_April23__1___1[Date]=$A3)* (All_India_Index_Upto_April23__1___1[Sector]="Rural+Urban"),0)), INDEX(All_India_Index_Upto_April23__1___1[Egg], MATCH(1,(All_India_Index_Upto_April23__1___1[Date]=$A3)* (All_India_Index_Upto_April23__1___1[Sector]="Rural+Urban"),0)), INDEX(All_India_Index_Upto_April23__1___1[Milk and products], MATCH(1,(All_India_Index_Upto_April23__1___1[Date]=$A3)* (All_India_Index_Upto_April23__1___1[Sector]="Rural+Urban"),0)), INDEX(All_India_Index_Upto_April23__1___1[Oils and fats], MATCH(1,(All_India_Index_Upto_April23__1___1[Date]=$A3)* (All_India_Index_Upto_April23__1___1[Sector]="Rural+Urban"),0)), INDEX(All_India_Index_Upto_April23__1___1[Fruits], MATCH(1,(All_India_Index_Upto_April23__1___1[Date]=$A3)* (All_India_Index_Upto_April23__1___1[Sector]="Rural+Urban"),0)), INDEX(All_India_Index_Upto_April23__1___1[Vegetables], MATCH(1,(All_India_Index_Upto_April23__1___1[Date]=$A3)* (All_India_Index_Upto_April23__1___1[Sector]="Rural+Urban"),0)), INDEX(All_India_Index_Upto_April23__1___1[Pulses and products], MATCH(1,(All_India_Index_Upto_April23__1___1[Date]=$A3)* (All_India_Index_Upto_April23__1___1[Sector]="Rural+Urban"),0)), INDEX(All_India_Index_Upto_April23__1___1[Sugar and Confectionery], MATCH(1,(All_India_Index_Upto_April23__1___1[Date]=$A3)* (All_India_Index_Upto_April23__1___1[Sector]="Rural+Urban"),0)), INDEX(All_India_Index_Upto_April23__1___1[Spices], MATCH(1,(All_India_Index_Upto_April23__1___1[Date]=$A3)* (All_India_Index_Upto_April23__1___1[Sector]="Rural+Urban"),0)), INDEX(All_India_Index_Upto_April23__1___1[Non-alcoholic beverages], MATCH(1,(All_India_Index_Upto_April23__1___1[Date]=$A3)* (All_India_Index_Upto_April23__1___1[Sector]="Rural+Urban"),0)), INDEX(All_India_Index_Upto_April23__1___1[Prepared meals, snacks, sweets etc.], MATCH(1,(All_India_Index_Upto_April23__1___1[Date]=$A3)* (All_India_Index_Upto_April23__1___1[Sector]="Rural+Urban"),0)) ), "")} -> 132.44167 | P3: {=IFERROR( AVERAGE( INDEX(All_India_Index_Upto_April23__1___1[Cereals and products], MATCH(1,(All_India_Index_Upto_April23__1___1[Date]=EDATE($A3,-12))* (All_India_Index_Upto_April23__1___1[Sector]="Rural+Urban"),0)), INDEX(All_India_Index_Upto_April23__1___1[Meat and fish], MATCH(1,(All_India_Index_Upto_April23__1___1[Date]=EDATE($A3,-12))* (All_India_Index_Upto_April23__1___1[Sector]="Rural+Urban"),0)), INDEX(All_India_Index_Upto_April23__1___1[Egg], MATCH(1,(All_India_Index_Upto_April23__1___1[Date]=EDATE($A3,-12))* (All_India_Index_Upto_April23__1___1[Sector]="Rural+Urban"),0)), INDEX(All_India_Index_Upto_April23__1___1[Milk and products], MATCH(1,(All_India_Index_Upto_April23__1___1[Date]=EDATE($A3,-12))* (All_India_Index_Upto_April23__1___1[Sector]="Rural+Urban"),0)), INDEX(All_India_Index_Upto_April23__1___1[Oils and fats], MATCH(1,(All_India_Index_Upto_April23__1___1[Date]=EDATE($A3,-12))* (All_India_Index_Upto_April23__1___1[Sector]="Rural+Urban"),0)), INDEX(All_India_Index_Upto_April23__1___1[Fruits], MATCH(1,(All_India_Index_Upto_April23__1___1[Date]=EDATE($A3,-12))* (All_India_Index_Upto_April23__1___1[Sector]="Rural+Urban"),0)), INDEX(All_India_Index_Upto_April23__1___1[Vegetables], MATCH(1,(All_India_Index_Upto_April23__1___1[Date]=EDATE($A3,-12))* (All_India_Index_Upto_April23__1___1[Sector]="Rural+Urban"),0)), INDEX(All_India_Index_Upto_April23__1___1[Pulses and products], MATCH(1,(All_India_Index_Upto_April23__1___1[Date]=EDATE($A3,-12))* (All_India_Index_Upto_April23__1___1[Sector]="Rural+Urban"),0)), INDEX(All_India_Index_Upto_April23__1___1[Sugar and Confectionery], MATCH(1,(All_India_Index_Upto_April23__1___1[Date]=EDATE($A3,-12))* (All_India_Index_Upto_April23__1___1[Sector]="Rural+Urban"),0)), INDEX(All_India_Index_Upto_April23__1___1[Spices], MATCH(1,(All_India_Index_Upto_April23__1___1[Date]=EDATE($A3,-12))* (All_India_Index_Upto_April23__1___1[Sector]="Rural+Urban"),0)), INDEX(All_India_Index_Upto_April23__1___1[Non-alcoholic beverages], MATCH(1,(All_India_Index_Upto_April23__1___1[Date]=EDATE($A3,-12))* (All_India_Index_Upto_April23__1___1[Sector]="Rural+Urban"),0)), INDEX(All_India_Index_Upto_April23__1___1[Prepared meals, snacks, sweets etc.], MATCH(1,(All_India_Index_Upto_April23__1___1[Date]=EDATE($A3,-12))* (All_India_Index_Upto_April23__1___1[Sector]="Rural+Urban"),0)) ), "")} -> 129.01667 | Q3: =IFERROR((O3-P3)/P3,"") -> 0.026546958 | R3: =IF(A3<DATE(2020,3,1), "Pre-COVID", IF(A3<DATE(2022,4,1), "COVID", "Post-COVID" ) ) -> Pre-COVID | T3: {=IFERROR( INDEX( All_India_Index_Upto_April23__1___1[Health], MATCH( 1, (All_India_Index_Upto_April23__1___1[Date]=$A3) * (All_India_Index_Upto_April23__1___1[Sector]="Rural+Urban"), 0 ) ), "")} -> 127.4 | U3: {=IFERROR( INDEX( All_India_Index_Upto_April23__1___1[Health], MATCH( 1, (All_India_Index_Upto_April23__1___1[Date]=EDATE($A3,-12)) * (All_India_Index_Upto_April23__1___1[Sector]="Rural+Urban"), 0 ) ), "")} -> 122.5 | V3: =IFERROR((T3-U3)/U3,"") -> 0.04 | W3: =IF(A3<DATE(2020,3,1), "Pre-COVID", IF(A3<DATE(2022,4,1), "COVID", "Post-COVID" ) ) -> Pre-COVID | Y3: {=IFERROR( AVERAGE( INDEX(All_India_Index_Upto_April23__1___1[Pan, tobacco and intoxicants], MATCH(1,(All_India_Index_Upto_April23__1___1[Date]=$A3)* (All_India_Index_Upto_April23__1___1[Sector]="Rural+Urban"),0)), INDEX(All_India_Index_Upto_April23__1___1[Clothing], MATCH(1,(All_India_Index_Upto_April23__1___1[Date]=$A3)* (All_India_Index_Upto_April23__1___1[Sector]="Rural+Urban"),0)), INDEX(All_India_Index_Upto_April23__1___1[Footwear], MATCH(1,(All_India_Index_Upto_April23__1___1[Date]=$A3)* (All_India_Index_Upto_April23__1___1[Sector]="Rural+Urban"),0)), INDEX(All_India_Index_Upto_April23__1___1[Clothing and footwear], MATCH(1,(All_India_Index_Upto_April23__1___1[Date]=$A3)* (All_India_Index_Upto_April23__1___1[Sector]="Rural+Urban"),0)), INDEX(All_India_Index_Upto_April23__1___1[Housing], MATCH(1,(All_India_Index_Upto_April23__1___1[Date]=$A3)* (All_India_Index_Upto_April23__1___1[Sector]="Rural+Urban"),0)), INDEX(All_India_Index_Upto_April23__1___1[Fuel and light], MATCH(1,(All_India_Index_Upto_April23__1___1[Date]=$A3)* (All_India_Index_Upto_April23__1___1[Sector]="Rural+Urban"),0)), INDEX(All_India_Index_Upto_April23__1___1[Household goods and services], MATCH(1,(All_India_Index_Upto_April23__1___1[Date]=$A3)* (All_India_Index_Upto_April23__1___1[Sector]="Rural+Urban"),0)), INDEX(All_India_Index_Upto_April23__1___1[Health], MATCH(1,(All_India_Index_Upto_April23__1___1[Date]=$A3)* (All_India_Index_Upto_April23__1___1[Sector]="Rural+Urban"),0)), INDEX(All_India_Index_Upto_April23__1___1[Transport and communication], MATCH(1,(All_India_Index_Upto_April23__1___1[Date]=$A3)* (All_India_Index_Upto_April23__1___1[Sector]="Rural+Urban"),0)), INDEX(All_India_Index_Upto_April23__1___1[Recreation and amusement], MATCH(1,(All_India_Index_Upto_April23__1___1[Date]=$A3)* (All_India_Index_Upto_April23__1___1[Sector]="Rural+Urban"),0)), INDEX(All_India_Index_Upto_April23__1___1[Education], MATCH(1,(All_India_Index_Upto_April23__1___1[Date]=$A3)* (All_India_Index_Upto_April23__1___1[Sector]="Rural+Urban"),0)), INDEX(All_India_Index_Upto_April23__1___1[Personal care and effects], MATCH(1,(All_India_Index_Upto_April23__1___1[Date]=$A3)* (All_India_Index_Upto_April23__1___1[Sector]="Rural+Urban"),0)), INDEX(All_India_Index_Upto_April23__1___1[Miscellaneous], MATCH(1,(All_India_Index_Upto_April23__1___1[Date]=$A3)* (All_India_Index_Upto_April23__1___1[Sector]="Rural+Urban"),0)) ), "")} -> 129.6 | Z3: {=IFERROR( AVERAGE( INDEX(All_India_Index_Upto_April23__1___1[Pan, tobacco and intoxicants], MATCH(1,(All_India_Index_Upto_April23__1___1[Date]=EDATE($A3,-12))* (All_India_Index_Upto_April23__1___1[Sector]="Rural+Urban"),0)), INDEX(All_India_Index_Upto_April23__1___1[Clothing], MATCH(1,(All_India_Index_Upto_April23__1___1[Date]=EDATE($A3,-12))* (All_India_Index_Upto_April23__1___1[Sector]="Rural+Urban"),0)), INDEX(All_India_Index_Upto_April23__1___1[Footwear], MATCH(1,(All_India_Index_Upto_April23__1___1[Date]=EDATE($A3,-12))* (All_India_Index_Upto_April23__1___1[Sector]="Rural+Urban"),0)), INDEX(All_India_Index_Upto_April23__1___1[Clothing and footwear], MATCH(1,(All_India_Index_Upto_April23__1___1[Date]=EDATE($A3,-12))* (All_India_Index_Upto_April23__1___1[Sector]="Rural+Urban"),0)), INDEX(All_India_Index_Upto_April23__1___1[Housing], MATCH(1,(All_India_Index_Upto_April23__1___1[Date]=EDATE($A3,-12))* (All_India_Index_Upto_April23__1___1[Sector]="Rural+Urban"),0)), INDEX(All_India_Index_Upto_April23__1___1[Fuel and light], MATCH(1,(All_India_Index_Upto_April23__1___1[Date]=EDATE($A3,-12))* (All_India_Index_Upto_April23__1___1[Sector]="Rural+Urban"),0)), INDEX(All_India_Index_Upto_April23__1___1[Household goods and services], MATCH(1,(All_India_Index_Upto_April23__1___1[Date]=EDATE($A3,-12))* (All_India_Index_Upto_April23__1___1[Sector]="Rural+Urban"),0)), INDEX(All_India_Index_Upto_April23__1___1[Health], MATCH(1,(All_India_Index_Upto_April23__1___1[Date]=EDATE($A3,-12))* (All_India_Index_Upto_April23__1___1[Sector]="Rural+Urban"),0)), INDEX(All_India_Index_Upto_April23__1___1[Transport and communication], MATCH(1,(All_India_Index_Upto_April23__1___1[Date]=EDATE($A3,-12))* (All_India_Index_Upto_April23__1___1[Sector]="Rural+Urban"),0)), INDEX(All_India_Index_Upto_April23__1___1[Recreation and amusement], MATCH(1,(All_India_Index_Upto_April23__1___1[Date]=EDATE($A3,-12))* (All_India_Index_Upto_April23__1___1[Sector]="Rural+Urban"),0)), INDEX(All_India_Index_Upto_April23__1___1[Education], MATCH(1,(All_India_Index_Upto_April23__1___1[Date]=EDATE($A3,-12))* (All_India_Index_Upto_April23__1___1[Sector]="Rural+Urban"),0)), INDEX(All_India_Index_Upto_April23__1___1[Personal care and effects], MATCH(1,(All_India_Index_Upto_April23__1___1[Date]=EDATE($A3,-12))* (All_India_Index_Upto_April23__1___1[Sector]="Rural+Urban"),0)), INDEX(All_India_Index_Upto_April23__1___1[Miscellaneous], MATCH(1,(All_India_Index_Upto_April23__1___1[Date]=EDATE($A3,-12))* (All_India_Index_Upto_April23__1___1[Sector]="Rural+Urban"),0)) ), "")} -> 123.91667 | AA3: =IFERROR((Y3-Z3)/Z3,"") -> 0.045864156 | AB3: =IF(A3<DATE(2020,3,1), "Pre-COVID", IF(A3<DATE(2022,4,1), "COVID", "Post-COVID" ) ) -> Pre-COVID | AD3: Food | AE3: 0.022 | AF3: 0.073
A4: 42795 | B4: 2017 | C4: March | D4: {=IFERROR( INDEX( All_India_Index_Upto_April23__1___1[General index], MATCH( 1, (All_India_Index_Upto_April23__1___1[Sector]="Rural+Urban") * (All_India_Index_Upto_April23__1___1[Date]=A4), 0 ) ), "")} -> 130.9 | E4: {=IFERROR( INDEX( All_India_Index_Upto_April23__1___1[General index], MATCH( 1, (All_India_Index_Upto_April23__1___1[Sector]="Rural+Urban") * (All_India_Index_Upto_April23__1___1[Date]=EDATE(A4,-12)), 0 ) ), "")} -> 126 | F4: =IF(OR(E4="",D4=""),NA(),(D4/E4)-1) -> 0.038888889 | G4: =IF(A4<DATE(2020,3,1), "Pre-COVID", IF(A4<DATE(2022,4,1), "COVID", "Post-COVID" ) ) -> Pre-COVID | O4: {=IFERROR( AVERAGE( INDEX(All_India_Index_Upto_April23__1___1[Cereals and products], MATCH(1,(All_India_Index_Upto_April23__1___1[Date]=$A4)* (All_India_Index_Upto_April23__1___1[Sector]="Rural+Urban"),0)), INDEX(All_India_Index_Upto_April23__1___1[Meat and fish], MATCH(1,(All_India_Index_Upto_April23__1___1[Date]=$A4)* (All_India_Index_Upto_April23__1___1[Sector]="Rural+Urban"),0)), INDEX(All_India_Index_Upto_April23__1___1[Egg], MATCH(1,(All_India_Index_Upto_April23__1___1[Date]=$A4)* (All_India_Index_Upto_April23__1___1[Sector]="Rural+Urban"),0)), INDEX(All_India_Index_Upto_April23__1___1[Milk and products], MATCH(1,(All_India_Index_Upto_April23__1___1[Date]=$A4)* (All_India_Index_Upto_April23__1___1[Sector]="Rural+Urban"),0)), INDEX(All_India_Index_Upto_April23__1___1[Oils and fats], MATCH(1,(All_India_Index_Upto_April23__1___1[Date]=$A4)* (All_India_Index_Upto_April23__1___1[Sector]="Rural+Urban"),0)), INDEX(All_India_Index_Upto_April23__1___1[Fruits], MATCH(1,(All_India_Index_Upto_April23__1___1[Date]=$A4)* (All_India_Index_Upto_April23__1___1[Sector]="Rural+Urban"),0)), INDEX(All_India_Index_Upto_April23__1___1[Vegetables], MATCH(1,(All_India_Index_Upto_April23__1___1[Date]=$A4)* (All_India_Index_Upto_April23__1___1[Sector]="Rural+Urban"),0)), INDEX(All_India_Index_Upto_April23__1___1[Pulses and products], MATCH(1,(All_India_Index_Upto_April23__1___1[Date]=$A4)* (All_India_Index_Upto_April23__1___1[Sector]="Rural+Urban"),0)), INDEX(All_India_Index_Upto_April23__1___1[Sugar and Confectionery], MATCH(1,(All_India_Index_Upto_April23__1___1[Date]=$A4)* (All_India_Index_Upto_April23__1___1[Sector]="Rural+Urban"),0)), INDEX(All_India_Index_Upto_April23__1___1[Spices], MATCH(1,(All_India_Index_Upto_April23__1___1[Date]=$A4)* (All_India_Index_Upto_April23__1___1[Sector]="Rural+Urban"),0)), INDEX(All_India_Index_Upto_April23__1___1[Non-alcoholic beverages], MATCH(1,(All_India_Index_Upto_April23__1___1[Date]=$A4)* (All_India_Index_Upto_April23__1___1[Sector]="Rural+Urban"),0)), INDEX(All_India_Index_Upto_April23__1___1[Prepared meals, snacks, sweets etc.], MATCH(1,(All_India_Index_Upto_April23__1___1[Date]=$A4)* (All_India_Index_Upto_April23__1___1[Sector]="Rural+Urban"),0)) ), "")} -> 132.15 | P4: {=IFERROR( AVERAGE( INDEX(All_India_Index_Upto_April23__1___1[Cereals and products], MATCH(1,(All_India_Index_Upto_April23__1___1[Date]=EDATE($A4,-12))* (All_India_Index_Upto_April23__1___1[Sector]="Rural+Urban"),0)), INDEX(All_India_Index_Upto_April23__1___1[Meat and fish], MATCH(1,(All_India_Index_Upto_April23__1___1[Date]=EDATE($A4,-12))* (All_India_Index_Upto_April23__1___1[Sector]="Rural+Urban"),0)), INDEX(All_India_Index_Upto_April23__1___1[Egg], MATCH(1,(All_India_Index_Upto_April23__1___1[Date]=EDATE($A4,-12))* (All_India_Index_Upto_April23__1___1[Sector]="Rural+Urban"),0)), INDEX(All_India_Index_Upto_April23__1___1[Milk and products], MATCH(1,(All_India_Index_Upto_April23__1___1[Date]=EDATE($A4,-12))* (All_India_Index_Upto_April23__1___1[Sector]="Rural+Urban"),0)), INDEX(All_India_Index_Upto_April23__1___1[Oils and fats], MATCH(1,(All_India_Index_Upto_April23__1___1[Date]=EDATE($A4,-12))* (All_India_Index_Upto_April23__1___1[Sector]="Rural+Urban"),0)), INDEX(All_India_Index_Upto_April23__1___1[Fruits], MATCH(1,(All_India_Index_Upto_April23__1___1[Date]=EDATE($A4,-12))* (All_India_Index_Upto_April23__1___1[Sector]="Rural+Urban"),0)), INDEX(All_India_Index_Upto_April23__1___1[Vegetables], MATCH(1,(All_India_Index_Upto_April23__1___1[Date]=EDATE($A4,-12))* (All_India_Index_Upto_April23__1___1[Sector]="Rural+Urban"),0)), INDEX(All_India_Index_Upto_April23__1___1[Pulses and products], MATCH(1,(All_India_Index_Upto_April23__1___1[Date]=EDATE($A4,-12))* (All_India_Index_Upto_April23__1___1[Sector]="Rural+Urban"),0)), INDEX(All_India_Index_Upto_April23__1___1[Sugar and Confectionery], MATCH(1,(All_India_Index_Upto_April23__1___1[Date]=EDATE($A4,-12))* (All_India_Index_Upto_April23__1___1[Sector]="Rural+Urban"),0)), INDEX(All_India_Index_Upto_April23__1___1[Spices], MATCH(1,(All_India_Index_Upto_April23__1___1[Date]=EDATE($A4,-12))* (All_India_Index_Upto_April23__1___1[Sector]="Rural+Urban"),0)), INDEX(All_India_Index_Upto_April23__1___1[Non-alcoholic beverages], MATCH(1,(All_India_Index_Upto_April23__1___1[Date]=EDATE($A4,-12))* (All_India_Index_Upto_April23__1___1[Sector]="Rural+Urban"),0)), INDEX(All_India_Index_Upto_April23__1___1[Prepared meals, snacks, sweets etc.], MATCH(1,(All_India_Index_Upto_April23__1___1[Date]=EDATE($A4,-12))* (All_India_Index_Upto_April23__1___1[Sector]="Rural+Urban"),0)) ), "")} -> 128.78333 | Q4: =IFERROR((O4-P4)/P4,"") -> 0.026142099 | R4: =IF(A4<DATE(2020,3,1), "Pre-COVID", IF(A4<DATE(2022,4,1), "COVID", "Post-COVID" ) ) -> Pre-COVID | T4: {=IFERROR( INDEX( All_India_Index_Upto_April23__1___1[Health], MATCH( 1, (All_India_Index_Upto_April23__1___1[Date]=$A4) * (All_India_Index_Upto_April23__1___1[Sector]="Rural+Urban"), 0 ) ), "")} -> 127.8 | U4: {=IFERROR( INDEX( All_India_Index_Upto_April23__1___1[Health], MATCH( 1, (All_India_Index_Upto_April23__1___1[Date]=EDATE($A4,-12)) * (All_India_Index_Upto_April23__1___1[Sector]="Rural+Urban"), 0 ) ), "")} -> 122.9 | V4: =IFERROR((T4-U4)/U4,"") -> 0.039869813 | W4: =IF(A4<DATE(2020,3,1), "Pre-COVID", IF(A4<DATE(2022,4,1), "COVID", "Post-COVID" ) ) -> Pre-COVID | Y4: {=IFERROR( AVERAGE( INDEX(All_India_Index_Upto_April23__1___1[Pan, tobacco and intoxicants], MATCH(1,(All_India_Index_Upto_April23__1___1[Date]=$A4)* (All_India_Index_Upto_April23__1___1[Sector]="Rural+Urban"),0)), INDEX(All_India_Index_Upto_April23__1___1[Clothing], MATCH(1,(All_India_Index_Upto_April23__1___1[Date]=$A4)* (All_India_Index_Upto_April23__1___1[Sector]="Rural+Urban"),0)), INDEX(All_India_Index_Upto_April23__1___1[Footwear], MATCH(1,(All_India_Index_Upto_April23__1___1[Date]=$A4)* (All_India_Index_Upto_April23__1___1[Sector]="Rural+Urban"),0)), INDEX(All_India_Index_Upto_April23__1___1[Clothing and footwear], MATCH(1,(All_India_Index_Upto_April23__1___1[Date]=$A4)* (All_India_Index_Upto_April23__1___1[Sector]="Rural+Urban"),0)), INDEX(All_India_Index_Upto_April23__1___1[Housing], MATCH(1,(All_India_Index_Upto_April23__1___1[Date]=$A4)* (All_India_Index_Upto_April23__1___1[Sector]="Rural+Urban"),0)), INDEX(All_India_Index_Upto_April23__1___1[Fuel and light], MATCH(1,(All_India_Index_Upto_April23__1___1[Date]=$A4)* (All_India_Index_Upto_April23__1___1[Sector]="Rural+Urban"),0)), INDEX(All_India_Index_Upto_April23__1___1[Household goods and services], MATCH(1,(All_India_Index_Upto_April23__1___1[Date]=$A4)* (All_India_Index_Upto_April23__1___1[Sector]="Rural+Urban"),0)), INDEX(All_India_Index_Upto_April23__1___1[Health], MATCH(1,(All_India_Index_Upto_April23__1___1[Date]=$A4)* (All_India_Index_Upto_April23__1___1[Sector]="Rural+Urban"),0)), INDEX(All_India_Index_Upto_April23__1___1[Transport and communication], MATCH(1,(All_India_Index_Upto_April23__1___1[Date]=$A4)* (All_India_Index_Upto_April23__1___1[Sector]="Rural+Urban"),0)), INDEX(All_India_Index_Upto_April23__1___1[Recreation and amusement], MATCH(1,(All_India_Index_Upto_April23__1___1[Date]=$A4)* (All_India_Index_Upto_April23__1___1[Sector]="Rural+Urban"),0)), INDEX(All_India_Index_Upto_April23__1___1[Education], MATCH(1,(All_India_Index_Upto_April23__1___1[Date]=$A4)* (All_India_Index_Upto_April23__1___1[Sector]="Rural+Urban"),0)), INDEX(All_India_Index_Upto_April23__1___1[Personal care and effects], MATCH(1,(All_India_Index_Upto_April23__1___1[Date]=$A4)* (All_India_Index_Upto_April23__1___1[Sector]="Rural+Urban"),0)), INDEX(All_India_Index_Upto_April23__1___1[Miscellaneous], MATCH(1,(All_India_Index_Upto_April23__1___1[Date]=$A4)* (All_India_Index_Upto_April23__1___1[Sector]="Rural+Urban"),0)) ), "")} -> 130.04167 | Z4: {=IFERROR( AVERAGE( INDEX(All_India_Index_Upto_April23__1___1[Pan, tobacco and intoxicants], MATCH(1,(All_India_Index_Upto_April23__1___1[Date]=EDATE($A4,-12))* (All_India_Index_Upto_April23__1___1[Sector]="Rural+Urban"),0)), INDEX(All_India_Index_Upto_April23__1___1[Clothing], MATCH(1,(All_India_Index_Upto_April23__1___1[Date]=EDATE($A4,-12))* (All_India_Index_Upto_April23__1___1[Sector]="Rural+Urban"),0)), INDEX(All_India_Index_Upto_April23__1___1[Footwear], MATCH(1,(All_India_Index_Upto_April23__1___1[Date]=EDATE($A4,-12))* (All_India_Index_Upto_April23__1___1[Sector]="Rural+Urban"),0)), INDEX(All_India_Index_Upto_April23__1___1[Clothing and footwear], MATCH(1,(All_India_Index_Upto_April23__1___1[Date]=EDATE($A4,-12))* (All_India_Index_Upto_April23__1___1[Sector]="Rural+Urban"),0)), INDEX(All_India_Index_Upto_April23__1___1[Housing], MATCH(1,(All_India_Index_Upto_April23__1___1[Date]=EDATE($A4,-12))* (All_India_Index_Upto_April23__1___1[Sector]="Rural+Urban"),0)), INDEX(All_India_Index_Upto_April23__1___1[Fuel and light], MATCH(1,(All_India_Index_Upto_April23__1___1[Date]=EDATE($A4,-12))* (All_India_Index_Upto_April23__1___1[Sector]="Rural+Urban"),0)), INDEX(All_India_Index_Upto_April23__1___1[Household goods and services], MATCH(1,(All_India_Index_Upto_April23__1___1[Date]=EDATE($A4,-12))* (All_India_Index_Upto_April23__1___1[Sector]="Rural+Urban"),0)), INDEX(All_India_Index_Upto_April23__1___1[Health], MATCH(1,(All_India_Index_Upto_April23__1___1[Date]=EDATE($A4,-12))* (All_India_Index_Upto_April23__1___1[Sector]="Rural+Urban"),0)), INDEX(All_India_Index_Upto_April23__1___1[Transport and communication], MATCH(1,(All_India_Index_Upto_April23__1___1[Date]=EDATE($A4,-12))* (All_India_Index_Upto_April23__1___1[Sector]="Rural+Urban"),0)), INDEX(All_India_Index_Upto_April23__1___1[Recreation and amusement], MATCH(1,(All_India_Index_Upto_April23__1___1[Date]=EDATE($A4,-12))* (All_India_Index_Upto_April23__1___1[Sector]="Rural+Urban"),0)), INDEX(All_India_Index_Upto_April23__1___1[Education], MATCH(1,(All_India_Index_Upto_April23__1___1[Date]=EDATE($A4,-12))* (All_India_Index_Upto_April23__1___1[Sector]="Rural+Urban"),0)), INDEX(All_India_Index_Upto_April23__1___1[Personal care and effects], MATCH(1,(All_India_Index_Upto_April23__1___1[Date]=EDATE($A4,-12))* (All_India_Index_Upto_April23__1___1[Sector]="Rural+Urban"),0)), INDEX(All_India_Index_Upto_April23__1___1[Miscellaneous], MATCH(1,(All_India_Index_Upto_April23__1___1[Date]=EDATE($A4,-12))* (All_India_Index_Upto_April23__1___1[Sector]="Rural+Urban"),0)) ), "")} -> 124.15 | AA4: =IFERROR((Y4-Z4)/Z4,"") -> 0.047456034 | AB4: =IF(A4<DATE(2020,3,1), "Pre-COVID", IF(A4<DATE(2022,4,1), "COVID", "Post-COVID" ) ) -> Pre-COVID | AD4: Health | AE4: 0.058 | AF4: 0.064
A5: 42826 | B5: 2017 | C5: April | D5: {=IFERROR( INDEX( All_India_Index_Upto_April23__1___1[General index], MATCH( 1, (All_India_Index_Upto_April23__1___1[Sector]="Rural+Urban") * (All_India_Index_Upto_April23__1___1[Date]=A5), 0 ) ), "")} -> 131.1 | E5: {=IFERROR( INDEX( All_India_Index_Upto_April23__1___1[General index], MATCH( 1, (All_India_Index_Upto_April23__1___1[Sector]="Rural+Urban") * (All_India_Index_Upto_April23__1___1[Date]=EDATE(A5,-12)), 0 ) ), "")} -> 127.3 | F5: =IF(OR(E5="",D5=""),NA(),(D5/E5)-1) -> 0.029850746 | G5: =IF(A5<DATE(2020,3,1), "Pre-COVID", IF(A5<DATE(2022,4,1), "COVID", "Post-COVID" ) ) -> Pre-COVID | I5: Period | J5: Avg Health Inflation % | L5: Period | M5: Avg Other Inflation % | O5: {=IFERROR( AVERAGE( INDEX(All_India_Index_Upto_April23__1___1[Cereals and products], MATCH(1,(All_India_Index_Upto_April23__1___1[Date]=$A5)* (All_India_Index_Upto_April23__1___1[Sector]="Rural+Urban"),0)), INDEX(All_India_Index_Upto_April23__1___1[Meat and fish], MATCH(1,(All_India_Index_Upto_April23__1___1[Date]=$A5)* (All_India_Index_Upto_April23__1___1[Sector]="Rural+Urban"),0)), INDEX(All_India_Index_Upto_April23__1___1[Egg], MATCH(1,(All_India_Index_Upto_April23__1___1[Date]=$A5)* (All_India_Index_Upto_April23__1___1[Sector]="Rural+Urban"),0)), INDEX(All_India_Index_Upto_April23__1___1[Milk and products], MATCH(1,(All_India_Index_Upto_April23__1___1[Date]=$A5)* (All_India_Index_Upto_April23__1___1[Sector]="Rural+Urban"),0)), INDEX(All_India_Index_Upto_April23__1___1[Oils and fats], MATCH(1,(All_India_Index_Upto_April23__1___1[Date]=$A5)* (All_India_Index_Upto_April23__1___1[Sector]="Rural+Urban"),0)), INDEX(All_India_Index_Upto_April23__1___1[Fruits], MATCH(1,(All_India_Index_Upto_April23__1___1[Date]=$A5)* (All_India_Index_Upto_April23__1___1[Sector]="Rural+Urban"),0)), INDEX(All_India_Index_Upto_April23__1___1[Vegetables], MATCH(1,(All_India_Index_Upto_April23__1___1[Date]=$A5)* (All_India_Index_Upto_April23__1___1[Sector]="Rural+Urban"),0)), INDEX(All_India_Index_Upto_April23__1___1[Pulses and products], MATCH(1,(All_India_Index_Upto_April23__1___1[Date]=$A5)* (All_India_Index_Upto_April23__1___1[Sector]="Rural+Urban"),0)), INDEX(All_India_Index_Upto_April23__1___1[Sugar and Confectionery], MATCH(1,(All_India_Index_Upto_April23__1___1[Date]=$A5)* (All_India_Index_Upto_April23__1___1[Sector]="Rural+Urban"),0)), INDEX(All_India_Index_Upto_April23__1___1[Spices], MATCH(1,(All_India_Index_Upto_April23__1___1[Date]=$A5)* (All_India_Index_Upto_April23__1___1[Sector]="Rural+Urban"),0)), INDEX(All_India_Index_Upto_April23__1___1[Non-alcoholic beverages], MATCH(1,(All_India_Index_Upto_April23__1___1[Date]=$A5)* (All_India_Index_Upto_April23__1___1[Sector]="Rural+Urban"),0)), INDEX(All_India_Index_Upto_April23__1___1[Prepared meals, snacks, sweets etc.], MATCH(1,(All_India_Index_Upto_April23__1___1[Date]=$A5)* (All_India_Index_Upto_April23__1___1[Sector]="Rural+Urban"),0)) ), "")} -> 132.075 | P5: {=IFERROR( AVERAGE( INDEX(All_India_Index_Upto_April23__1___1[Cereals and products], MATCH(1,(All_India_Index_Upto_April23__1___1[Date]=EDATE($A5,-12))* (All_India_Index_Upto_April23__1___1[Sector]="Rural+Urban"),0)), INDEX(All_India_Index_Upto_April23__1___1[Meat and fish], MATCH(1,(All_India_Index_Upto_April23__1___1[Date]=EDATE($A5,-12))* (All_India_Index_Upto_April23__1___1[Sector]="Rural+Urban"),0)), INDEX(All_India_Index_Upto_April23__1___1[Egg], MATCH(1,(All_India_Index_Upto_April23__1___1[Date]=EDATE($A5,-12))* (All_India_Index_Upto_April23__1___1[Sector]="Rural+Urban"),0)), INDEX(All_India_Index_Upto_April23__1___1[Milk and products], MATCH(1,(All_India_Index_Upto_April23__1___1[Date]=EDATE($A5,-12))* (All_India_Index_Upto_April23__1___1[Sector]="Rural+Urban"),0)), INDEX(All_India_Index_Upto_April23__1___1[Oils and fats], MATCH(1,(All_India_Index_Upto_April23__1___1[Date]=EDATE($A5,-12))* (All_India_Index_Upto_April23__1___1[Sector]="Rural+Urban"),0)), INDEX(All_India_Index_Upto_April23__1___1[Fruits], MATCH(1,(All_India_Index_Upto_April23__1___1[Date]=EDATE($A5,-12))* (All_India_Index_Upto_April23__1___1[Sector]="Rural+Urban"),0)), INDEX(All_India_Index_Upto_April23__1___1[Vegetables], MATCH(1,(All_India_Index_Upto_April23__1___1[Date]=EDATE($A5,-12))* (All_India_Index_Upto_April23__1___1[Sector]="Rural+Urban"),0)), INDEX(All_India_Index_Upto_April23__1___1[Pulses and products], MATCH(1,(All_India_Index_Upto_April23__1___1[Date]=EDATE($A5,-12))* (All_India_Index_Upto_April23__1___1[Sector]="Rural+Urban"),0)), INDEX(All_India_Index_Upto_April23__1___1[Sugar and Confectionery], MATCH(1,(All_India_Index_Upto_April23__1___1[Date]=EDATE($A5,-12))* (All_India_Index_Upto_April23__1___1[Sector]="Rural+Urban"),0)), INDEX(All_India_Index_Upto_April23__1___1[Spices], MATCH(1,(All_India_Index_Upto_April23__1___1[Date]=EDATE($A5,-12))* (All_India_Index_Upto_April23__1___1[Sector]="Rural+Urban"),0)), INDEX(All_India_Index_Upto_April23__1___1[Non-alcoholic beverages], MATCH(1,(All_India_Index_Upto_April23__1___1[Date]=EDATE($A5,-12))* (All_India_Index_Upto_April23__1___1[Sector]="Rural+Urban"),0)), INDEX(All_India_Index_Upto_April23__1___1[Prepared meals, snacks, sweets etc.], MATCH(1,(All_India_Index_Upto_April23__1___1[Date]=EDATE($A5,-12))* (All_India_Index_Upto_April23__1___1[Sector]="Rural+Urban"),0)) ), "")} -> 130.79167 | Q5: =IFERROR((O5-P5)/P5,"") -> 0.0098120421 | R5: =IF(A5<DATE(2020,3,1), "Pre-COVID", IF(A5<DATE(2022,4,1), "COVID", "Post-COVID" ) ) -> Pre-COVID | T5: {=IFERROR( INDEX( All_India_Index_Upto_April23__1___1[Health], MATCH( 1, (All_India_Index_Upto_April23__1___1[Date]=$A5) * (All_India_Index_Upto_April23__1___1[Sector]="Rural+Urban"), 0 ) ), "")} -> 128.1 | U5: {=IFERROR( INDEX( All_India_Index_Upto_April23__1___1[Health], MATCH( 1, (All_India_Index_Upto_April23__1___1[Date]=EDATE($A5,-12)) * (All_India_Index_Upto_April23__1___1[Sector]="Rural+Urban"), 0 ) ), "")} -> 123.2 | V5: =IFERROR((T5-U5)/U5,"") -> 0.039772727 | W5: =IF(A5<DATE(2020,3,1), "Pre-COVID", IF(A5<DATE(2022,4,1), "COVID", "Post-COVID" ) ) -> Pre-COVID | Y5: {=IFERROR( AVERAGE( INDEX(All_India_Index_Upto_April23__1___1[Pan, tobacco and intoxicants], MATCH(1,(All_India_Index_Upto_April23__1___1[Date]=$A5)* (All_India_Index_Upto_April23__1___1[Sector]="Rural+Urban"),0)), INDEX(All_India_Index_Upto_April23__1___1[Clothing], MATCH(1,(All_India_Index_Upto_April23__1___1[Date]=$A5)* (All_India_Index_Upto_April23__1___1[Sector]="Rural+Urban"),0)), INDEX(All_India_Index_Upto_April23__1___1[Footwear], MATCH(1,(All_India_Index_Upto_April23__1___1[Date]=$A5)* (All_India_Index_Upto_April23__1___1[Sector]="Rural+Urban"),0)), INDEX(All_India_Index_Upto_April23__1___1[Clothing and footwear], MATCH(1,(All_India_Index_Upto_April23__1___1[Date]=$A5)* (All_India_Index_Upto_April23__1___1[Sector]="Rural+Urban"),0)), INDEX(All_India_Index_Upto_April23__1___1[Housing], MATCH(1,(All_India_Index_Upto_April23__1___1[Date]=$A5)* (All_India_Index_Upto_April23__1___1[Sector]="Rural+Urban"),0)), INDEX(All_India_Index_Upto_April23__1___1[Fuel and light], MATCH(1,(All_India_Index_Upto_April23__1___1[Date]=$A5)* (All_India_Index_Upto_April23__1___1[Sector]="Rural+Urban"),0)), INDEX(All_India_Index_Upto_April23__1___1[Household goods and services], MATCH(1,(All_India_Index_Upto_April23__1___1[Date]=$A5)* (All_India_Index_Upto_April23__1___1[Sector]="Rural+Urban"),0)), INDEX(All_India_Index_Upto_April23__1___1[Health], MATCH(1,(All_India_Index_Upto_April23__1___1[Date]=$A5)* (All_India_Index_Upto_April23__1___1[Sector]="Rural+Urban"),0)), INDEX(All_India_Index_Upto_April23__1___1[Transport and communication], MATCH(1,(All_India_Index_Upto_April23__1___1[Date]=$A5)* (All_India_Index_Upto_April23__1___1[Sector]="Rural+Urban"),0)), INDEX(All_India_Index_Upto_April23__1___1[Recreation and amusement], MATCH(1,(All_India_Index_Upto_April23__1___1[Date]=$A5)* (All_India_Index_Upto_April23__1___1[Sector]="Rural+Urban"),0)), INDEX(All_India_Index_Upto_April23__1___1[Education], MATCH(1,(All_India_Index_Upto_April23__1___1[Date]=$A5)* (All_India_Index_Upto_April23__1___1[Sector]="Rural+Urban"),0)), INDEX(All_India_Index_Upto_April23__1___1[Personal care and effects], MATCH(1,(All_India_Index_Upto_April23__1___1[Date]=$A5)* (All_India_Index_Upto_April23__1___1[Sector]="Rural+Urban"),0)), INDEX(All_India_Index_Upto_April23__1___1[Miscellaneous], MATCH(1,(All_India_Index_Upto_April23__1___1[Date]=$A5)* (All_India_Index_Upto_April23__1___1[Sector]="Rural+Urban"),0)) ), "")} -> 130.35 | Z5: {=IFERROR( AVERAGE( INDEX(All_India_Index_Upto_April23__1___1[Pan, tobacco and intoxicants], MATCH(1,(All_India_Index_Upto_April23__1___1[Date]=EDATE($A5,-12))* (All_India_Index_Upto_April23__1___1[Sector]="Rural+Urban"),0)), INDEX(All_India_Index_Upto_April23__1___1[Clothing], MATCH(1,(All_India_Index_Upto_April23__1___1[Date]=EDATE($A5,-12))* (All_India_Index_Upto_April23__1___1[Sector]="Rural+Urban"),0)), INDEX(All_India_Index_Upto_April23__1___1[Footwear], MATCH(1,(All_India_Index_Upto_April23__1___1[Date]=EDATE($A5,-12))* (All_India_Index_Upto_April23__1___1[Sector]="Rural+Urban"),0)), INDEX(All_India_Index_Upto_April23__1___1[Clothing and footwear], MATCH(1,(All_India_Index_Upto_April23__1___1[Date]=EDATE($A5,-12))* (All_India_Index_Upto_April23__1___1[Sector]="Rural+Urban"),0)), INDEX(All_India_Index_Upto_April23__1___1[Housing], MATCH(1,(All_India_Index_Upto_April23__1___1[Date]=EDATE($A5,-12))* (All_India_Index_Upto_April23__1___1[Sector]="Rural+Urban"),0)), INDEX(All_India_Index_Upto_April23__1___1[Fuel and light], MATCH(1,(All_India_Index_Upto_April23__1___1[Date]=EDATE($A5,-12))* (All_India_Index_Upto_April23__1___1[Sector]="Rural+Urban"),0)), INDEX(All_India_Index_Upto_April23__1___1[Household goods and services], MATCH(1,(All_India_Index_Upto_April23__1___1[Date]=EDATE($A5,-12))* (All_India_Index_Upto_April23__1___1[Sector]="Rural+Urban"),0)), INDEX(All_India_Index_Upto_April23__1___1[Health], MATCH(1,(All_India_Index_Upto_April23__1___1[Date]=EDATE($A5,-12))* (All_India_Index_Upto_April23__1___1[Sector]="Rural+Urban"),0)), INDEX(All_India_Index_Upto_April23__1___1[Transport and communication], MATCH(1,(All_India_Index_Upto_April23__1___1[Date]=EDATE($A5,-12))* (All_India_Index_Upto_April23__1___1[Sector]="Rural+Urban"),0)), INDEX(All_India_Index_Upto_April23__1___1[Recreation and amusement], MATCH(1,(All_India_Index_Upto_April23__1___1[Date]=EDATE($A5,-12))* (All_India_Index_Upto_April23__1___1[Sector]="Rural+Urban"),0)), INDEX(All_India_Index_Upto_April23__1___1[Education], MATCH(1,(All_India_Index_Upto_April23__1___1[Date]=EDATE($A5,-12))* (All_India_Index_Upto_April23__1___1[Sector]="Rural+Urban"),0)), INDEX(All_India_Index_Upto_April23__1___1[Personal care and effects], MATCH(1,(All_India_Index_Upto_April23__1___1[Date]=EDATE($A5,-12))* (All_India_Index_Upto_April23__1___1[Sector]="Rural+Urban"),0)), INDEX(All_India_Index_Upto_April23__1___1[Miscellaneous], MATCH(1,(All_India_Index_Upto_April23__1___1[Date]=EDATE($A5,-12))* (All_India_Index_Upto_April23__1___1[Sector]="Rural+Urban"),0)) ), "")} -> 124.69167 | AA5: =IFERROR((Y5-Z5)/Z5,"") -> 0.045378601 | AB5: =IF(A5<DATE(2020,3,1), "Pre-COVID", IF(A5<DATE(2022,4,1), "COVID", "Post-COVID" ) ) -> Pre-COVID | AD5: Other | AE5: 0.045 | AF5: 0.061
A6: 42856 | B6: 2017 | C6: May | D6: {=IFERROR( INDEX( All_India_Index_Upto_April23__1___1[General index], MATCH( 1, (All_India_Index_Upto_April23__1___1[Sector]="Rural+Urban") * (All_India_Index_Upto_April23__1___1[Date]=A6), 0 ) ), "")} -> 131.4 | E6: {=IFERROR( INDEX( All_India_Index_Upto_April23__1___1[General index], MATCH( 1, (All_India_Index_Upto_April23__1___1[Sector]="Rural+Urban") * (All_India_Index_Upto_April23__1___1[Date]=EDATE(A6,-12)), 0 ) ), "")} -> 128.6 | F6: =IF(OR(E6="",D6=""),NA(),(D6/E6)-1) -> 0.021772939 | G6: =IF(A6<DATE(2020,3,1), "Pre-COVID", IF(A6<DATE(2022,4,1), "COVID", "Post-COVID" ) ) -> Pre-COVID | I6: Pre-COVID | J6: =AVERAGEIFS( V:V, W:W, "Pre-COVID" ) -> 0.057610892 | L6: Pre-COVID | M6: =AVERAGEIFS( AA:AA, AB:AB, "Pre-COVID" ) -> 0.045050195 | O6: {=IFERROR( AVERAGE( INDEX(All_India_Index_Upto_April23__1___1[Cereals and products], MATCH(1,(All_India_Index_Upto_April23__1___1[Date]=$A6)* (All_India_Index_Upto_April23__1___1[Sector]="Rural+Urban"),0)), INDEX(All_India_Index_Upto_April23__1___1[Meat and fish], MATCH(1,(All_India_Index_Upto_April23__1___1[Date]=$A6)* (All_India_Index_Upto_April23__1___1[Sector]="Rural+Urban"),0)), INDEX(All_India_Index_Upto_April23__1___1[Egg], MATCH(1,(All_India_Index_Upto_April23__1___1[Date]=$A6)* (All_India_Index_Upto_April23__1___1[Sector]="Rural+Urban"),0)), INDEX(All_India_Index_Upto_April23__1___1[Milk and products], MATCH(1,(All_India_Index_Upto_April23__1___1[Date]=$A6)* (All_India_Index_Upto_April23__1___1[Sector]="Rural+Urban"),0)), INDEX(All_India_Index_Upto_April23__1___1[Oils and fats], MATCH(1,(All_India_Index_Upto_April23__1___1[Date]=$A6)* (All_India_Index_Upto_April23__1___1[Sector]="Rural+Urban"),0)), INDEX(All_India_Index_Upto_April23__1___1[Fruits], MATCH(1,(All_India_Index_Upto_April23__1___1[Date]=$A6)* (All_India_Index_Upto_April23__1___1[Sector]="Rural+Urban"),0)), INDEX(All_India_Index_Upto_April23__1___1[Vegetables], MATCH(1,(All_India_Index_Upto_April23__1___1[Date]=$A6)* (All_India_Index_Upto_April23__1___1[Sector]="Rural+Urban"),0)), INDEX(All_India_Index_Upto_April23__1___1[Pulses and products], MATCH(1,(All_India_Index_Upto_April23__1___1[Date]=$A6)* (All_India_Index_Upto_April23__1___1[Sector]="Rural+Urban"),0)), INDEX(All_India_Index_Upto_April23__1___1[Sugar and Confectionery], MATCH(1,(All_India_Index_Upto_April23__1___1[Date]=$A6)* (All_India_Index_Upto_April23__1___1[Sector]="Rural+Urban"),0)), INDEX(All_India_Index_Upto_April23__1___1[Spices], MATCH(1,(All_India_Index_Upto_April23__1___1[Date]=$A6)* (All_India_Index_Upto_April23__1___1[Sector]="Rural+Urban"),0)), INDEX(All_India_Index_Upto_April23__1___1[Non-alcoholic beverages], MATCH(1,(All_India_Index_Upto_April23__1___1[Date]=$A6)* (All_India_Index_Upto_April23__1___1[Sector]="Rural+Urban"),0)), INDEX(All_India_Index_Upto_April23__1___1[Prepared meals, snacks, sweets etc.], MATCH(1,(All_India_Index_Upto_April23__1___1[Date]=$A6)* (All_India_Index_Upto_April23__1___1[Sector]="Rural+Urban"),0)) ), "")} -> 132.15833 | P6: {=IFERROR( AVERAGE( INDEX(All_India_Index_Upto_April23__1___1[Cereals and products], MATCH(1,(All_India_Index_Upto_April23__1___1[Date]=EDATE($A6,-12))* (All_India_Index_Upto_April23__1___1[Sector]="Rural+Urban"),0)), INDEX(All_India_Index_Upto_April23__1___1[Meat and fish], MATCH(1,(All_India_Index_Upto_April23__1___1[Date]=EDATE($A6,-12))* (All_India_Index_Upto_April23__1___1[Sector]="Rural+Urban"),0)), INDEX(All_India_Index_Upto_April23__1___1[Egg], MATCH(1,(All_India_Index_Upto_April23__1___1[Date]=EDATE($A6,-12))* (All_India_Index_Upto_April23__1___1[Sector]="Rural+Urban"),0)), INDEX(All_India_Index_Upto_April23__1___1[Milk and products], MATCH(1,(All_India_Index_Upto_April23__1___1[Date]=EDATE($A6,-12))* (All_India_Index_Upto_April23__1___1[Sector]="Rural+Urban"),0)), INDEX(All_India_Index_Upto_April23__1___1[Oils and fats], MATCH(1,(All_India_Index_Upto_April23__1___1[Date]=EDATE($A6,-12))* (All_India_Index_Upto_April23__1___1[Sector]="Rural+Urban"),0)), INDEX(All_India_Index_Upto_April23__1___1[Fruits], MATCH(1,(All_India_Index_Upto_April23__1___1[Date]=EDATE($A6,-12))* (All_India_Index_Upto_April23__1___1[Sector]="Rural+Urban"),0)), INDEX(All_India_Index_Upto_April23__1___1[Vegetables], MATCH(1,(All_India_Index_Upto_April23__1___1[Date]=EDATE($A6,-12))* (All_India_Index_Upto_April23__1___1[Sector]="Rural+Urban"),0)), INDEX(All_India_Index_Upto_April23__1___1[Pulses and products], MATCH(1,(All_India_Index_Upto_April23__1___1[Date]=EDATE($A6,-12))* (All_India_Index_Upto_April23__1___1[Sector]="Rural+Urban"),0)), INDEX(All_India_Index_Upto_April23__1___1[Sugar and Confectionery], MATCH(1,(All_India_Index_Upto_April23__1___1[Date]=EDATE($A6,-12))* (All_India_Index_Upto_April23__1___1[Sector]="Rural+Urban"),0)), INDEX(All_India_Index_Upto_April23__1___1[Spices], MATCH(1,(All_India_Index_Upto_April23__1___1[Date]=EDATE($A6,-12))* (All_India_Index_Upto_April23__1___1[Sector]="Rural+Urban"),0)), INDEX(All_India_Index_Upto_April23__1___1[Non-alcoholic beverages], MATCH(1,(All_India_Index_Upto_April23__1___1[Date]=EDATE($A6,-12))* (All_India_Index_Upto_April23__1___1[Sector]="Rural+Urban"),0)), INDEX(All_India_Index_Upto_April23__1___1[Prepared meals, snacks, sweets etc.], MATCH(1,(All_India_Index_Upto_April23__1___1[Date]=EDATE($A6,-12))* (All_India_Index_Upto_April23__1___1[Sector]="Rural+Urban"),0)) ), "")} -> 133.03333 | Q6: =IFERROR((O6-P6)/P6,"") -> -0.0065772989 | R6: =IF(A6<DATE(2020,3,1), "Pre-COVID", IF(A6<DATE(2022,4,1), "COVID", "Post-COVID" ) ) -> Pre-COVID | T6: {=IFERROR( INDEX( All_India_Index_Upto_April23__1___1[Health], MATCH( 1, (All_India_Index_Upto_April23__1___1[Date]=$A6) * (All_India_Index_Upto_April23__1___1[Sector]="Rural+Urban"), 0 ) ), "")} -> 128.4 | U6: {=IFERROR( INDEX( All_India_Index_Upto_April23__1___1[Health], MATCH( 1, (All_India_Index_Upto_April23__1___1[Date]=EDATE($A6,-12)) * (All_India_Index_Upto_April23__1___1[Sector]="Rural+Urban"), 0 ) ), "")} -> 123.7 | V6: =IFERROR((T6-U6)/U6,"") -> 0.03799515 | W6: =IF(A6<DATE(2020,3,1), "Pre-COVID", IF(A6<DATE(2022,4,1), "COVID", "Post-COVID" ) ) -> Pre-COVID | Y6: {=IFERROR( AVERAGE( INDEX(All_India_Index_Upto_April23__1___1[Pan, tobacco and intoxicants], MATCH(1,(All_India_Index_Upto_April23__1___1[Date]=$A6)* (All_India_Index_Upto_April23__1___1[Sector]="Rural+Urban"),0)), INDEX(All_India_Index_Upto_April23__1___1[Clothing], MATCH(1,(All_India_Index_Upto_April23__1___1[Date]=$A6)* (All_India_Index_Upto_April23__1___1[Sector]="Rural+Urban"),0)), INDEX(All_India_Index_Upto_April23__1___1[Footwear], MATCH(1,(All_India_Index_Upto_April23__1___1[Date]=$A6)* (All_India_Index_Upto_April23__1___1[Sector]="Rural+Urban"),0)), INDEX(All_India_Index_Upto_April23__1___1[Clothing and footwear], MATCH(1,(All_India_Index_Upto_April23__1___1[Date]=$A6)* (All_India_Index_Upto_April23__1___1[Sector]="Rural+Urban"),0)), INDEX(All_India_Index_Upto_April23__1___1[Housing], MATCH(1,(All_India_Index_Upto_April23__1___1[Date]=$A6)* (All_India_Index_Upto_April23__1___1[Sector]="Rural+Urban"),0)), INDEX(All_India_Index_Upto_April23__1___1[Fuel and light], MATCH(1,(All_India_Index_Upto_April23__1___1[Date]=$A6)* (All_India_Index_Upto_April23__1___1[Sector]="Rural+Urban"),0)), INDEX(All_India_Index_Upto_April23__1___1[Household goods and services], MATCH(1,(All_India_Index_Upto_April23__1___1[Date]=$A6)* (All_India_Index_Upto_April23__1___1[Sector]="Rural+Urban"),0)), INDEX(All_India_Index_Upto_April23__1___1[Health], MATCH(1,(All_India_Index_Upto_April23__1___1[Date]=$A6)* (All_India_Index_Upto_April23__1___1[Sector]="Rural+Urban"),0)), INDEX(All_India_Index_Upto_April23__1___1[Transport and communication], MATCH(1,(All_India_Index_Upto_April23__1___1[Date]=$A6)* (All_India_Index_Upto_April23__1___1[Sector]="Rural+Urban"),0)), INDEX(All_India_Index_Upto_April23__1___1[Recreation and amusement], MATCH(1,(All_India_Index_Upto_April23__1___1[Date]=$A6)* (All_India_Index_Upto_April23__1___1[Sector]="Rural+Urban"),0)), INDEX(All_India_Index_Upto_April23__1___1[Education], MATCH(1,(All_India_Index_Upto_April23__1___1[Date]=$A6)* (All_India_Index_Upto_April23__1___1[Sector]="Rural+Urban"),0)), INDEX(All_India_Index_Upto_April23__1___1[Personal care and effects], MATCH(1,(All_India_Index_Upto_April23__1___1[Date]=$A6)* (All_India_Index_Upto_April23__1___1[Sector]="Rural+Urban"),0)), INDEX(All_India_Index_Upto_April23__1___1[Miscellaneous], MATCH(1,(All_India_Index_Upto_April23__1___1[Date]=$A6)* (All_India_Index_Upto_April23__1___1[Sector]="Rural+Urban"),0)) ), "")} -> 130.6 | Z6: {=IFERROR( AVERAGE( INDEX(All_India_Index_Upto_April23__1___1[Pan, tobacco and intoxicants], MATCH(1,(All_India_Index_Upto_April23__1___1[Date]=EDATE($A6,-12))* (All_India_Index_Upto_April23__1___1[Sector]="Rural+Urban"),0)), INDEX(All_India_Index_Upto_April23__1___1[Clothing], MATCH(1,(All_India_Index_Upto_April23__1___1[Date]=EDATE($A6,-12))* (All_India_Index_Upto_April23__1___1[Sector]="Rural+Urban"),0)), INDEX(All_India_Index_Upto_April23__1___1[Footwear], MATCH(1,(All_India_Index_Upto_April23__1___1[Date]=EDATE($A6,-12))* (All_India_Index_Upto_April23__1___1[Sector]="Rural+Urban"),0)), INDEX(All_India_Index_Upto_April23__1___1[Clothing and footwear], MATCH(1,(All_India_Index_Upto_April23__1___1[Date]=EDATE($A6,-12))* (All_India_Index_Upto_April23__1___1[Sector]="Rural+Urban"),0)), INDEX(All_India_Index_Upto_April23__1___1[Housing], MATCH(1,(All_India_Index_Upto_April23__1___1[Date]=EDATE($A6,-12))* (All_India_Index_Upto_April23__1___1[Sector]="Rural+Urban"),0)), INDEX(All_India_Index_Upto_April23__1___1[Fuel and light], MATCH(1,(All_India_Index_Upto_April23__1___1[Date]=EDATE($A6,-12))* (All_India_Index_Upto_April23__1___1[Sector]="Rural+Urban"),0)), INDEX(All_India_Index_Upto_April23__1___1[Household goods and services], MATCH(1,(All_India_Index_Upto_April23__1___1[Date]=EDATE($A6,-12))* (All_India_Index_Upto_April23__1___1[Sector]="Rural+Urban"),0)), INDEX(All_India_Index_Upto_April23__1___1[Health], MATCH(1,(All_India_Index_Upto_April23__1___1[Date]=EDATE($A6,-12))* (All_India_Index_Upto_April23__1___1[Sector]="Rural+Urban"),0)), INDEX(All_India_Index_Upto_April23__1___1[Transport and communication], MATCH(1,(All_India_Index_Upto_April23__1___1[Date]=EDATE($A6,-12))* (All_India_Index_Upto_April23__1___1[Sector]="Rural+Urban"),0)), INDEX(All_India_Index_Upto_April23__1___1[Recreation and amusement], MATCH(1,(All_India_Index_Upto_April23__1___1[Date]=EDATE($A6,-12))* (All_India_Index_Upto_April23__1___1[Sector]="Rural+Urban"),0)), INDEX(All_India_Index_Upto_April23__1___1[Education], MATCH(1,(All_India_Index_Upto_April23__1___1[Date]=EDATE($A6,-12))* (All_India_Index_Upto_April23__1___1[Sector]="Rural+Urban"),0)), INDEX(All_India_Index_Upto_April23__1___1[Personal care and effects], MATCH(1,(All_India_Index_Upto_April23__1___1[Date]=EDATE($A6,-12))* (All_India_Index_Upto_April23__1___1[Sector]="Rural+Urban"),0)), INDEX(All_India_Index_Upto_April23__1___1[Miscellaneous], MATCH(1,(All_India_Index_Upto_April23__1___1[Date]=EDATE($A6,-12))* (All_India_Index_Upto_April23__1___1[Sector]="Rural+Urban"),0)) ), "")} -> 125.26667 | AA6: =IFERROR((Y6-Z6)/Z6,"") -> 0.042575838 | AB6: =IF(A6<DATE(2020,3,1), "Pre-COVID", IF(A6<DATE(2022,4,1), "COVID", "Post-COVID" ) ) -> Pre-COVID
